Workbook
Name \0: #REF!
Name \0: #REF!
Name \0: #REF!
Name \0: #REF!
Name \0: #REF!
Name \0: #REF!
Name \0: #REF!
Name \0: #REF!
Name \0: #REF!
Name \0: #REF!
Name \0: #REF!
Name \0: #REF!
Name \0: #REF!
Name \0: #REF!
Name \0: #REF!
Name \0: #REF!
Name \0: #REF!
Name \0: #REF!
Name \0: #REF!
Name \0: #REF!
Name \0: #REF!
Name \0: #REF!
Name \0: #REF!
Name \0: #REF!
Name \0: #REF!
Name \0: #REF!
Name \0: #REF!
Name \0: #REF!
Name \0: #REF!
Name \0: #REF!
Name \0: #REF!
Name \0: #REF!
Name \0: #REF!
Name \0: #REF!
Name \0: #REF!
Name \0: #REF!
Name \0: #REF!
Name \0: #REF!
Name \0: #REF!
Name \0: #REF!
Name \0: #REF!
Name \0: #REF!
Name \0: #REF!
Name \0: #REF!
Name \0: #REF!
Name \0: #REF!
Name \0: #REF!
Name \0: #REF!
Name \0: #REF!
Name \0: #REF!
Name \0: #REF!
Name \0: #REF!
Name \0: #REF!
Name \0: #REF!
Name \00: #REF!
Name \00: #REF!
Name \00: #REF!
Name \00: #REF!
Name \a: #REF!
Name \a: #REF!

Sheet PLAN AUTORIZADO
C2: PLAN DE INTERVENCIÓN ESPECIFICO
D3: CONTRATO No. | F3: OBJETO: SERVICIO PARA LA OPERACIÓN DE LA MAQUINARIA AMARILLA ADSCRITA A LA DIRECCIÓN DEPARTAMENTAL PARA LA GESTIÓN DEL RIESGO DE DESASTRES PARA LA REDUCCIÓN DEL RIESGO EN LOS VEINTINUEVE (29) MUNICIPIOS DEL DEPARTAMENTO DEL META.
C4: PRESUPUESTO OPERACIÓN MAQUINARIA: | F4: 671921001 | G4: FECHA DE INICIO: | J4: FECHA DIA QUE SE ACTUALIZO:
C5: VALOR TOTAL CONTRATO INCLUYE IVA: | F5: =+F4*1.19 -> 7.9958599e+08 | G5: FECHA TERMINACIÓN: | J5: SUPERVISOR: | N5: APOYO A LA SUPERVISION:
A7: CONTRATO INICIAL
A8: N° PUNTO | B8: MUNICIPIO | C8: ZONA ESPECIFICA | D8: ACCIONES A REALIZAR | E8: RIESGO DE UN POSIBLE DESASTRE NATURAL O CALAMIDAD PUBLICA | F8: HORAS PROYECTADAS | J8: HORAS EJECUTADAS | L8: HORAS PROGRAMADAS | N8: OBSERVACIONES | O8: COORDINADOR DIGERD
F9: TIPO DE MAQUINA | G9: CANT. HORAS | H9: VALOR UNITARIO | I9: VALOR ($) | J9: CANT. HORAS | K9: VALOR ($) | L9: CANT. HORAS | M9: VALOR ($)
A10: 1 | B10: EL CALVARIO | C10: VEREDA EL CARMEN 73°43'48.51"O 4°20'41.81"N | D10: REHABILITACION PUNTOS CRÍTICOS VIA TERCIARIA. | E10: DERRUMBES, AFECTACIÓN DE LA VIA | F10: FUNCIONAMIENTO Y OPERACIÓN DE BULLDOZER SOBRE ORUGA CATERPILLAR D6K XL | G10: 75 | H10: 443300 | I10: =+G10*H10 -> 33247500 | J10: 0 | K10: =+J10*H10 -> 0 | L10: =+G10-J10 -> 75 | M10: =+L10*H10 -> 33247500 | N10: DE LAS 100 HORAS DE BULLDOZER ASIGNADAS AL PUNTO; 75 HORAS SE USARAN PARA LA INTERVENCIÓN, LAS CUALES INCLUYEN EL DESPLAZAMIENTO DE LA MAQUINA DESDE EL PUNTO ACTUAL DE PARQUEO HASTA EL PUNTO DE TRABAJO. LAS 25 HORAS RESTANTES SE DESTINAN PARA QUE EL BULLDOZER SE TRASLADE POR SUS PROPIOS MEDIOS HASTA EL SITIO MONTEREDONDO DONDE SERÁ RECOGIDO POR EL TRACTO CAMIÓN CAMABAJA. UNA VEZ FINALIZA LA INTERVENCIÓN LA MAQUINA UTILIZARA 25 HORAS PARA DESPLAZARCE DESDE EL PUNTO DE TRABAJO HASTA EL PUNTO DE EMBARCACIÓN A LA CAMA BAJA. | Q10: =+G10+G16+G21+G26+G31+G36+G41+G46+G11 -> 100
F11: FUNCIONAMIENTO Y OPERACIÓN DE BULLDOZER SOBRE ORUGA CATERPILLAR D6K XL | G11: 25 | H11: 443300 | I11: =+G11*H11 -> 11082500 | J11: 0 | K11: =+J11*H11 -> 0 | L11: =+G11-J11 -> 25 | M11: =+L11*H11 -> 11082500
F12: FUNCIONAMIENTO Y OPERACIÓN DE EXCAVADORA SOBRE ORUGA LINK-BELT 210 X2 | G12: 0 | H12: 460400 | I12: =+G12*H12 -> 0 | J12: 0 | K12: =+J12*H12 -> 0 | L12: 0 | M12: =+L12*H12 -> 0 | Q12: =+G12+G17+G22+G27+G32+G42+G47+G37 -> 550
F13: FUNCIONAMIENTO Y OPERACIÓN DE VOLQUETA SENCILLA FTR CHEVROLET | G13: 0 | H13: 278400 | I13: =+G13*H13 -> 0 | J13: 0 | K13: =+J13*H13 -> 0 | L13: 0 | M13: =+L13*H13 -> 0 | Q13: =+G13+G18+G23+G28+G33+G38+G43+G48 -> 0
F14: FUNCIONAMIENTO Y OPERACIÓN DE RETROEXCAVADORA CATERPILLAR 416 E | G14: 0 | H14: 325000 | I14: =+G14*H14 -> 0 | J14: 0 | K14: =+J14*H14 -> 0 | L14: 0 | M14: =+L14*H14 -> 0 | Q14: =+G14+G19+G24+G29+G34+G39+G44+G49 -> 0
H15: SUBTOTAL | I15: =SUM(I10:I14) -> 44330000 | K15: =SUM(K10:K14) -> 0 | M15: =SUM(M10:M14) -> 44330000
A16: 2 | B16: GUAMAL | C16: PIO XII 73°48'9.28"O 3°54'14.01"N | D16: DESCOLMATACIÓN, ENCAUZAMIENTO O CONFORMACIÓN DE JARILLONES | E16: DESBORDAMIENTO E INUNDACIÓN | F16: FUNCIONAMIENTO Y OPERACIÓN DE BULLDOZER SOBRE ORUGA CATERPILLAR D6K XL | G16: 0 | H16: 443300 | I16: =+G16*H16 -> 0 | J16: 0 | K16: =+J16*H16 -> 0 | L16: 0 | M16: =+L16*H16 -> 0 | N16: LAS 200 HORAS ASIGNADAS SON INSUFICIENTES PARA ATENDER ADECUADAMENTE LA AFECTACIÓN POR DESBORADAMIENTO E INUNDACIÓN DEL RIO GUAMAL EN EL SECTOR PIO XII, YA QUE SON MÁS DE 2 BRAZOS DEL RÍO QUE ATACAN LA MARGEN IZQUIERDA DEL RÍO GUAMAL LO QUE REQUIERE CONTAR CON HORAS SUFICIENTE PARA EJECUTAR LOS TRABAJOS AGUAS ARRIBA DE MANERA EFICIENTE.
F17: FUNCIONAMIENTO Y OPERACIÓN DE EXCAVADORA SOBRE ORUGA LINK-BELT 210 X2 | G17: 200 | H17: 460400 | I17: =+G17*H17 -> 92080000 | J17: 0 | K17: =+J17*H17 -> 0 | L17: =+G17-J17 -> 200 | M17: =+L17*H17 -> 92080000
F18: FUNCIONAMIENTO Y OPERACIÓN DE VOLQUETA SENCILLA FTR CHEVROLET | G18: 0 | H18: 278400 | I18: =+G18*H18 -> 0 | J18: 0 | K18: =+J18*H18 -> 0 | L18: 0 | M18: =+L18*H18 -> 0
F19: FUNCIONAMIENTO Y OPERACIÓN DE RETROEXCAVADORA CATERPILLAR 416 E | G19: 0 | H19: 325000 | I19: =+G19*H19 -> 0 | J19: 0 | K19: =+J19*H19 -> 0 | L19: 0 | M19: =+L19*H19 -> 0
H20: SUBTOTAL | I20: =SUM(I16:I19) -> 92080000 | K20: =SUM(K16:K19) -> 0 | M20: =SUM(M16:M19) -> 92080000
A21: 3 | B21: GRANADA | C21: PUENTE CAÑO URICHARE 73°43'35.18"O 3°25'3.11"N | D21: DESCOLMATACIÓN, ENCAUZAMIENTO O CONFORMACIÓN DE JARILLONES | E21: DESBORDAMIENTO E INUNDACIÓN | F21: FUNCIONAMIENTO Y OPERACIÓN DE BULLDOZER SOBRE ORUGA CATERPILLAR D6K XL | G21: 0 | H21: 443300 | I21: =+G21*H21 -> 0 | J21: 0 | K21: =+J21*H21 -> 0 | L21: 0 | M21: =+L21*H21 -> 0 | N21: EL MUNICIPIO DE GRANADA REQUIERE HACER CONCERTACIÓN CON EL INVIAS PARA DETERMINAR EL TIPO ESPECÍFICO DE TRABAJO EN LA ZONA DE INFLUENCIA DEL PUENTE
F22: FUNCIONAMIENTO Y OPERACIÓN DE EXCAVADORA SOBRE ORUGA LINK-BELT 210 X2 | G22: 100 | H22: 460400 | I22: =+G22*H22 -> 46040000 | J22: 0 | K22: =+J22*H22 -> 0 | L22: =+G22-J22 -> 100 | M22: =+L22*H22 -> 46040000
F23: FUNCIONAMIENTO Y OPERACIÓN DE VOLQUETA SENCILLA FTR CHEVROLET | G23: 0 | H23: 278400 | I23: =+G23*H23 -> 0 | J23: 0 | K23: =+J23*H23 -> 0 | L23: 0 | M23: =+L23*H23 -> 0
F24: FUNCIONAMIENTO Y OPERACIÓN DE RETROEXCAVADORA CATERPILLAR 416 E | G24: 0 | H24: 325000 | I24: =+G24*H24 -> 0 | J24: 0 | K24: =+J24*H24 -> 0 | L24: 0 | M24: =+L24*H24 -> 0
H25: SUBTOTAL | I25: =SUM(I21:I24) -> 46040000 | K25: =SUM(K21:K24) -> 0 | M25: =SUM(M21:M24) -> 46040000
A26: 4 | B26: VILLAVICENCIO | C26: PALMARITO ARRAYANES 73°19'6.96"O 3°57'54.72"N | D26: DESCOLMATACIÓN, ENCAUZAMIENTO O CONFORMACIÓN DE JARILLONES | E26: DESBORDAMIENTO E INUNDACIÓN | F26: FUNCIONAMIENTO Y OPERACIÓN DE BULLDOZER SOBRE ORUGA CATERPILLAR D6K XL | G26: 0 | H26: 443300 | I26: =+G26*H26 -> 0 | J26: 0 | K26: =+J26*H26 -> 0 | L26: 0 | M26: =+L26*H26 -> 0 | N26: LA MAGNITUD DE AFECTACIÓN DE ESTE PUNTO ES MUY GRANDE POR LO QUE SE REQUIERE INICIAR INTERVENCIÓN EN ÉPOCAS EN LA QUE EL RÍO HAYA BAJADO SU NIVEL
F27: FUNCIONAMIENTO Y OPERACIÓN DE EXCAVADORA SOBRE ORUGA LINK-BELT 210 X2 | G27: 250 | H27: 460400 | I27: =+G27*H27 -> 115100000 | J27: 0 | K27: =+J27*H27 -> 0 | L27: =+G27-J27 -> 250 | M27: =+L27*H27 -> 115100000
F28: FUNCIONAMIENTO Y OPERACIÓN DE VOLQUETA SENCILLA FTR CHEVROLET | G28: 0 | H28: 278400 | I28: =+G28*H28 -> 0 | J28: 0 | K28: =+J28*H28 -> 0 | L28: 0 | M28: =+L28*H28 -> 0
F29: FUNCIONAMIENTO Y OPERACIÓN DE RETROEXCAVADORA CATERPILLAR 416 E | G29: 0 | H29: 325000 | I29: =+G29*H29 -> 0 | J29: 0 | K29: =+J29*H29 -> 0 | L29: 0 | M29: =+L29*H29 -> 0
H30: SUBTOTAL | I30: =SUM(I26:I29) -> 115100000 | K30: =SUM(K26:K29) -> 0 | M30: =SUM(M26:M29) -> 115100000
A31: 5 | F31: FUNCIONAMIENTO Y OPERACIÓN DE BULLDOZER SOBRE ORUGA CATERPILLAR D6K XL | G31: 0 | H31: 443300 | I31: =+G31*H31 -> 0 | J31: 0 | K31: =+J31*H31 -> 0 | L31: 0 | M31: =+L31*H31 -> 0 | N31: INFORMACION ENTREGADA POR RIESGOS MUNICIPAL NO SE HA HECHO VISITA
F32: FUNCIONAMIENTO Y OPERACIÓN DE EXCAVADORA SOBRE ORUGA LINK-BELT 210 X2 | G32: 0 | H32: 460400 | I32: =+G32*H32 -> 0 | J32: 0 | K32: =+J32*H32 -> 0 | L32: =+G32-J32 -> 0 | M32: =+L32*H32 -> 0
F33: FUNCIONAMIENTO Y OPERACIÓN DE VOLQUETA SENCILLA FTR CHEVROLET | G33: 0 | H33: 278400 | I33: =+G33*H33 -> 0 | J33: 0 | K33: =+J33*H33 -> 0 | L33: =+G33-J33 -> 0 | M33: =+L33*H33 -> 0
F34: FUNCIONAMIENTO Y OPERACIÓN DE RETROEXCAVADORA CATERPILLAR 416 E | G34: 0 | H34: 325000 | I34: =+G34*H34 -> 0 | J34: 0 | K34: =+J34*H34 -> 0 | L34: 0 | M34: =+L34*H34 -> 0
H35: SUBTOTAL | I35: =SUM(I31:I34) -> 0 | K35: =SUM(K31:K34) -> 0 | M35: =SUM(M31:M34) -> 0
A36: 6 | F36: FUNCIONAMIENTO Y OPERACIÓN DE BULLDOZER SOBRE ORUGA CATERPILLAR D6K XL | G36: 0 | H36: 443300 | I36: =+G36*H36 -> 0 | J36: 0 | K36: =+J36*H36 -> 0 | L36: 0 | M36: =+L36*H36 -> 0 | N36: INFORMACION ENTREGADA POR RIESGOS MUNICIPAL NO SE HA HECHO VISITA
F37: FUNCIONAMIENTO Y OPERACIÓN DE EXCAVADORA SOBRE ORUGA LINK-BELT 210 X2 | G37: 0 | H37: 460400 | I37: =+G37*H37 -> 0 | J37: 0 | K37: =+J37*H37 -> 0 | L37: =+G37-J37 -> 0 | M37: =+L37*H37 -> 0
F38: FUNCIONAMIENTO Y OPERACIÓN DE VOLQUETA SENCILLA FTR CHEVROLET | G38: 0 | H38: 278400 | I38: =+G38*H38 -> 0 | J38: 0 | K38: =+J38*H38 -> 0 | L38: =+G38-J38 -> 0 | M38: =+L38*H38 -> 0
F39: FUNCIONAMIENTO Y OPERACIÓN DE RETROEXCAVADORA CATERPILLAR 416 E | G39: 0 | H39: 325000 | I39: =+G39*H39 -> 0 | J39: 0 | K39: =+J39*H39 -> 0 | L39: 0 | M39: =+L39*H39 -> 0
H40: SUBTOTAL | I40: =SUM(I36:I39) -> 0 | K40: =SUM(K36:K39) -> 0 | M40: =SUM(M36:M39) -> 0
A41: 7 | F41: FUNCIONAMIENTO Y OPERACIÓN DE BULLDOZER SOBRE ORUGA CATERPILLAR D6K XL | G41: 0 | H41: 443300 | I41: =+G41*H41 -> 0 | J41: 0 | K41: =+J41*H41 -> 0 | L41: 0 | M41: =+L41*H41 -> 0 | N41: INFORMACION ENTREGADA POR RIESGOS MUNICIPAL NO SE HA HECHO VISITA
F42: FUNCIONAMIENTO Y OPERACIÓN DE EXCAVADORA SOBRE ORUGA LINK-BELT 210 X2 | G42: 0 | H42: 460400 | I42: =+G42*H42 -> 0 | J42: 0 | K42: =+J42*H42 -> 0 | L42: =+G42-J42 -> 0 | M42: =+L42*H42 -> 0
F43: FUNCIONAMIENTO Y OPERACIÓN DE VOLQUETA SENCILLA FTR CHEVROLET | G43: 0 | H43: 278400 | I43: =+G43*H43 -> 0 | J43: 0 | K43: =+J43*H43 -> 0 | L43: =+G43-J43 -> 0 | M43: =+L43*H43 -> 0
F44: FUNCIONAMIENTO Y OPERACIÓN DE RETROEXCAVADORA CATERPILLAR 416 E | G44: 0 | H44: 325000 | I44: =+G44*H44 -> 0 | J44: 0 | K44: =+J44*H44 -> 0 | L44: 0 | M44: =+L44*H44 -> 0
H45: SUBTOTAL | I45: =SUM(I41:I44) -> 0 | K45: =SUM(K41:K44) -> 0 | M45: =SUM(M41:M44) -> 0
A46: 8 | F46: FUNCIONAMIENTO Y OPERACIÓN DE BULLDOZER SOBRE ORUGA CATERPILLAR D6K XL | G46: 0 | H46: 443300 | I46: =+G46*H46 -> 0 | K46: =+J46*H46 -> 0 | L46: 0 | M46: =+L46*H46 -> 0 | N46: INFORMACION ENTREGADA POR RIESGOS MUNICIPAL NO SE HA HECHO VISITA
F47: FUNCIONAMIENTO Y OPERACIÓN DE EXCAVADORA SOBRE ORUGA LINK-BELT 210 X2 | G47: 0 | H47: 460400 | I47: =+G47*H47 -> 0 | K47: =+J47*H47 -> 0 | L47: =+G47-J47 -> 0 | M47: =+L47*H47 -> 0
F48: FUNCIONAMIENTO Y OPERACIÓN DE VOLQUETA SENCILLA FTR CHEVROLET | G48: 0 | H48: 278400 | I48: =+G48*H48 -> 0 | K48: =+J48*H48 -> 0 | L48: =+G48-J48 -> 0 | M48: =+L48*H48 -> 0
F49: FUNCIONAMIENTO Y OPERACIÓN DE RETROEXCAVADORA CATERPILLAR 416 E | G49: 0 | H49: 325000 | I49: =+G49*H49 -> 0 | K49: =+J49*H49 -> 0 | L49: 0 | M49: =+L49*H49 -> 0
H50: SUBTOTAL | I50: =SUM(I46:I49) -> 0 | K50: =SUM(K46:K49) -> 0 | M50: =SUM(M46:M49) -> 0
A51: 8 | B51: POR PROGRAMAR | C51: POR PROGRAMAR | F51: FUNCIONAMIENTO Y OPERACIÓN DE BULLDOZER SOBRE ORUGA CATERPILLAR D6K XL | G51: 0 | H51: 443300 | I51: =+G51*H51 -> 0 | K51: =+J51*H51 -> 0 | M51: =+L51*H51 -> 0 | N51: INFORMACION ENTREGADA POR RIESGOS MUNICIPAL NO SE HA HECHO VISITA
F52: FUNCIONAMIENTO Y OPERACIÓN DE EXCAVADORA SOBRE ORUGA LINK-BELT 210 X2 | G52: 0 | H52: 460400 | I52: =+G52*H52 -> 0 | K52: =+J52*H52 -> 0 | M52: =+L52*H52 -> 0
F53: FUNCIONAMIENTO Y OPERACIÓN DE VOLQUETA SENCILLA FTR CHEVROLET | G53: 0 | H53: 278400 | I53: =+G53*H53 -> 0 | K53: =+J53*H53 -> 0 | M53: =+L53*H53 -> 0
F54: FUNCIONAMIENTO Y OPERACIÓN DE RETROEXCAVADORA CATERPILLAR 416 E | G54: 0 | H54: 325000 | I54: =+G54*H54 -> 0 | K54: =+J54*H54 -> 0 | M54: =+L54*H54 -> 0
H55: SUBTOTAL | I55: =SUM(I51:I54) -> 0 | K55: =SUM(K51:K54) -> 0 | M55: =SUM(M51:M54) -> 0
A56: FUNCIONAMIENTO Y OPERACIÓN DE TRACTO-CAMIÓN | G56: 62 | H56: 450000 | I56: =+H56*G56 -> 27900000 | J56: 0 | K56: =+J56*H56 -> 0 | L56: =+G56-J56 -> 62 | M56: =+L56*H56 -> 27900000
A57: FUNCIONAMIENTO DE CAMIONETA BT50 | G57: 30 | H57: 287000 | I57: =+H57*G57 -> 8610000 | J57: 0 | K57: =+J57*H57 -> 0 | L57: =+G57-J57 -> 30 | M57: =+L57*H57 -> 8610000
A58: IMPREVISTOS Y EVENTUALIDADES | G58: 2 | H58: 33600000 | I58: =+H58*G58 -> 67200000 | J58: 0 | K58: =+J58*H58 -> 0 | L58: =+G58-J58 -> 2 | M58: =+L58*H58 -> 67200000
H59: SUBTOTAL | I59: =SUM(I56:I58) -> 103710000 | K59: =SUM(K56:K58) -> 0 | M59: =SUM(M56:M58) -> 103710000
A60: SUBTOTAL | I60: =+I59+I15+I25+I35+I30+I20+I40+I45+I50+I55 -> 401260000 | J60: SUBTOTAL | K60: =+K59+K15+K25+K35+K30+K20 -> 0 | L60: SUBTOTAL | M60: =+M59+M15+M25+M35+M30+M20+M40+M45+M50+M55 -> 401260000
A61: TOTAL INCLUYE IVA | I61: =+I60*1.19 -> 477499400 | J61: TOTAL INCLUYE IVA | K61: =+(K60*0.19)+K60 -> 0 | L61: TOTAL INCLUYE IVA | M61: =+(M60*0.19)+M60 -> 477499400
B74: LUIS MIGUEL ANGEL RAMIREZ ROMERO | H74: ARQ. LUZ NELLY MONZÓN DIAZ
B75: REPRESENTANTE LEGAL | H75: DIRECTORA DEPARTAMENTAL PARA LA GESTIÓN DEL RIESGO DE DESASTRES
B76: SERVICIOS MAQUINARIA Y CONSTRUCCIONES S.A.S. "SERVIMACONS S.A.S."
B85: CARMEN LUCIA AGUILAR GOMEZ | H85: XXXXXXXXXXXXXXXXX
B86: DIRECTORA | H86: SUPERVISOR
B87: SERVICIOS MAQUINARIA Y CONSTRUCCIONES S.A.S. "SERVIMACONS S.A.S." | H87: DIRECCION DEPARTAMENTAL PARA LA GESTIÓN DEL RIESGO DE DESASTRES

Sheet PLAN con otrs puntos Vcio
C2: PLAN DE INTERVENCIÓN ESPECIFICO
D3: CONTRATO No. | F3: OBJETO: SERVICIO PARA LA OPERACIÓN DE LA MAQUINARIA AMARILLA ADSCRITA A LA DIRECCIÓN DEPARTAMENTAL PARA LA GESTIÓN DEL RIESGO DE DESASTRES PARA LA REDUCCIÓN DEL RIESGO EN LOS VEINTINUEVE (29) MUNICIPIOS DEL DEPARTAMENTO DEL META.
C4: PRESUPUESTO OPERACIÓN MAQUINARIA: | F4: 671921001 | G4: FECHA DE INICIO: | J4: FECHA DIA QUE SE ACTUALIZO:
C5: VALOR TOTAL CONTRATO INCLUYE IVA: | F5: =+F4*1.19 -> 7.9958599e+08 | G5: FECHA TERMINACIÓN: | J5: SUPERVISOR: | N5: APOYO A LA SUPERVISION:
A7: CONTRATO INICIAL
A8: N° PUNTO | B8: MUNICIPIO | C8: ZONA ESPECIFICA | D8: ACCIONES A REALIZAR | E8: RIESGO DE UN POSIBLE DESASTRE NATURAL O CALAMIDAD PUBLICA | F8: HORAS PROYECTADAS | J8: HORAS EJECUTADAS | L8: HORAS PROGRAMADAS | N8: OBSERVACIONES | O8: COORDINADOR DIGERD
F9: TIPO DE MAQUINA | G9: CANT. HORAS | H9: VALOR UNITARIO | I9: VALOR ($) | J9: CANT. HORAS | K9: VALOR ($) | L9: CANT. HORAS | M9: VALOR ($)
A10: 1 | B10: EL CALVARIO | C10: VEREDA EL CARMEN 73°43'48.51"O 4°20'41.81"N | D10: REHABILITACION PUNTOS CRÍTICOS VIA TERCIARIA. | E10: DERRUMBES, AFECTACIÓN DE LA VIA | F10: FUNCIONAMIENTO Y OPERACIÓN DE BULLDOZER SOBRE ORUGA CATERPILLAR D6K XL | G10: 75 | H10: 443300 | I10: =+G10*H10 -> 33247500 | J10: 0 | K10: =+J10*H10 -> 0 | L10: =+G10-J10 -> 75 | M10: =+L10*H10 -> 33247500 | N10: DE LAS 100 HORAS DE BULLDOZER ASIGNADAS AL PUNTO; 75 HORAS SE USARAN PARA LA INTERVENCIÓN, LAS CUALES INCLUYEN EL DESPLAZAMIENTO DE LA MAQUINA DESDE EL PUNTO ACTUAL DE PARQUEO HASTA EL PUNTO DE TRABAJO. LAS 25 HORAS RESTANTES SE DESTINAN PARA QUE EL BULLDOZER SE TRASLADE POR SUS PROPIOS MEDIOS HASTA EL SITIO MONTEREDONDO DONDE SERÁ RECOGIDO POR EL TRACTO CAMIÓN CAMABAJA. UNA VEZ FINALIZA LA INTERVENCIÓN LA MAQUINA UTILIZARA 25 HORAS PARA DESPLAZARCE DESDE EL PUNTO DE TRABAJO HASTA EL PUNTO DE EMBARCACIÓN A LA CAMA BAJA. | Q10: =+G10+G16+G21+G26+G31+G36+G41+G46+G11 -> 100
F11: FUNCIONAMIENTO Y OPERACIÓN DE BULLDOZER SOBRE ORUGA CATERPILLAR D6K XL | G11: 25 | H11: 443300 | I11: =+G11*H11 -> 11082500 | J11: 0 | K11: =+J11*H11 -> 0 | L11: =+G11-J11 -> 25 | M11: =+L11*H11 -> 11082500
F12: FUNCIONAMIENTO Y OPERACIÓN DE EXCAVADORA SOBRE ORUGA LINK-BELT 210 X2 | G12: 0 | H12: 460400 | I12: =+G12*H12 -> 0 | J12: 0 | K12: =+J12*H12 -> 0 | L12: 0 | M12: =+L12*H12 -> 0 | Q12: =+G12+G17+G22+G27+G32+G42+G47+G37 -> 867
F13: FUNCIONAMIENTO Y OPERACIÓN DE VOLQUETA SENCILLA FTR CHEVROLET | G13: 0 | H13: 278400 | I13: =+G13*H13 -> 0 | J13: 0 | K13: =+J13*H13 -> 0 | L13: 0 | M13: =+L13*H13 -> 0 | Q13: =+G13+G18+G23+G28+G33+G38+G43+G48 -> 150
F14: FUNCIONAMIENTO Y OPERACIÓN DE RETROEXCAVADORA CATERPILLAR 416 E | G14: 0 | H14: 325000 | I14: =+G14*H14 -> 0 | J14: 0 | K14: =+J14*H14 -> 0 | L14: 0 | M14: =+L14*H14 -> 0 | Q14: =+G14+G19+G24+G29+G34+G39+G44+G49 -> 0
H15: SUBTOTAL | I15: =SUM(I10:I14) -> 44330000 | K15: =SUM(K10:K14) -> 0 | M15: =SUM(M10:M14) -> 44330000
A16: 2 | B16: GUAMAL | C16: PIO XII 73°48'9.28"O 3°54'14.01"N | D16: DESCOLMATACIÓN, ENCAUZAMIENTO O CONFORMACIÓN DE JARILLONES | E16: DESBORDAMIENTO E INUNDACIÓN | F16: FUNCIONAMIENTO Y OPERACIÓN DE BULLDOZER SOBRE ORUGA CATERPILLAR D6K XL | G16: 0 | H16: 443300 | I16: =+G16*H16 -> 0 | J16: 0 | K16: =+J16*H16 -> 0 | L16: 0 | M16: =+L16*H16 -> 0 | N16: LAS 200 HORAS ASIGNADAS SON INSUFICIENTES PARA ATENDER ADECUADAMENTE LA AFECTACIÓN POR DESBORADAMIENTO E INUNDACIÓN DEL RIO GUAMAL EN EL SECTOR PIO XII, YA QUE SON MÁS DE 2 BRAZOS DEL RÍO QUE ATACAN LA MARGEN IZQUIERDA DEL RÍO GUAMAL LO QUE REQUIERE CONTAR CON HORAS SUFICIENTE PARA EJECUTAR LOS TRABAJOS AGUAS ARRIBA DE MANERA EFICIENTE.
F17: FUNCIONAMIENTO Y OPERACIÓN DE EXCAVADORA SOBRE ORUGA LINK-BELT 210 X2 | G17: 200 | H17: 460400 | I17: =+G17*H17 -> 92080000 | J17: 0 | K17: =+J17*H17 -> 0 | L17: =+G17-J17 -> 200 | M17: =+L17*H17 -> 92080000
F18: FUNCIONAMIENTO Y OPERACIÓN DE VOLQUETA SENCILLA FTR CHEVROLET | G18: 0 | H18: 278400 | I18: =+G18*H18 -> 0 | J18: 0 | K18: =+J18*H18 -> 0 | L18: 0 | M18: =+L18*H18 -> 0
F19: FUNCIONAMIENTO Y OPERACIÓN DE RETROEXCAVADORA CATERPILLAR 416 E | G19: 0 | H19: 325000 | I19: =+G19*H19 -> 0 | J19: 0 | K19: =+J19*H19 -> 0 | L19: 0 | M19: =+L19*H19 -> 0
H20: SUBTOTAL | I20: =SUM(I16:I19) -> 92080000 | K20: =SUM(K16:K19) -> 0 | M20: =SUM(M16:M19) -> 92080000
A21: 3 | B21: GRANADA | C21: PUENTE CAÑO URICHARE 73°43'35.18"O 3°25'3.11"N | D21: DESCOLMATACIÓN, ENCAUZAMIENTO O CONFORMACIÓN DE JARILLONES | E21: DESBORDAMIENTO E INUNDACIÓN | F21: FUNCIONAMIENTO Y OPERACIÓN DE BULLDOZER SOBRE ORUGA CATERPILLAR D6K XL | G21: 0 | H21: 443300 | I21: =+G21*H21 -> 0 | J21: 0 | K21: =+J21*H21 -> 0 | L21: 0 | M21: =+L21*H21 -> 0 | N21: EL MUNICIPIO DE GRANADA REQUIERE HACER CONCERTACIÓN CON EL INVIAS PARA DETERMINAR EL TIPO ESPECÍFICO DE TRABAJO EN LA ZONA DE INFLUENCIA DEL PUENTE
F22: FUNCIONAMIENTO Y OPERACIÓN DE EXCAVADORA SOBRE ORUGA LINK-BELT 210 X2 | G22: 100 | H22: 460400 | I22: =+G22*H22 -> 46040000 | J22: 0 | K22: =+J22*H22 -> 0 | L22: =+G22-J22 -> 100 | M22: =+L22*H22 -> 46040000
F23: FUNCIONAMIENTO Y OPERACIÓN DE VOLQUETA SENCILLA FTR CHEVROLET | G23: 0 | H23: 278400 | I23: =+G23*H23 -> 0 | J23: 0 | K23: =+J23*H23 -> 0 | L23: 0 | M23: =+L23*H23 -> 0
F24: FUNCIONAMIENTO Y OPERACIÓN DE RETROEXCAVADORA CATERPILLAR 416 E | G24: 0 | H24: 325000 | I24: =+G24*H24 -> 0 | J24: 0 | K24: =+J24*H24 -> 0 | L24: 0 | M24: =+L24*H24 -> 0
H25: SUBTOTAL | I25: =SUM(I21:I24) -> 46040000 | K25: =SUM(K21:K24) -> 0 | M25: =SUM(M21:M24) -> 46040000
A26: 4 | B26: VILLAVICENCIO | C26: PALMARITO ARRAYANES 73°19'6.96"O 3°57'54.72"N | D26: DESCOLMATACIÓN, ENCAUZAMIENTO O CONFORMACIÓN DE JARILLONES | E26: DESBORDAMIENTO E INUNDACIÓN | F26: FUNCIONAMIENTO Y OPERACIÓN DE BULLDOZER SOBRE ORUGA CATERPILLAR D6K XL | G26: 0 | H26: 443300 | I26: =+G26*H26 -> 0 | J26: 0 | K26: =+J26*H26 -> 0 | L26: 0 | M26: =+L26*H26 -> 0 | N26: LA MAGNITUD DE AFECTACIÓN DE ESTE PUNTO ES MUY GRANDE POR LO QUE SE REQUIERE INICIAR INTERVENCIÓN EN ÉPOCAS EN LA QUE EL RÍO HAYA BAJADO SU NIVEL
F27: FUNCIONAMIENTO Y OPERACIÓN DE EXCAVADORA SOBRE ORUGA LINK-BELT 210 X2 | G27: 250 | H27: 460400 | I27: =+G27*H27 -> 115100000 | J27: 0 | K27: =+J27*H27 -> 0 | L27: =+G27-J27 -> 250 | M27: =+L27*H27 -> 115100000
F28: FUNCIONAMIENTO Y OPERACIÓN DE VOLQUETA SENCILLA FTR CHEVROLET | G28: 0 | H28: 278400 | I28: =+G28*H28 -> 0 | J28: 0 | K28: =+J28*H28 -> 0 | L28: 0 | M28: =+L28*H28 -> 0
F29: FUNCIONAMIENTO Y OPERACIÓN DE RETROEXCAVADORA CATERPILLAR 416 E | G29: 0 | H29: 325000 | I29: =+G29*H29 -> 0 | J29: 0 | K29: =+J29*H29 -> 0 | L29: 0 | M29: =+L29*H29 -> 0
H30: SUBTOTAL | I30: =SUM(I26:I29) -> 115100000 | K30: =SUM(K26:K29) -> 0 | M30: =SUM(M26:M29) -> 115100000
A31: 5 | B31: VILLAVICENCIO | C31: VEREDA LA ARGENTINA | D31: DESCOLMATACIÓN, ENCAUZAMIENTO O CONFORMACIÓN DE JARILLONES | E31: DESBORDAMIENTO E INUNDACIÓN | F31: FUNCIONAMIENTO Y OPERACIÓN DE BULLDOZER SOBRE ORUGA CATERPILLAR D6K XL | G31: 0 | H31: 443300 | I31: =+G31*H31 -> 0 | J31: 0 | K31: =+J31*H31 -> 0 | L31: 0 | M31: =+L31*H31 -> 0 | N31: INFORMACION ENTREGADA POR RIESGOS MUNICIPAL NO SE HA HECHO VISITA
F32: FUNCIONAMIENTO Y OPERACIÓN DE EXCAVADORA SOBRE ORUGA LINK-BELT 210 X2 | G32: 57 | H32: 460400 | I32: =+G32*H32 -> 26242800 | J32: 0 | K32: =+J32*H32 -> 0 | L32: =+G32-J32 -> 57 | M32: =+L32*H32 -> 26242800
F33: FUNCIONAMIENTO Y OPERACIÓN DE VOLQUETA SENCILLA FTR CHEVROLET | G33: 75 | H33: 278400 | I33: =+G33*H33 -> 20880000 | J33: 0 | K33: =+J33*H33 -> 0 | L33: =+G33-J33 -> 75 | M33: =+L33*H33 -> 20880000
F34: FUNCIONAMIENTO Y OPERACIÓN DE RETROEXCAVADORA CATERPILLAR 416 E | G34: 0 | H34: 325000 | I34: =+G34*H34 -> 0 | J34: 0 | K34: =+J34*H34 -> 0 | L34: 0 | M34: =+L34*H34 -> 0
H35: SUBTOTAL | I35: =SUM(I31:I34) -> 47122800 | K35: =SUM(K31:K34) -> 0 | M35: =SUM(M31:M34) -> 47122800
A36: 6 | B36: VILLAVICENCIO | C36: QUINTAS DEL LLANO | D36: DESCOLMATACIÓN, ENCAUZAMIENTO O CONFORMACIÓN DE JARILLONES | E36: DESBORDAMIENTO E INUNDACIÓN | F36: FUNCIONAMIENTO Y OPERACIÓN DE BULLDOZER SOBRE ORUGA CATERPILLAR D6K XL | G36: 0 | H36: 443300 | I36: =+G36*H36 -> 0 | J36: 0 | K36: =+J36*H36 -> 0 | L36: 0 | M36: =+L36*H36 -> 0 | N36: INFORMACION ENTREGADA POR RIESGOS MUNICIPAL NO SE HA HECHO VISITA
F37: FUNCIONAMIENTO Y OPERACIÓN DE EXCAVADORA SOBRE ORUGA LINK-BELT 210 X2 | G37: 100 | H37: 460400 | I37: =+G37*H37 -> 46040000 | J37: 0 | K37: =+J37*H37 -> 0 | L37: =+G37-J37 -> 100 | M37: =+L37*H37 -> 46040000
F38: FUNCIONAMIENTO Y OPERACIÓN DE VOLQUETA SENCILLA FTR CHEVROLET | G38: 75 | H38: 278400 | I38: =+G38*H38 -> 20880000 | J38: 0 | K38: =+J38*H38 -> 0 | L38: =+G38-J38 -> 75 | M38: =+L38*H38 -> 20880000
F39: FUNCIONAMIENTO Y OPERACIÓN DE RETROEXCAVADORA CATERPILLAR 416 E | G39: 0 | H39: 325000 | I39: =+G39*H39 -> 0 | J39: 0 | K39: =+J39*H39 -> 0 | L39: 0 | M39: =+L39*H39 -> 0
H40: SUBTOTAL | I40: =SUM(I36:I39) -> 66920000 | K40: =SUM(K36:K39) -> 0 | M40: =SUM(M36:M39) -> 66920000
A41: 7 | B41: VILLAVICENCIO | C41: BRISAS DE APIAY | D41: DESCOLMATACIÓN, ENCAUZAMIENTO O CONFORMACIÓN DE JARILLONES | E41: DESBORDAMIENTO E INUNDACIÓN | F41: FUNCIONAMIENTO Y OPERACIÓN DE BULLDOZER SOBRE ORUGA CATERPILLAR D6K XL | G41: 0 | H41: 443300 | I41: =+G41*H41 -> 0 | J41: 0 | K41: =+J41*H41 -> 0 | L41: 0 | M41: =+L41*H41 -> 0 | N41: INFORMACION ENTREGADA POR RIESGOS MUNICIPAL NO SE HA HECHO VISITA
F42: FUNCIONAMIENTO Y OPERACIÓN DE EXCAVADORA SOBRE ORUGA LINK-BELT 210 X2 | G42: 80 | H42: 460400 | I42: =+G42*H42 -> 36832000 | J42: 0 | K42: =+J42*H42 -> 0 | L42: =+G42-J42 -> 80 | M42: =+L42*H42 -> 36832000
F43: FUNCIONAMIENTO Y OPERACIÓN DE VOLQUETA SENCILLA FTR CHEVROLET | G43: 0 | H43: 278400 | I43: =+G43*H43 -> 0 | J43: 0 | K43: =+J43*H43 -> 0 | L43: =+G43-J43 -> 0 | M43: =+L43*H43 -> 0
F44: FUNCIONAMIENTO Y OPERACIÓN DE RETROEXCAVADORA CATERPILLAR 416 E | G44: 0 | H44: 325000 | I44: =+G44*H44 -> 0 | J44: 0 | K44: =+J44*H44 -> 0 | L44: 0 | M44: =+L44*H44 -> 0
H45: SUBTOTAL | I45: =SUM(I41:I44) -> 36832000 | K45: =SUM(K41:K44) -> 0 | M45: =SUM(M41:M44) -> 36832000
A46: 8 | B46: VILLAVICENCIO | C46: VEREDA SAN JUAN BOSCO | D46: DESCOLMATACIÓN, ENCAUZAMIENTO O CONFORMACIÓN DE JARILLONES | E46: DESBORDAMIENTO E INUNDACIÓN | F46: FUNCIONAMIENTO Y OPERACIÓN DE BULLDOZER SOBRE ORUGA CATERPILLAR D6K XL | G46: 0 | H46: 443300 | I46: =+G46*H46 -> 0 | K46: =+J46*H46 -> 0 | L46: 0 | M46: =+L46*H46 -> 0 | N46: INFORMACION ENTREGADA POR RIESGOS MUNICIPAL NO SE HA HECHO VISITA
F47: FUNCIONAMIENTO Y OPERACIÓN DE EXCAVADORA SOBRE ORUGA LINK-BELT 210 X2 | G47: 80 | H47: 460400 | I47: =+G47*H47 -> 36832000 | K47: =+J47*H47 -> 0 | L47: =+G47-J47 -> 80 | M47: =+L47*H47 -> 36832000
F48: FUNCIONAMIENTO Y OPERACIÓN DE VOLQUETA SENCILLA FTR CHEVROLET | G48: 0 | H48: 278400 | I48: =+G48*H48 -> 0 | K48: =+J48*H48 -> 0 | L48: =+G48-J48 -> 0 | M48: =+L48*H48 -> 0
F49: FUNCIONAMIENTO Y OPERACIÓN DE RETROEXCAVADORA CATERPILLAR 416 E | G49: 0 | H49: 325000 | I49: =+G49*H49 -> 0 | K49: =+J49*H49 -> 0 | L49: 0 | M49: =+L49*H49 -> 0
H50: SUBTOTAL | I50: =SUM(I46:I49) -> 36832000 | K50: =SUM(K46:K49) -> 0 | M50: =SUM(M46:M49) -> 36832000
A51: 8 | B51: POR PROGRAMAR | C51: POR PROGRAMAR | D51: DESCOLMATACIÓN, ENCAUZAMIENTO O CONFORMACIÓN DE JARILLONES | E51: DESBORDAMIENTO E INUNDACIÓN | F51: FUNCIONAMIENTO Y OPERACIÓN DE BULLDOZER SOBRE ORUGA CATERPILLAR D6K XL | G51: 0 | H51: 443300 | I51: =+G51*H51 -> 0 | K51: =+J51*H51 -> 0 | M51: =+L51*H51 -> 0 | N51: INFORMACION ENTREGADA POR RIESGOS MUNICIPAL NO SE HA HECHO VISITA
F52: FUNCIONAMIENTO Y OPERACIÓN DE EXCAVADORA SOBRE ORUGA LINK-BELT 210 X2 | G52: =990-867 -> 123 | H52: 460400 | I52: =+G52*H52 -> 56629200 | K52: =+J52*H52 -> 0 | M52: =+L52*H52 -> 0
F53: FUNCIONAMIENTO Y OPERACIÓN DE VOLQUETA SENCILLA FTR CHEVROLET | G53: 0 | H53: 278400 | I53: =+G53*H53 -> 0 | K53: =+J53*H53 -> 0 | M53: =+L53*H53 -> 0
F54: FUNCIONAMIENTO Y OPERACIÓN DE RETROEXCAVADORA CATERPILLAR 416 E | G54: 81 | H54: 325000 | I54: =+G54*H54 -> 26325000 | K54: =+J54*H54 -> 0 | M54: =+L54*H54 -> 0
H55: SUBTOTAL | I55: =SUM(I51:I54) -> 82954200 | K55: =SUM(K51:K54) -> 0 | M55: =SUM(M51:M54) -> 0
A56: FUNCIONAMIENTO Y OPERACIÓN DE TRACTO-CAMIÓN | G56: 62 | H56: 450000 | I56: =+H56*G56 -> 27900000 | J56: 0 | K56: =+J56*H56 -> 0 | L56: =+G56-J56 -> 62 | M56: =+L56*H56 -> 27900000
A57: FUNCIONAMIENTO DE CAMIONETA BT50 | G57: 30 | H57: 287000 | I57: =+H57*G57 -> 8610000 | J57: 0 | K57: =+J57*H57 -> 0 | L57: =+G57-J57 -> 30 | M57: =+L57*H57 -> 8610000
A58: IMPREVISTOS Y EVENTUALIDADES | G58: 2 | H58: 33600000 | I58: =+H58*G58 -> 67200000 | J58: 0 | K58: =+J58*H58 -> 0 | L58: =+G58-J58 -> 2 | M58: =+L58*H58 -> 67200000
H59: SUBTOTAL | I59: =SUM(I56:I58) -> 103710000 | K59: =SUM(K56:K58) -> 0 | M59: =SUM(M56:M58) -> 103710000
A60: SUBTOTAL | I60: =+I59+I15+I25+I35+I30+I20+I40+I45+I50+I55 -> 671921000 | J60: SUBTOTAL | K60: =+K59+K15+K25+K35+K30+K20 -> 0 | L60: SUBTOTAL | M60: =+M59+M15+M25+M35+M30+M20+M40+M45+M50+M55 -> 588966800
A61: TOTAL INCLUYE IVA | I61: =+I60*1.19 -> 799585990 | J61: TOTAL INCLUYE IVA | K61: =+(K60*0.19)+K60 -> 0 | L61: TOTAL INCLUYE IVA | M61: =+(M60*0.19)+M60 -> 700870492
B74: LUIS MIGUEL ANGEL RAMIREZ ROMERO | H74: ARQ. LUZ NELLY MONZÓN DIAZ
B75: REPRESENTANTE LEGAL | H75: DIRECTORA DEPARTAMENTAL PARA LA GESTIÓN DEL RIESGO DE DESASTRES
B76: SERVICIOS MAQUINARIA Y CONSTRUCCIONES S.A.S. "SERVIMACONS S.A.S."
B85: CARMEN LUCIA AGUILAR GOMEZ | H85: XXXXXXXXXXXXXXXXX
B86: DIRECTORA | H86: SUPERVISOR
B87: SERVICIOS MAQUINARIA Y CONSTRUCCIONES S.A.S. "SERVIMACONS S.A.S." | H87: DIRECCION DEPARTAMENTAL PARA LA GESTIÓN DEL RIESGO DE DESASTRES

Sheet PLAN DE ACCIÓN
C2: PLAN DE INTERVENCIÓN ESPECIFICO
C3: CONTRATO No. | E3: OBJETO:
C4: PRESUPUESTO OPERACIÓN MAQUINARIA: | F4: 671921001 | G4: FECHA DE INICIO: | I4: 45755 | J4: SUPERVISOR:
C5: VALOR TOTAL CONTRATO INCLUYE IVA: | F5: =+F4*1.19 -> 7.9958599e+08 | G5: FECHA TERMINACIÓN: | I5: 45815 | J5: APOYO A LA SUPERVISIÓN: | N5: APOYO A LA SUPERVISION:
G6: FECHA DE ACTUALIZACIÓN: | I6: 45858
A8: CONTRATO INICIAL
A9: N° PUNTO | B9: MUNICIPIO | C9: ZONA ESPECIFICA | D9: ACCIONES A REALIZAR | E9: RIESGO DE UN POSIBLE DESASTRE NATURAL O CALAMIDAD PUBLICA | F9: HORAS PROYECTADAS | J9: HORAS EJECUTADAS | L9: HORAS POR EJECUTAR | N9: OBSERVACIONES | O9: COORDINADOR DIGERD
F10: TIPO DE MAQUINA | G10: CANT. HORAS | H10: VALOR UNITARIO | I10: VALOR ($) | J10: CANT. HORAS | K10: VALOR ($) | L10: CANT. HORAS | M10: VALOR ($)
A11: 1 | B11: EL CALVARIO | C11: VEREDA EL CARMEN Y VEREDA SAN BERNARDO 73°43'48.51"O 4°20'41.81"N | D11: REHABILITACION PUNTOS CRÍTICOS VIA TERCIARIA. | E11: DERRUMBES, AFECTACIÓN DE LA VIA | F11: FUNCIONAMIENTO Y OPERACIÓN DE BULLDOZER SOBRE ORUGA CATERPILLAR D6K XL | G11: 0 | H11: 0 | I11: =+G11*H11 -> 0 | J11: 0 | K11: =+J11*H11 -> 0 | L11: =+G11-J11 -> 0 | M11: =+L11*H11 -> 0 | N11: DE LAS 100 HORAS DE BULLDOZER ASIGNADAS AL PUNTO; 75 HORAS SE USARAN PARA LA INTERVENCIÓN, LAS CUALES INCLUYEN EL DESPLAZAMIENTO DE LA MAQUINA DESDE EL PUNTO ACTUAL DE PARQUEO HASTA EL PUNTO DE TRABAJO. LAS 25 HORAS RESTANTES SE DESTINAN PARA QUE EL BULLDOZER SE TRASLADE POR SUS PROPIOS MEDIOS HASTA EL SITIO MONTEREDONDO DONDE SERÁ RECOGIDO POR EL TRACTO CAMIÓN CAMABAJA. UNA VEZ FINALIZA LA INTERVENCIÓN LA MAQUINA UTILIZARA 25 HORAS PARA DESPLAZARCE DESDE EL PUNTO DE TRABAJO HASTA EL PUNTO DE EMBARCACIÓN A LA CAMA BAJA.
F12: FUNCIONAMIENTO Y OPERACIÓN DE EXCAVADORA SOBRE ORUGA LINK-BELT 210 X2 | G12: 0 | H12: 0 | I12: =+G12*H12 -> 0 | J12: 0 | K12: =+J12*H12 -> 0 | L12: 0 | M12: =+L12*H12 -> 0
F13: FUNCIONAMIENTO Y OPERACIÓN DE VOLQUETA SENCILLA FTR CHEVROLET | G13: 0 | H13: 0 | I13: =+G13*H13 -> 0 | J13: 0 | K13: =+J13*H13 -> 0 | L13: 0 | M13: =+L13*H13 -> 0
F14: FUNCIONAMIENTO Y OPERACIÓN DE RETROEXCAVADORA CATERPILLAR 416 E | G14: 0 | H14: 0 | I14: =+G14*H14 -> 0 | J14: 0 | K14: =+J14*H14 -> 0 | L14: 0 | M14: =+L14*H14 -> 0
H15: SUBTOTAL | I15: =SUM(I11:I14) -> 0 | K15: =SUM(K11:K14) -> 0 | M15: =SUM(M11:M14) -> 0
A16: 2 | C16: VIA VILLAVICENCIO - MONFORTH 73°38'26.11"O 4°19'17.70"N | D16: DESCOLMATACIÓN, ENCAUZAMIENTO O CONFORMACIÓN DE JARILLONES | E16: DESBORDAMIENTO E INUNDACIÓN | F16: FUNCIONAMIENTO Y OPERACIÓN DE BULLDOZER SOBRE ORUGA CATERPILLAR D6K XL | H16: 0 | I16: =+G16*H16 -> 0 | J16: 0 | K16: =+J16*H16 -> 0 | L16: =+G16-J16 -> 0 | M16: =+L16*H16 -> 0 | N16: INFORMACION ENTREGADA POR RIESGOS MUNICIPAL NO SE HA HECHO VISITA
F17: FUNCIONAMIENTO Y OPERACIÓN DE EXCAVADORA SOBRE ORUGA LINK-BELT 210 X2 | H17: 0 | I17: =+G17*H17 -> 0 | J17: 0 | K17: =+J17*H17 -> 0 | L17: =+G17-J17 -> 0 | M17: =+L17*H17 -> 0
F18: FUNCIONAMIENTO Y OPERACIÓN DE VOLQUETA SENCILLA FTR CHEVROLET | H18: 0 | I18: =+G18*H18 -> 0 | J18: 0 | K18: =+J18*H18 -> 0 | L18: =+G18-J18 -> 0 | M18: =+L18*H18 -> 0
F19: FUNCIONAMIENTO Y OPERACIÓN DE RETROEXCAVADORA CATERPILLAR 416 E | G19: 0 | H19: 0 | I19: =+G19*H19 -> 0 | J19: 0 | K19: =+J19*H19 -> 0 | L19: =+G19-J19 -> 0 | M19: =+L19*H19 -> 0
H20: SUBTOTAL | I20: =SUM(I16:I19) -> 0 | K20: =SUM(K16:K19) -> 0 | M20: =SUM(M16:M19) -> 0
A21: 3 | B21: GUAMAL | C21: PIO XII 73°48'9.28"O 3°54'14.01"N | D21: DESCOLMATACIÓN, ENCAUZAMIENTO O CONFORMACIÓN DE JARILLONES | E21: DESBORDAMIENTO E INUNDACIÓN | F21: FUNCIONAMIENTO Y OPERACIÓN DE BULLDOZER SOBRE ORUGA CATERPILLAR D6K XL | G21: 0 | H21: 0 | I21: =+G21*H21 -> 0 | J21: 0 | K21: =+J21*H21 -> 0 | L21: 0 | M21: =+L21*H21 -> 0 | N21: LAS 200 HORAS ASIGNADAS SON INSUFICIENTES PARA ATENDER ADECUADAMENTE LA AFECTACIÓN POR DESBORADAMIENTO E INUNDACIÓN DEL RIO GUAMAL EN EL SECTOR PIO XII, YA QUE SON MÁS DE 2 BRAZOS DEL RÍO QUE ATACAN LA MARGEN IZQUIERDA DEL RÍO GUAMAL LO QUE REQUIERE CONTAR CON HORAS SUFICIENTE PARA EJECUTAR LOS TRABAJOS AGUAS ARRIBA DE MANERA EFICIENTE.
F22: FUNCIONAMIENTO Y OPERACIÓN DE EXCAVADORA SOBRE ORUGA LINK-BELT 210 X2 | G22: 130 | H22: 0 | I22: =+G22*H22 -> 0 | J22: 0 | K22: =+J22*H22 -> 0 | L22: 0 | M22: =+L22*H22 -> 0
F23: FUNCIONAMIENTO Y OPERACIÓN DE VOLQUETA SENCILLA FTR CHEVROLET | G23: 0 | H23: 0 | I23: =+G23*H23 -> 0 | J23: 0 | K23: =+J23*H23 -> 0 | L23: 0 | M23: =+L23*H23 -> 0
F24: FUNCIONAMIENTO Y OPERACIÓN DE RETROEXCAVADORA CATERPILLAR 416 E | G24: 0 | H24: 0 | I24: =+G24*H24 -> 0 | J24: 0 | K24: =+J24*H24 -> 0 | L24: 0 | M24: =+L24*H24 -> 0
H25: SUBTOTAL | I25: =SUM(I21:I24) -> 0 | K25: =SUM(K21:K24) -> 0 | M25: =SUM(M21:M24) -> 0
A26: 4 | C26: SECTOR LA ISLA 73°48'54.35"O 3°54'18.38"N 73°49'38.21"O 3°54'34.58"N | D26: DESCOLMATACIÓN, ENCAUZAMIENTO O CONFORMACIÓN DE JARILLONES | E26: DESBORDAMIENTO E INUNDACIÓN | F26: FUNCIONAMIENTO Y OPERACIÓN DE BULLDOZER SOBRE ORUGA CATERPILLAR D6K XL | G26: 0 | H26: 0 | I26: =+G26*H26 -> 0 | J26: 0 | K26: =+J26*H26 -> 0 | L26: 0 | M26: =+L26*H26 -> 0 | N26: LAS 200 HORAS ASIGNADAS SON INSUFICIENTES PARA ATENDER ADECUADAMENTE LA AFECTACIÓN POR DESBORADAMIENTO E INUNDACIÓN DEL RIO GUAMAL EN EL SECTOR PIO XII, YA QUE SON MÁS DE 2 BRAZOS DEL RÍO QUE ATACAN LA MARGEN IZQUIERDA DEL RÍO GUAMAL LO QUE REQUIERE CONTAR CON HORAS SUFICIENTE PARA EJECUTAR LOS TRABAJOS AGUAS ARRIBA DE MANERA EFICIENTE.
F27: FUNCIONAMIENTO Y OPERACIÓN DE EXCAVADORA SOBRE ORUGA LINK-BELT 210 X2 | G27: =70+200 -> 270 | H27: 0 | I27: =+G27*H27 -> 0 | J27: 0 | K27: =+J27*H27 -> 0 | L27: 0 | M27: =+L27*H27 -> 0
F28: FUNCIONAMIENTO Y OPERACIÓN DE VOLQUETA SENCILLA FTR CHEVROLET | G28: 0 | H28: 0 | I28: =+G28*H28 -> 0 | J28: 0 | K28: =+J28*H28 -> 0 | L28: 0 | M28: =+L28*H28 -> 0
F29: FUNCIONAMIENTO Y OPERACIÓN DE RETROEXCAVADORA CATERPILLAR 416 E | G29: 0 | H29: 0 | I29: =+G29*H29 -> 0 | J29: 0 | K29: =+J29*H29 -> 0 | L29: 0 | M29: =+L29*H29 -> 0
H30: SUBTOTAL | I30: =SUM(I26:I29) -> 0 | K30: =SUM(K26:K29) -> 0 | M30: =SUM(M26:M29) -> 0
A31: 6 | B31: VILLAVICENCIO | C31: PALMARITO ARRAYANES 73°19'6.96"O 3°57'54.72"N | D31: DESCOLMATACIÓN, ENCAUZAMIENTO O CONFORMACIÓN DE JARILLONES | E31: DESBORDAMIENTO E INUNDACIÓN | F31: FUNCIONAMIENTO Y OPERACIÓN DE BULLDOZER SOBRE ORUGA CATERPILLAR D6K XL | G31: 0 | H31: 0 | I31: =+G31*H31 -> 0 | J31: 0 | K31: =+J31*H31 -> 0 | L31: 0 | M31: =+L31*H31 -> 0 | N31: LA MAGNITUD DE AFECTACIÓN DE ESTE PUNTO ES MUY GRANDE POR LO QUE SE REQUIERE INICIAR INTERVENCIÓN EN ÉPOCAS EN LA QUE EL RÍO HAYA BAJADO SU NIVEL
F32: FUNCIONAMIENTO Y OPERACIÓN DE EXCAVADORA SOBRE ORUGA LINK-BELT 210 X2 | G32: 0 | H32: 0 | I32: =+G32*H32 -> 0 | J32: 0 | K32: =+J32*H32 -> 0 | L32: =+G32-J32 -> 0 | M32: =+L32*H32 -> 0
F33: FUNCIONAMIENTO Y OPERACIÓN DE VOLQUETA SENCILLA FTR CHEVROLET | G33: 0 | H33: 0 | I33: =+G33*H33 -> 0 | J33: 0 | K33: =+J33*H33 -> 0 | L33: 0 | M33: =+L33*H33 -> 0
F34: FUNCIONAMIENTO Y OPERACIÓN DE RETROEXCAVADORA CATERPILLAR 416 E | G34: 0 | H34: 0 | I34: =+G34*H34 -> 0 | J34: 0 | K34: =+J34*H34 -> 0 | L34: 0 | M34: =+L34*H34 -> 0
H35: SUBTOTAL | I35: =SUM(I31:I34) -> 0 | K35: =SUM(K31:K34) -> 0 | M35: =SUM(M31:M34) -> 0
A36: 7 | C36: PARCELAS DEL PROGRESO | D36: DESCOLMATACIÓN, ENCAUZAMIENTO O CONFORMACIÓN DE JARILLONES | E36: DESBORDAMIENTO E INUNDACIÓN | F36: FUNCIONAMIENTO Y OPERACIÓN DE BULLDOZER SOBRE ORUGA CATERPILLAR D6K XL | H36: 0 | I36: =+G36*H36 -> 0 | J36: 0 | K36: =+J36*H36 -> 0 | L36: =+G36-J36 -> 0 | M36: =+L36*H36 -> 0 | N36: INFORMACION ENTREGADA POR RIESGOS MUNICIPAL NO SE HA HECHO VISITA
F37: FUNCIONAMIENTO Y OPERACIÓN DE EXCAVADORA SOBRE ORUGA LINK-BELT 210 X2 | H37: 0 | I37: =+G37*H37 -> 0 | J37: 0 | K37: =+J37*H37 -> 0 | L37: =+G37-J37 -> 0 | M37: =+L37*H37 -> 0
F38: FUNCIONAMIENTO Y OPERACIÓN DE VOLQUETA SENCILLA FTR CHEVROLET | G38: 0 | H38: 0 | I38: =+G38*H38 -> 0 | J38: 0 | K38: =+J38*H38 -> 0 | L38: =+G38-J38 -> 0 | M38: =+L38*H38 -> 0
F39: FUNCIONAMIENTO Y OPERACIÓN DE RETROEXCAVADORA CATERPILLAR 416 E | H39: 0 | I39: =+G39*H39 -> 0 | J39: 0 | K39: =+J39*H39 -> 0 | L39: =+G39-J39 -> 0 | M39: =+L39*H39 -> 0
H40: SUBTOTAL | I40: =SUM(I36:I39) -> 0 | K40: =SUM(K36:K39) -> 0 | M40: =SUM(M36:M39) -> 0
A41: 8 | B41: EL CASTILLO, EL DORADO | C41: TRASVASE DE RIO ARIARI A RIO VIEJO | D41: DESCOLMATACIÓN, ENCAUZAMIENTO O CONFORMACIÓN DE JARILLONES | E41: DESBORDAMIENTO E INUNDACIÓN | F41: FUNCIONAMIENTO Y OPERACIÓN DE BULLDOZER SOBRE ORUGA CATERPILLAR D6K XL | H41: 0 | I41: =+G41*H41 -> 0 | J41: 0 | K41: =+J41*H41 -> 0 | L41: =+G41-J41 -> 0 | M41: =+L41*H41 -> 0 | N41: INFORMACION ENTREGADA POR RIESGOS MUNICIPAL NO SE HA HECHO VISITA
F42: FUNCIONAMIENTO Y OPERACIÓN DE EXCAVADORA SOBRE ORUGA LINK-BELT 210 X2 | G42: 0 | H42: 0 | I42: =+G42*H42 -> 0 | J42: 0 | K42: =+J42*H42 -> 0 | L42: =+G42-J42 -> 0 | M42: =+L42*H42 -> 0
F43: FUNCIONAMIENTO Y OPERACIÓN DE VOLQUETA SENCILLA FTR CHEVROLET | H43: 0 | I43: =+G43*H43 -> 0 | J43: 0 | K43: =+J43*H43 -> 0 | L43: =+G43-J43 -> 0 | M43: =+L43*H43 -> 0
F44: FUNCIONAMIENTO Y OPERACIÓN DE RETROEXCAVADORA CATERPILLAR 416 E | H44: 0 | I44: =+G44*H44 -> 0 | J44: 0 | K44: =+J44*H44 -> 0 | L44: =+G44-J44 -> 0 | M44: =+L44*H44 -> 0
H45: SUBTOTAL | I45: =SUM(I41:I44) -> 0 | K45: =SUM(K41:K44) -> 0 | M45: =SUM(M41:M44) -> 0
A46: 9 | B46: EL CASTILLO | C46: PUERTO ESPERANZA, RIO LA CAL | D46: DESCOLMATACIÓN, ENCAUZAMIENTO O CONFORMACIÓN DE JARILLONES | E46: DESBORDAMIENTO E INUNDACIÓN | F46: FUNCIONAMIENTO Y OPERACIÓN DE BULLDOZER SOBRE ORUGA CATERPILLAR D6K XL | H46: 0 | I46: =+G46*H46 -> 0 | J46: 0 | K46: =+J46*H46 -> 0 | L46: =+G46-J46 -> 0 | M46: =+L46*H46 -> 0 | N46: INFORMACION ENTREGADA POR RIESGOS MUNICIPAL NO SE HA HECHO VISITA
F47: FUNCIONAMIENTO Y OPERACIÓN DE EXCAVADORA SOBRE ORUGA LINK-BELT 210 X2 | G47: 0 | H47: 0 | I47: =+G47*H47 -> 0 | J47: 0 | K47: =+J47*H47 -> 0 | L47: =+G47-J47 -> 0 | M47: =+L47*H47 -> 0
F48: FUNCIONAMIENTO Y OPERACIÓN DE VOLQUETA SENCILLA FTR CHEVROLET | H48: 0 | I48: =+G48*H48 -> 0 | J48: 0 | K48: =+J48*H48 -> 0 | L48: =+G48-J48 -> 0 | M48: =+L48*H48 -> 0
F49: FUNCIONAMIENTO Y OPERACIÓN DE RETROEXCAVADORA CATERPILLAR 416 E | H49: 0 | I49: =+G49*H49 -> 0 | J49: 0 | K49: =+J49*H49 -> 0 | L49: =+G49-J49 -> 0 | M49: =+L49*H49 -> 0
H50: SUBTOTAL | I50: =SUM(I46:I49) -> 0 | K50: =SUM(K46:K49) -> 0 | M50: =SUM(M46:M49) -> 0
A51: FUNCIONAMIENTO Y OPERACIÓN DE TRACTO-CAMIÓN | G51: 0 | H51: 0 | I51: =+H51*G51 -> 0 | J51: 0 | K51: =+J51*H51 -> 0 | L51: =+G51-J51 -> 0 | M51: =+L51*H51 -> 0
A52: FUNCIONAMIENTO DE CAMIONETA BT50 | G52: 0 | H52: 0 | I52: =+H52*G52 -> 0 | J52: 0 | K52: =+J52*H52 -> 0 | L52: =+G52-J52 -> 0 | M52: =+L52*H52 -> 0
A53: IMPREVISTOS Y EVENTUALIDADES | G53: 0 | H53: 0 | I53: =+H53*G53 -> 0 | J53: 0 | K53: =+J53*H53 -> 0 | L53: =+G53-J53 -> 0 | M53: =+L53*H53 -> 0 | Q53: 59181221 | R53: =+Q53/H53 -> #DIV/0!
H54: SUBTOTAL | I54: =SUM(I51:I53) -> 0 | K54: =SUM(K51:K53) -> 0 | M54: =SUM(M51:M53) -> 0
A55: SUBTOTAL | I55: =+I54+I20+I35+I30+I25+I15+I45+I40+I50 -> 0 | J55: SUBTOTAL | K55: =+K54+K20+K35+K30+K25+K15+K45+K40+K50 -> 0 | L55: SUBTOTAL | M55: =+M54+M20+M35+M30+M25+M15+M45+M40+M50 -> 0
A56: TOTAL INCLUYE IVA | I56: =+I55*1.19 -> 0 | J56: TOTAL INCLUYE IVA | K56: =+(K55*0.19)+K55 -> 0 | L56: TOTAL INCLUYE IVA | M56: =+(M55*0.19)+M55 -> 0
A57: PORCENTAJE | I57: =+K57+M57 -> #DIV/0! | J57: PORCENTAJE EJECUTADO | K57: =+K56/I56 -> #DIV/0! | L57: PORCENTAJE POR EJECUTAR | M57: =+M56/I56 -> #DIV/0!
B61: LUIS MIGUEL ANGEL RAMIREZ ROMERO | H61: LUZ NELLY MONZÓN DIAZ
B62: REPRESENTANTE LEGAL | H62: DIRECTORA DEPARTAMENTAL PARA LA GESTIÓN DEL RIESGO DE DESASTRES
B63: SERVICIOS MAQUINARIA Y CONSTRUCCIONES S.A.S. "SERVIMACONS S.A.S." | H63: SUPERVISORA
B71: CARMEN LUCIA AGUILAR GOMEZ
B72: DIRECTORA
B73: SERVICIOS MAQUINARIA Y CONSTRUCCIONES S.A.S. "SERVIMACONS S.A.S."

Sheet RESUMEN
A1: RESUMEN GENERAL DE ACTIVIDADES EJECUTADAS
A2: CONTRATO Nº:
A3: OBJETO:
A4: PERIODO DEL INFORME: | F4: AL
A5: FECHA PRESENTE ACTA:
A8: ITEM | B8: DESCRIPCIÓN / MAQUINA | C8: MUNICIPIO | D8: PUNTO | E8: FECHA INICIO | F8: FECHA FINAL | G8: HORAS EJECUTADAS | H8: VALOR EJECUTADO | I8: ACTIVIDAD REALIZADA
A9: 1 | B9: FUNCIONAMIENTO Y OPERACIÓN DE TRACTO-CAMIÓN INTERNACIONAL 7600 CAPACIDAD CARGA 35 TONELADAS CON ACCESORIO CAMABAJA
B10: =+'CAMABAJA OJT166'!C6 -> CAMABAJA INTERNATIONAL OJT166 | C10: =+'CAMABAJA OJT166'!C10 -> VILLAVICENCIO - PATIO GALICIA SERVIMACONS | D10: =+'CAMABAJA OJT166'!D10 -> BAJO POMPEYA SECTOR PALMARITO, RIO GUAYURIBA | E10: =+'CAMABAJA OJT166'!B10 -> 45755 | F10: =+'CAMABAJA OJT166'!B10 -> 45755 | G10: =+'CAMABAJA OJT166'!H10 -> 4 | H10: =+G10*'PLAN DE ACCIÓN'!$H$51 -> 0 | I10: =+'CAMABAJA OJT166'!I10 -> NOS DIRIJIMOS DEL MUNICIPIO DE VILLAVICENCIO PARA TRANSPORTAR LA EXCAVADORA LINK BELT 2181 #1 DEL PATIO GALICIA SERVIMACONS PARA EL PUNTO DE TRABAJO BAJO POMPEYA SECTOR PALMARITO, RIO GUAYURIBA Y NOS REGRESAMOS AL PATIO SERVIMACONS
C11: =+'CAMABAJA OJT166'!C11 -> VILLAVICENCIO - PATIO GALICIA SERVIMACONS | D11: =+'CAMABAJA OJT166'!D11 -> BAJO POMPEYA SECTOR PALMARITO, RIO GUAYURIBA | E11: =+'CAMABAJA OJT166'!B11 -> 45755 | F11: =+'CAMABAJA OJT166'!B11 -> 45755 | G11: =+'CAMABAJA OJT166'!H11 -> 4 | H11: =+G11*'PLAN DE ACCIÓN'!$H$51 -> 0 | I11: =+'CAMABAJA OJT166'!I11 -> NOS DIRIJIMOS DEL MUNICIPIO DE VILLAVICENCIO PARA TRANSPORTAR LA EXCAVADORA LINK BELT 2180 #5 DEL PATIO GALICIA SERVIMACONS PARA EL PUNTO DE TRABAJO BAJO POMPEYA SECTOR PALMARITO, RIO GUAYURIBA Y NOS REGRESAMOS AL PATIO SERVIMACONS
C12: =+'CAMABAJA OJT166'!C12 -> VILLAVICENCIO - PATIO GALICIA SERVIMACONS | D12: =+'CAMABAJA OJT166'!D12 -> SECTOR LA ISLA, RIO GUAMAL | E12: =+'CAMABAJA OJT166'!B12 -> 45756 | F12: =+'CAMABAJA OJT166'!B12 -> 45756 | G12: =+'CAMABAJA OJT166'!H12 -> 8 | H12: =+G12*'PLAN DE ACCIÓN'!$H$51 -> 0 | I12: =+'CAMABAJA OJT166'!I12 -> NOS DIRIJIMOS DEL MUNICIPIO DE VILLAVICENCIO PARA TRANSPORTAR LA EXCAVADORA LINK BELT 2183 #3 DEL PATIO GALICIA SERVIMACONS PARA EL PUNTO DE TRABAJO SECTOR LA ISLA RIO GUAMAL Y NOS REGRESAMOS AL PATIO SERVIMACONS
C13: =+'CAMABAJA OJT166'!C13 -> VILLAVICENCIO - PATIO GALICIA SERVIMACONS | D13: =+'CAMABAJA OJT166'!D13 -> SECTOR PIO XII, RIO GUAMAL | E13: =+'CAMABAJA OJT166'!B13 -> 45757 | F13: =+'CAMABAJA OJT166'!B13 -> 45757 | G13: =+'CAMABAJA OJT166'!H13 -> 4 | H13: =+G13*'PLAN DE ACCIÓN'!$H$51 -> 0 | I13: =+'CAMABAJA OJT166'!I13 -> NOS DIRIJIMOS DEL MUNICIPIO DE VILLAVICENCIO PARA TRANSPORTAR LA EXCAVADORA LINK BELT 2179 #4 DEL PATIO GALICIA SERVIMACONS PARA EL PUNTO DE TRABAJO SECTOR PIO XII RIO GUAMAL Y NOS REGRESAMOS AL PATIO SERVIMACONS
C14: =+'CAMABAJA OJT166'!C14 -> EL CALVARIO | D14: =+'CAMABAJA OJT166'!D14 -> VIA MONFORTH | E14: =+'CAMABAJA OJT166'!B14 -> 45770 | F14: =+'CAMABAJA OJT166'!B14 -> 45770 | G14: =+'CAMABAJA OJT166'!H14 -> 3 | H14: =+G14*'PLAN DE ACCIÓN'!$H$51 -> 0 | I14: =+'CAMABAJA OJT166'!I14 -> NOS DIRIJIMOS DEL MUNICIPIO DE VILLAVICENCIO PARA TRANSPORTAR LA RETROEXCAVADORA CATERPILLAR 8585 416E DEL PATIO GALICIA SERVIMACONS PARA LA VIA MONFORTH Y NOS REGRESAMOS AL PATIO SERVIMACONS
C15: =+'CAMABAJA OJT166'!C15 -> BAJO POMPEYA SECTOR PALMARITO, RIO GUAYURIBA | D15: =+'CAMABAJA OJT166'!D15 -> VILLAVICENCIO - PATIO GALICIA SERVIMACONS | E15: =+'CAMABAJA OJT166'!B15 -> 45777 | F15: =+'CAMABAJA OJT166'!B15 -> 45777 | G15: =+'CAMABAJA OJT166'!H15 -> 4 | H15: =+G15*'PLAN DE ACCIÓN'!$H$51 -> 0 | I15: =+'CAMABAJA OJT166'!I15 -> NOS DIRIJIMOS DEL MUNICIPIO DE VILLAVICENCIO PARA TRANSPORTAR LA EXCAVADORA LINK BELT 2181 #1 DEL PUNTO DE TRABAJO BAJO POMPEYA PARA EL PATIO GALICIA SERVIMACONS
C16: =+'CAMABAJA OJT166'!C16 -> BAJO POMPEYA SECTOR PALMARITO, RIO GUAYURIBA | D16: =+'CAMABAJA OJT166'!D16 -> VILLAVICENCIO - PATIO GALICIA SERVIMACONS | E16: =+'CAMABAJA OJT166'!B16 -> 45777 | F16: =+'CAMABAJA OJT166'!B16 -> 45777 | G16: =+'CAMABAJA OJT166'!H16 -> 4 | H16: =+G16*'PLAN DE ACCIÓN'!$H$51 -> 0 | I16: =+'CAMABAJA OJT166'!I16 -> NOS DIRIJIMOS DEL MUNICIPIO DE VILLAVICENCIO PARA TRANSPORTAR LA EXCAVADORA LINK BELT 2180 #5 DEL PUNTO DE TRABAJO BAJO POMPEYA PARA EL PATIO GALICIA SERVIMACONS
C17: =+'CAMABAJA OJT166'!C17 -> VILLAVICENCIO - PATIO GALICIA SERVIMACONS | D17: =+'CAMABAJA OJT166'!D17 -> EL DORADO, SECTOR LA ISLA RIO ARIARI | E17: =+'CAMABAJA OJT166'!B17 -> 45778 | F17: =+'CAMABAJA OJT166'!B17 -> 45778 | G17: =+'CAMABAJA OJT166'!H17 -> 5 | H17: =+G17*'PLAN DE ACCIÓN'!$H$51 -> 0 | I17: =+'CAMABAJA OJT166'!I17 -> NOS DIRIJIMOS DEL MUNICIPIO DE VILLAVICENCIO PARA TRANSPORTAR LA EXCAVADORA LINK BELT 2181 #1 DEL PATIO SERVIMACONS PARA EL PUNTO DE TRABAJO EL DORADO PUENTE LA AMISTAD Y NOS REGRESAMOS AL PATIO SERVIMACONS
C18: =+'CAMABAJA OJT166'!C18 -> VILLAVICENCIO - PATIO GALICIA SERVIMACONS | D18: =+'CAMABAJA OJT166'!D18 -> EL DORADO, SECTOR LA ISLA RIO ARIARI | E18: =+'CAMABAJA OJT166'!B18 -> 45784 | F18: =+'CAMABAJA OJT166'!B18 -> 45784 | G18: =+'CAMABAJA OJT166'!H18 -> 4 | H18: =+G18*'PLAN DE ACCIÓN'!$H$51 -> 0 | I18: =+'CAMABAJA OJT166'!I18 -> NOS DIRIJIMOS DEL MUNICIPIO DE VILLAVICENCIO PARA TRANSPORTAR LA EXCAVADORA LINK BELT 2180 #5 DEL PATIO GALICIA SERVIMACONS PARA EL PUNTO DE TRABAJO EL DORADO, SECTOR LA ISLA RIO ARIARI Y NOS DIRIJIMOS AL MUNICIPIO DE GUAMAL
C19: =+'CAMABAJA OJT166'!C19 -> VILLAVICENCIO - PATIO GALICIA SERVIMACONS | D19: =+'CAMABAJA OJT166'!D19 -> EL DORADO, SECTOR LA ISLA RIO ARIARI | E19: =+'CAMABAJA OJT166'!B19 -> 45784 | F19: =+'CAMABAJA OJT166'!B19 -> 45784 | G19: =+'CAMABAJA OJT166'!H19 -> 4 | H19: =+G19*'PLAN DE ACCIÓN'!$H$51 -> 0 | I19: =+'CAMABAJA OJT166'!I19 -> NOS DIRIJIMOS DEL MUNICIPIO DE VILLAVICENCIO PARA TRANSPORTAR LA EXCAVADORA LINK BELT 2179 #4 DEL PUNTO DE TRABAJO PIO XII PARA EL PUNTO DE TRABAJO EL DORARO SECTOR LA ISLA RIO ARIARI Y NOS REGRESAMOS AL PATIO SERVIMACONS
C20: =+'CAMABAJA OJT166'!C20 -> EL DORADO, SECTOR LA ISLA RIO ARIARI | D20: =+'CAMABAJA OJT166'!D20 -> SECTOR PUERTO ESPERANZA | E20: =+'CAMABAJA OJT166'!B20 -> 45794 | F20: =+'CAMABAJA OJT166'!B20 -> 45794 | G20: =+'CAMABAJA OJT166'!H20 -> 4 | H20: =+G20*'PLAN DE ACCIÓN'!$H$51 -> 0 | I20: =+'CAMABAJA OJT166'!I20 -> NOS DIRIJIMOS DEL MUNICIPIO DE VILLAVICENCIO PARA TRANSPORTAR LA EXCAVADORA LINK BELT 2179 #4 DEL PUNTO DE TRABAJO SECTOR LA ISLA RIO ARIARI PARA EL PUNTO PUERTO ESPERANZA Y NOS REGRESAMOS AL PATIO SERVIMACONS
C21: =+'CAMABAJA OJT166'!C21 -> GUAMAL, SECTOR LA ISLA RIO GUAMAL | D21: =+'CAMABAJA OJT166'!D21 -> VILLAVICENCIO - PATIO GALICIA SERVIMACONS | E21: =+'CAMABAJA OJT166'!B21 -> 45800 | F21: =+'CAMABAJA OJT166'!B21 -> 45800 | G21: =+'CAMABAJA OJT166'!H21 -> 4 | H21: =+G21*'PLAN DE ACCIÓN'!$H$51 -> 0 | I21: =+'CAMABAJA OJT166'!I21 -> NOS DIRIJIMOS DEL MUNICIPIO DE VILLAVICENCIO PARA TRANSPORTAR LA EXCAVADORA LINK BELT 2183 #3 DEL PUNTO DE TRABAJO GUAMAL, SECTOR LA ISLA RIO ARIARI Y NOS REGRESAMOS AL PATIO SERVIMACONS
C22: =+'CAMABAJA OJT166'!C22 -> EL DORADO, SECTOR LA ISLA RIO ARIARI | D22: =+'CAMABAJA OJT166'!D22 -> VILLAVICENCIO - PATIO GALICIA SERVIMACONS | E22: =+'CAMABAJA OJT166'!B22 -> 45801 | F22: =+'CAMABAJA OJT166'!B22 -> 45801 | G22: =+'CAMABAJA OJT166'!H22 -> 5 | H22: =+G22*'PLAN DE ACCIÓN'!$H$51 -> 0 | I22: =+'CAMABAJA OJT166'!I22 -> NOS DIRIJIMOS DEL MUNICIPIO DE VILLAVICENCIO PARA TRANSPORTAR LA EXCAVADORA LINK BELT 2180 #5 DEL PUNTO DE TRABAJO EL DORADO, SECTOR LA ISLA Y NOS REGRESAMOS AL PATIO SERVIMACONS
... C28: =+'CAMABAJA OJT166'!C28 -> VILLAVICENCIO - PATIO GALICIA SERVIMACONS | D28: =+'CAMABAJA OJT166'!D28 -> GUAMAL - SECTOR PIO XII, RIO GUAMAL | E28: =+'CAMABAJA OJT166'!B28 -> 45840 | F28: =+'CAMABAJA OJT166'!B28 -> 45840 | G28: =+'CAMABAJA OJT166'!H28 -> 6 | H28: =+G28*'PLAN DE ACCIÓN'!$H$51 -> 0 | I28: =+'CAMABAJA OJT166'!I28 -> NOS DIRIJIMOS DEL MUNICIPIO DE VILLAVICENCIO PARA TRANSPORTAR LA EXCAVADORA LINK BELT 2180 #5 DEL PATIO GALICIA SERVIMACONS PARA EL PUNTO DE TRABAJO GUAMAL SECTOR PIO XII Y NOS REGRESAMOS AL PATIO SERVIMACONS
C29: =+'CAMABAJA OJT166'!C29 -> GUAMAL - SECTOR PIO XII, RIO GUAMAL | D29: =+'CAMABAJA OJT166'!D29 -> VILLAVICENCIO - PATIO GALICIA SERVIMACONS | E29: =+'CAMABAJA OJT166'!B29 -> 45847 | F29: =+'CAMABAJA OJT166'!B29 -> 45847 | G29: =+'CAMABAJA OJT166'!H29 -> 6 | H29: =+G29*'PLAN DE ACCIÓN'!$H$51 -> 0 | I29: =+'CAMABAJA OJT166'!I29 -> NOS DIRIJIMOS DEL MUNICIPIO DE VILLAVICENCIO PARA TRANSPORTAR LA EXCAVADORA LINK BELT 2180 #5 DEL PUNTO DE TRABAJO GUAMAL PIO XII PARA EL PATIO GALICIA SERVIMACONS | J29: EL TOTAL DE LAS HORAS DE LA CAMABAJA ES MAYOR AL AUTORIZADO
A30: TOTAL | G30: =SUM(G10:G29) -> 102 | H30: =SUM(H10:H29) -> 0
A31: 2 | B31: FUNCIONAMIENTO Y OPERACIÓN DE BULLDOZER SOBRE ORUGA CATERPILLAR D6K XL
B32: =+'2'!B10 -> BULLDOZER CATERPILLAR 2765 #2 | C32: =+'2'!C10 -> nombre municipio | D32: =+'2'!D10 -> nombre punto | E32: =+'2'!E10 -> 45769 | F32: =+'2'!F10 -> 45783 | G32: =+'2'!G10 -> 100 | H32: =+'2'!H10 -> 0 | I32: =+'2'!I10 -> SE REALIZA REHABILITACIÓN DE VIA EN EL PUNTO LA PAILA, RECORRIDO DE LA MAQUINA DEL PUNTO LA PAILA PARA EL DERRUMBE EN LA VEREDA EL CARMEN
B33: =+'2'!B11 -> BULLDOZER CATERPILLAR 2765 #2 | C33: =+'2'!C11 -> EL CALVARIO | D33: =+'2'!D11 -> SECTOR LAS BRUJAS | E33: =+'2'!E11 -> 45814 | F33: =+'2'!F11 -> 45825 | G33: =+'2'!G11 -> 188 | H33: =+'2'!H11 -> 0 | I33: =+'2'!I11 -> MAQUINA DISPONIBLE EN EL PUNTO DE TRABAJO, SE PRESENTAN FUERTES LLUVIAS EN EL SECTOR
B34: =+'2'!B12 -> #REF! | C34: =+'2'!C12 -> #REF! | D34: =+'2'!D12 -> #REF! | E34: =+'2'!E12 -> #REF! | F34: =+'2'!F12 -> #REF! | G34: =+'2'!G12 -> #REF! | H34: =+'2'!H12 -> #REF! | I34: =+'2'!I12 -> #REF!
A35: TOTAL | G35: =SUM(G32:G33) -> 288 | H35: =SUM(H32:H34) -> #REF!
A36: 3 | B36: FUNCIONAMIENTO Y OPERACIÓN DE EXCAVADORA SOBRE ORUGA LINK-BELT 210 X2, CAPACIDAD BALDE 1 M3 21 TONELADAS
B37: =+'BAJO POMPEYA - PALMARITO'!B9 -> EXCAVADORA LINK BELT 2181 #1 | C37: =+'BAJO POMPEYA - PALMARITO'!C9 -> VILLAVICENCIO | D37: =+'BAJO POMPEYA - PALMARITO'!D9 -> BAJO POMPEYA SECTOR PALMARITO, RIO GUAYURIBA | E37: =+'BAJO POMPEYA - PALMARITO'!E9 -> 45755 | F37: =+'BAJO POMPEYA - PALMARITO'!F9 -> 45777 | G37: =+'BAJO POMPEYA - PALMARITO'!G9 -> 127.2 | H37: =+'BAJO POMPEYA - PALMARITO'!H9 -> 0 | I37: =+'BAJO POMPEYA - PALMARITO'!I9 -> SE REALIZA EXCAVACIÓN EN EL CANAL PARA CONSTRUCIÓN DEL JARILLON Y PODER DESVIAR EL RIO
B38: =+'BAJO POMPEYA - PALMARITO'!B10 -> EXCAVADORA LINK BELT 2180 #5 | C38: =+'BAJO POMPEYA - PALMARITO'!C10 -> VILLAVICENCIO | D38: =+'BAJO POMPEYA - PALMARITO'!D10 -> BAJO POMPEYA SECTOR PALMARITO, RIO GUAYURIBA | E38: =+'BAJO POMPEYA - PALMARITO'!E10 -> 45755 | F38: =+'BAJO POMPEYA - PALMARITO'!F10 -> 45777 | G38: =+'BAJO POMPEYA - PALMARITO'!G10 -> 122.8 | H38: =+'BAJO POMPEYA - PALMARITO'!H10 -> 0 | I38: =+'BAJO POMPEYA - PALMARITO'!I10 -> SE REALIZA EXCAVACIÓN PARA DESVIAR UN BRAZO DEL RIO QUE ESTA RECOSTADO EN LA MARGEN IZQUIERDA
B39: =+'3'!B12 -> EXCAVADORA LINK BELT 2183 #3 | C39: =+'3'!C12 -> GUAMAL | D39: =+'3'!D12 -> SECTOR LA ISLA, RIO GUAMAL | E39: =+'3'!E12 -> 45757 | F39: =+'3'!F12 -> 45800 | G39: =+'3'!G12 -> 270 | H39: =+'3'!H12 -> 0 | I39: =+'3'!I12 -> SE REALIZA EXCAVACIÓN PARA CONSTRUCCIÓN DE UN JARILLON DE PROTECCIÓN
B40: =+'3'!B13 -> EXCAVADORA LINK BELT 2179 #4 | C40: =+'3'!C13 -> GUAMAL | D40: =+'3'!D13 -> SECTOR PIO XII, RIO GUAMAL | E40: =+'3'!E13 -> 45757 | F40: =+'3'!F13 -> 45784 | G40: =+'3'!G13 -> 130 | H40: =+'3'!H13 -> 0 | I40: =+'3'!I13 -> SE REALIZA CONSTRUCCIÓN DE JARILLON PARA QUITAR PRESION DE LA MARGEN IZQUIERDA AGUAS ABAJO Y SE CENTRA PARTE DEL RIO
B41: =+'3'!B14 -> EXCAVADORA LINK BELT 2181 #1 | C41: =+'3'!C14 -> EL CASTILLO | D41: =+'3'!D14 -> PUENTE LA AMISTAD, RIO ARIARI | E41: =+'3'!E14 -> 45779 | F41: =+'3'!F14 -> 45793 | G41: =+'3'!G14 -> 106.5 | H41: =+'3'!H14 -> 0 | I41: =+'3'!I14 -> SE TRANSPALEA MATERIAL PARA AMPLIACIÓN DE CANAL EN EL RIO ARIARI
B42: =+'3'!B15 -> EXCAVADORA LINK BELT 2180 #5 | C42: =+'3'!C15 -> EL CASTILLO | D42: =+'3'!D15 -> PUENTE LA AMISTAD, RIO ARIARI | E42: =+'3'!E15 -> 45784 | F42: =+'3'!F15 -> 45802 | G42: =+'3'!G15 -> 107.8 | H42: =+'3'!H15 -> 0 | I42: =+'3'!I15 -> SE REALIZA LA CONSTRUCCIÓN DEL CANAL PARA DESVIO DEL CAUCE DEL RIO
B43: =+'3'!B16 -> EXCAVADORA LINK BELT 2179 #4 | C43: =+'3'!C16 -> EL CASTILLO | D43: =+'3'!D16 -> PUENTE LA AMISTAD, RIO ARIARI | E43: =+'3'!E16 -> 45784 | F43: =+'3'!F16 -> 45804 | G43: =+'3'!G16 -> 8.7 | H43: =+'3'!H16 -> 0 | I43: =+'3'!I16 -> SE REALIZA LA CONSTRUCCIÓN DEL CANAL PARA DESVIO DEL CAUCE DEL RIO
B44: =+'3'!B17 -> EXCAVADORA LINK BELT 2181 #1 | C44: =+'3'!C17 -> EL CASTILLO | D44: =+'3'!D17 -> PUERTO ESPERANZA, RIO LA CAL | E44: =+'3'!E17 -> 45794 | F44: =+'3'!F17 -> 45807 | G44: =+'3'!G17 -> 117 | H44: =+'3'!H17 -> 0 | I44: =+'3'!I17 -> EXCAVACIÓN PARA CANAL Y SE CONFORMA JARILLON DE PROTECCIÓN
B45: =+'3'!B18 -> EXCAVADORA LINK BELT 2119 #4 | C45: =+'3'!C18 -> EL DORADO | D45: =+'3'!D18 -> RIO ARIARI | E45: =+'3'!E18 -> 45825 | F45: =+'3'!F18 -> 45849 | G45: =+'3'!G18 -> 100 | H45: =+'3'!H18 -> 0 | I45: =+'3'!I18 -> SE REALIZA EXCAVACIÓN PARA CONFORMACIÓN DE JARILLON DE PROTECCIÓN
B46: =+'3'!B19 -> EXCAVADORA LINK BELT 2183 #3 | C46: =+'3'!C19 -> SAN CARLOS DE GUAROA | D46: =+'3'!D19 -> SECTOR PUENTE TRES ARCOS | E46: =+'3'!E19 -> 45821 | F46: =+'3'!F19 -> 45838 | G46: =+'3'!G19 -> 100 | H46: =+'3'!H19 -> 0 | I46: =+'3'!I19 -> SE REALIZA ENROCADO EN LA MARGEN DERECHA AGUAS ABAJO PARA MITIGAR DESBORDAMIENTO EN EL TERRAPLEN DE LA CARRETERA Y REHABILITAR EL PASO EN EL PUENTE
B47: =+#REF! -> #REF! | C47: =+#REF! -> #REF! | D47: =+#REF! -> #REF! | E47: =+#REF! -> #REF! | F47: =+#REF! -> #REF! | G47: =+#REF! -> #REF! | H47: =+#REF! -> #REF! | I47: =+#REF! -> #REF!
B48: =+'3'!B20 -> #REF! | C48: =+'3'!C20 -> #REF! | D48: =+'3'!D20 -> #REF! | E48: =+'3'!E20 -> #REF! | F48: =+'3'!F20 -> #REF! | G48: =+'3'!G20 -> #REF! | H48: =+'3'!H20 -> #REF! | I48: =+'3'!I20 -> #REF!
A49: TOTAL | G49: =SUM(G37:G48) -> #REF! | H49: =SUM(H37:H48) -> #REF!
A50: 4 | B50: FUNCIONAMIENTO Y OPERACIÓN DE VOLQUETA SENCILLA FTR CHEVROLET
B51: =+'VILLAVICENCIO - PARCELAS'!B9 -> VOLQUETA CHEVROLET OJT163 #3 | C51: =+'VILLAVICENCIO - PARCELAS'!C9 -> VILLAVICENCIO | D51: =+'VILLAVICENCIO - PARCELAS'!D9 -> PARCELAS DEL PROGRESO | E51: =+'VILLAVICENCIO - PARCELAS'!E9 -> 45789 | F51: =+'VILLAVICENCIO - PARCELAS'!F9 -> 45796 | G51: =+'VILLAVICENCIO - PARCELAS'!G9 -> 65.4 | H51: =+'VILLAVICENCIO - PARCELAS'!H9 -> 0 | I51: =+'VILLAVICENCIO - PARCELAS'!I9 -> TRANSPORTE DE MATERIAL DEL RIO GUATIQUIA PARA CONSTRUCCIÓN DEL JARILLON
B52: =+'VILLAVICENCIO - PARCELAS'!B10 -> VOLQUETA CHEVROLET OJT165 #5 | C52: =+'VILLAVICENCIO - PARCELAS'!C10 -> VILLAVICENCIO | D52: =+'VILLAVICENCIO - PARCELAS'!D10 -> PARCELAS DEL PROGRESO | E52: =+'VILLAVICENCIO - PARCELAS'!E10 -> 45789 | F52: =+'VILLAVICENCIO - PARCELAS'!F10 -> 45796 | G52: =+'VILLAVICENCIO - PARCELAS'!G10 -> 65 | H52: =+'VILLAVICENCIO - PARCELAS'!H10 -> 0 | I52: =+'VILLAVICENCIO - PARCELAS'!I10 -> TRANSPORTE DE MATERIAL DEL RIO GUATIQUIA PARA CONSTRUCCIÓN DEL JARILLON
B53: =+'VILLAVICENCIO - PARCELAS'!B11 -> VOLQUETA CHEVROLET OJT162 #2 | C53: =+'VILLAVICENCIO - PARCELAS'!C11 -> VILLAVICENCIO | D53: =+'VILLAVICENCIO - PARCELAS'!D11 -> PARCELAS DEL PROGRESO | E53: =+'VILLAVICENCIO - PARCELAS'!E11 -> 45790 | F53: =+'VILLAVICENCIO - PARCELAS'!F11 -> 45793 | G53: =+'VILLAVICENCIO - PARCELAS'!G11 -> 19.6 | H53: =+'VILLAVICENCIO - PARCELAS'!H11 -> 0 | I53: =+'VILLAVICENCIO - PARCELAS'!I11 -> TRANSPORTE DE MATERIAL DEL RIO GUATIQUIA PARA CONSTRUCCIÓN DEL JARILLON
A54: TOTAL | G54: =SUM(G51:G53) -> 150 | H54: =SUM(H51:H53) -> 0
A55: 5 | B55: FUNCIONAMIENTO Y OPERACIÓN DE RETROEXCAVADORA CATERPILLAR 416 E
B56: =+'5'!B10 -> RETROEXCAVADORA CATERPILLAR 8585 416E | C56: =+'5'!C10 -> nombre del municipio | D56: =+'5'!D10 -> nombre del punto | E56: =+'5'!E10 -> 45775 | F56: =+'5'!F10 -> 45833 | G56: =+'5'!G10 -> 81 | H56: =+'5'!H10 -> 0 | I56: =+'5'!I10 -> REHABILITACIÓN DE LA VIA MONFORTH Y CONFORMACIÓN DE CUNETAS
B57: =+'5'!B11 -> RETROEXCAVADORA CATERPILLAR 8585 416E | C57: =+'5'!C11 -> EL CALVARIO | D57: =+'5'!D11 -> VIA MONFORTH | E57: =+'5'!E11 -> 45833 | F57: =+'5'!F11 -> 45839 | G57: =+'5'!G11 -> 50 | H57: =+'5'!H11 -> 0 | I57: =+'5'!I11 -> REHABILITACIÓN DE VIA Y CONFORMACIÓN DE CUNETAS
A58: TOTAL | G58: =SUM(G56:G57) -> 131 | H58: =SUM(H56:H57) -> 0
A59: 6 | B59: FUNCIONAMIENTO DE CAMIONETA BT50
G60: 30 | H60: =+G61*'PLAN DE ACCIÓN'!H52 -> 0
A61: TOTAL | G61: =SUM(G59:G60) -> 30 | H61: =SUM(H60) -> 0
A62: 7 | B62: IMPREVISTOS Y EVENTUALIDADES
G63: =+'PLAN DE ACCIÓN'!J53 -> 0 | H63: =+G63*'PLAN DE ACCIÓN'!H53 -> 0
A64: TOTAL | G64: =SUM(G62:G63) -> 0 | H64: =SUM(H63) -> 0
A65: SUBTOTAL | H65: =+H64+H61+H49+H30+H58+H54+H35 -> #REF!
A66: IVA 19% | H66: =+H65*19% -> #REF!
A67: TOTAL | H67: =+H65+H66 -> #REF!
B71: LUIS MIGUEL ANGEL RAMIREZ ROMERO
B72: Rep. Legal SERVICIOS MAQUINARIA Y CONSTRUCCIONES SAS "SERVIMACONS S.A.S."
B73: CONTRATISTA

Sheet 1
A1: RESUMEN GENERAL DE ACTIVIDADES EJECUTADAS
A2: CONTRATO Nº:
A3: OBJETO:
A4: PERIODO DEL INFORME: | F4: AL
A5: FECHA PRESENTE ACTA:
A8: ITEM | B8: DESCRIPCIÓN / MAQUINA | C8: MUNICIPIO | D8: PUNTO | E8: FECHA INICIO | F8: FECHA FINAL | G8: HORAS EJECUTADAS | H8: VALOR EJECUTADO | I8: ACTIVIDAD REALIZADA
A9: 1 | B9: FUNCIONAMIENTO Y OPERACIÓN DE TRACTO-CAMIÓN INTERNACIONAL 7600 CAPACIDAD CARGA 35 TONELADAS CON ACCESORIO CAMABAJA
B10: =+'CAMABAJA INTERNACIONAL OJT166'!B9 -> CAMABAJA INTERNATIONAL OJT166 | C10: =+'CAMABAJA OJT166'!C10 -> VILLAVICENCIO - PATIO GALICIA SERVIMACONS | D10: =+'CAMABAJA OJT166'!D10 -> BAJO POMPEYA SECTOR PALMARITO, RIO GUAYURIBA | E10: =+'CAMABAJA OJT166'!B10 -> 45755 | F10: =+E10 -> 45755 | G10: =+'CAMABAJA OJT166'!H10 -> 4 | H10: =+'1'!G10*'PLAN DE ACCIÓN'!H51 -> 0 | I10: =+'CAMABAJA OJT166'!I10 -> NOS DIRIJIMOS DEL MUNICIPIO DE VILLAVICENCIO PARA TRANSPORTAR LA EXCAVADORA LINK BELT 2181 #1 DEL PATIO GALICIA SERVIMACONS PARA EL PUNTO DE TRABAJO BAJO POMPEYA SECTOR PALMARITO, RIO GUAYURIBA Y NOS REGRESAMOS AL PATIO SERVIMACONS
C11: =+'CAMABAJA OJT166'!C11 -> VILLAVICENCIO - PATIO GALICIA SERVIMACONS | D11: =+'CAMABAJA OJT166'!D11 -> BAJO POMPEYA SECTOR PALMARITO, RIO GUAYURIBA | E11: =+'CAMABAJA OJT166'!B11 -> 45755 | F11: =+E11 -> 45755 | G11: =+'CAMABAJA OJT166'!H11 -> 4 | H11: =+G11*'PLAN DE ACCIÓN'!H51 -> 0 | I11: =+'CAMABAJA OJT166'!I11 -> NOS DIRIJIMOS DEL MUNICIPIO DE VILLAVICENCIO PARA TRANSPORTAR LA EXCAVADORA LINK BELT 2180 #5 DEL PATIO GALICIA SERVIMACONS PARA EL PUNTO DE TRABAJO BAJO POMPEYA SECTOR PALMARITO, RIO GUAYURIBA Y NOS REGRESAMOS AL PATIO SERVIMACONS
C12: =+'CAMABAJA OJT166'!C12 -> VILLAVICENCIO - PATIO GALICIA SERVIMACONS | D12: =+'CAMABAJA OJT166'!D12 -> SECTOR LA ISLA, RIO GUAMAL | E12: =+'CAMABAJA OJT166'!B12 -> 45756 | F12: =+E12 -> 45756 | G12: =+'CAMABAJA OJT166'!H12 -> 8 | H12: =+G12*'PLAN DE ACCIÓN'!H51 -> 0 | I12: =+'CAMABAJA OJT166'!I12 -> NOS DIRIJIMOS DEL MUNICIPIO DE VILLAVICENCIO PARA TRANSPORTAR LA EXCAVADORA LINK BELT 2183 #3 DEL PATIO GALICIA SERVIMACONS PARA EL PUNTO DE TRABAJO SECTOR LA ISLA RIO GUAMAL Y NOS REGRESAMOS AL PATIO SERVIMACONS
C13: =+'CAMABAJA INTERNACIONAL OJT166'!C12 -> VILLAVICENCIO - PATIO GALICIA SERVIMACONS | D13: =+'CAMABAJA INTERNACIONAL OJT166'!D12 -> SECTOR PIO XII, RIO GUAMAL | E13: =+'CAMABAJA INTERNACIONAL OJT166'!E12 -> 45757 | F13: =+'CAMABAJA INTERNACIONAL OJT166'!F12 -> 45757 | G13: =+'CAMABAJA INTERNACIONAL OJT166'!G12 -> 4 | H13: =+'CAMABAJA INTERNACIONAL OJT166'!H12 -> 0 | I13: =+'CAMABAJA INTERNACIONAL OJT166'!I12 -> NOS DIRIJIMOS DEL MUNICIPIO DE VILLAVICENCIO PARA TRANSPORTAR LA EXCAVADORA LINK BELT 2179 #4 DEL PATIO GALICIA SERVIMACONS PARA EL PUNTO DE TRABAJO SECTOR PIO XII RIO GUAMAL Y NOS REGRESAMOS AL PATIO SERVIMACONS
C14: =+'CAMABAJA INTERNACIONAL OJT166'!C13 -> EL CALVARIO | D14: =+'CAMABAJA INTERNACIONAL OJT166'!D13 -> VIA MONFORTH | E14: =+'CAMABAJA INTERNACIONAL OJT166'!E13 -> 45770 | F14: =+'CAMABAJA INTERNACIONAL OJT166'!F13 -> 45770 | G14: =+'CAMABAJA INTERNACIONAL OJT166'!G13 -> 3 | H14: =+'CAMABAJA INTERNACIONAL OJT166'!H13 -> 0 | I14: =+'CAMABAJA INTERNACIONAL OJT166'!I13 -> NOS DIRIJIMOS DEL MUNICIPIO DE VILLAVICENCIO PARA TRANSPORTAR LA RETROEXCAVADORA CATERPILLAR 8585 416E DEL PATIO GALICIA SERVIMACONS PARA LA VIA MONFORTH Y NOS REGRESAMOS AL PATIO SERVIMACONS
C15: =+'CAMABAJA INTERNACIONAL OJT166'!C14 -> BAJO POMPEYA SECTOR PALMARITO, RIO GUAYURIBA | D15: =+'CAMABAJA INTERNACIONAL OJT166'!D14 -> VILLAVICENCIO - PATIO GALICIA SERVIMACONS | E15: =+'CAMABAJA INTERNACIONAL OJT166'!E14 -> 45777 | F15: =+'CAMABAJA INTERNACIONAL OJT166'!F14 -> 45777 | G15: =+'CAMABAJA INTERNACIONAL OJT166'!G14 -> 4 | H15: =+'CAMABAJA INTERNACIONAL OJT166'!H14 -> 0 | I15: =+'CAMABAJA INTERNACIONAL OJT166'!I14 -> NOS DIRIJIMOS DEL MUNICIPIO DE VILLAVICENCIO PARA TRANSPORTAR LA EXCAVADORA LINK BELT 2181 #1 DEL PUNTO DE TRABAJO BAJO POMPEYA PARA EL PATIO GALICIA SERVIMACONS
C16: =+'CAMABAJA INTERNACIONAL OJT166'!C15 -> BAJO POMPEYA SECTOR PALMARITO, RIO GUAYURIBA | D16: =+'CAMABAJA INTERNACIONAL OJT166'!D15 -> VILLAVICENCIO - PATIO GALICIA SERVIMACONS | E16: =+'CAMABAJA INTERNACIONAL OJT166'!E15 -> 45777 | F16: =+'CAMABAJA INTERNACIONAL OJT166'!F15 -> 45777 | G16: =+'CAMABAJA INTERNACIONAL OJT166'!G15 -> 4 | H16: =+'CAMABAJA INTERNACIONAL OJT166'!H15 -> 0 | I16: =+'CAMABAJA INTERNACIONAL OJT166'!I15 -> NOS DIRIJIMOS DEL MUNICIPIO DE VILLAVICENCIO PARA TRANSPORTAR LA EXCAVADORA LINK BELT 2180 #5 DEL PUNTO DE TRABAJO BAJO POMPEYA PARA EL PATIO GALICIA SERVIMACONS
C17: =+'CAMABAJA INTERNACIONAL OJT166'!C16 -> VILLAVICENCIO - PATIO GALICIA SERVIMACONS | D17: =+'CAMABAJA INTERNACIONAL OJT166'!D16 -> EL DORADO, SECTOR LA ISLA RIO ARIARI | E17: =+'CAMABAJA INTERNACIONAL OJT166'!E16 -> 45778 | F17: =+'CAMABAJA INTERNACIONAL OJT166'!F16 -> 45778 | G17: =+'CAMABAJA INTERNACIONAL OJT166'!G16 -> 5 | H17: =+'CAMABAJA INTERNACIONAL OJT166'!H16 -> 0 | I17: =+'CAMABAJA INTERNACIONAL OJT166'!I16 -> NOS DIRIJIMOS DEL MUNICIPIO DE VILLAVICENCIO PARA TRANSPORTAR LA EXCAVADORA LINK BELT 2181 #1 DEL PATIO SERVIMACONS PARA EL PUNTO DE TRABAJO EL DORADO PUENTE LA AMISTAD Y NOS REGRESAMOS AL PATIO SERVIMACONS
C18: =+'CAMABAJA INTERNACIONAL OJT166'!C17 -> VILLAVICENCIO - PATIO GALICIA SERVIMACONS | D18: =+'CAMABAJA INTERNACIONAL OJT166'!D17 -> EL DORADO, SECTOR LA ISLA RIO ARIARI | E18: =+'CAMABAJA INTERNACIONAL OJT166'!E17 -> 45784 | F18: =+'CAMABAJA INTERNACIONAL OJT166'!F17 -> 45784 | G18: =+'CAMABAJA INTERNACIONAL OJT166'!G17 -> 4 | H18: =+'CAMABAJA INTERNACIONAL OJT166'!H17 -> 0 | I18: =+'CAMABAJA INTERNACIONAL OJT166'!I17 -> NOS DIRIJIMOS DEL MUNICIPIO DE VILLAVICENCIO PARA TRANSPORTAR LA EXCAVADORA LINK BELT 2180 #5 DEL PATIO GALICIA SERVIMACONS PARA EL PUNTO DE TRABAJO EL DORADO, SECTOR LA ISLA RIO ARIARI Y NOS DIRIJIMOS AL MUNICIPIO DE GUAMAL
C19: =+'CAMABAJA INTERNACIONAL OJT166'!C18 -> VILLAVICENCIO - PATIO GALICIA SERVIMACONS | D19: =+'CAMABAJA INTERNACIONAL OJT166'!D18 -> EL DORADO, SECTOR LA ISLA RIO ARIARI | E19: =+'CAMABAJA INTERNACIONAL OJT166'!E18 -> 45784 | F19: =+'CAMABAJA INTERNACIONAL OJT166'!F18 -> 45784 | G19: =+'CAMABAJA INTERNACIONAL OJT166'!G18 -> 4 | H19: =+'CAMABAJA INTERNACIONAL OJT166'!H18 -> 0 | I19: =+'CAMABAJA INTERNACIONAL OJT166'!I18 -> NOS DIRIJIMOS DEL MUNICIPIO DE VILLAVICENCIO PARA TRANSPORTAR LA EXCAVADORA LINK BELT 2179 #4 DEL PUNTO DE TRABAJO PIO XII PARA EL PUNTO DE TRABAJO EL DORARO SECTOR LA ISLA RIO ARIARI Y NOS REGRESAMOS AL PATIO SERVIMACONS
C20: =+'CAMABAJA INTERNACIONAL OJT166'!C19 -> EL DORADO, SECTOR LA ISLA RIO ARIARI | D20: =+'CAMABAJA INTERNACIONAL OJT166'!D19 -> SECTOR PUERTO ESPERANZA | E20: =+'CAMABAJA INTERNACIONAL OJT166'!E19 -> 45794 | F20: =+'CAMABAJA INTERNACIONAL OJT166'!F19 -> 45794 | G20: =+'CAMABAJA INTERNACIONAL OJT166'!G19 -> 4 | H20: =+'CAMABAJA INTERNACIONAL OJT166'!H19 -> 0 | I20: =+'CAMABAJA INTERNACIONAL OJT166'!I19 -> NOS DIRIJIMOS DEL MUNICIPIO DE VILLAVICENCIO PARA TRANSPORTAR LA EXCAVADORA LINK BELT 2179 #4 DEL PUNTO DE TRABAJO SECTOR LA ISLA RIO ARIARI PARA EL PUNTO PUERTO ESPERANZA Y NOS REGRESAMOS AL PATIO SERVIMACONS
C21: =+'CAMABAJA INTERNACIONAL OJT166'!C20 -> GUAMAL, SECTOR LA ISLA RIO GUAMAL | D21: =+'CAMABAJA INTERNACIONAL OJT166'!D20 -> VILLAVICENCIO - PATIO GALICIA SERVIMACONS | E21: =+'CAMABAJA INTERNACIONAL OJT166'!E20 -> 45800 | F21: =+'CAMABAJA INTERNACIONAL OJT166'!F20 -> 45800 | G21: =+'CAMABAJA INTERNACIONAL OJT166'!G20 -> 4 | H21: =+'CAMABAJA INTERNACIONAL OJT166'!H20 -> 0 | I21: =+'CAMABAJA INTERNACIONAL OJT166'!I20 -> NOS DIRIJIMOS DEL MUNICIPIO DE VILLAVICENCIO PARA TRANSPORTAR LA EXCAVADORA LINK BELT 2183 #3 DEL PUNTO DE TRABAJO GUAMAL, SECTOR LA ISLA RIO ARIARI Y NOS REGRESAMOS AL PATIO SERVIMACONS
C22: =+'CAMABAJA INTERNACIONAL OJT166'!C21 -> EL DORADO, SECTOR LA ISLA RIO ARIARI | D22: =+'CAMABAJA INTERNACIONAL OJT166'!D21 -> VILLAVICENCIO - PATIO GALICIA SERVIMACONS | E22: =+'CAMABAJA INTERNACIONAL OJT166'!E21 -> 45801 | F22: =+'CAMABAJA INTERNACIONAL OJT166'!F21 -> 45801 | G22: =+'CAMABAJA INTERNACIONAL OJT166'!G21 -> 5 | H22: =+'CAMABAJA INTERNACIONAL OJT166'!H21 -> 0 | I22: =+'CAMABAJA INTERNACIONAL OJT166'!I21 -> NOS DIRIJIMOS DEL MUNICIPIO DE VILLAVICENCIO PARA TRANSPORTAR LA EXCAVADORA LINK BELT 2180 #5 DEL PUNTO DE TRABAJO EL DORADO, SECTOR LA ISLA Y NOS REGRESAMOS AL PATIO SERVIMACONS
C23: =+'CAMABAJA INTERNACIONAL OJT166'!C22 -> EL DORADO, SECTOR LA ISLA RIO ARIARI | D23: =+'CAMABAJA INTERNACIONAL OJT166'!D22 -> VILLAVICENCIO - PATIO GALICIA SERVIMACONS | E23: =+'CAMABAJA INTERNACIONAL OJT166'!E22 -> 45804 | F23: =+'CAMABAJA INTERNACIONAL OJT166'!F22 -> 45804 | G23: =+'CAMABAJA INTERNACIONAL OJT166'!G22 -> 4 | H23: =+'CAMABAJA INTERNACIONAL OJT166'!H22 -> 0 | I23: =+'CAMABAJA INTERNACIONAL OJT166'!I22 -> NOS DIRIJIMOS DEL MUNICIPIO DE VILLAVICENCIO PARA TRANSPORTAR LA EXCAVADORA LINK BELT 2179 #4 DEL PUNTO DE TRABAJO EL DORADO SECTOR LA ISLA Y NOS REGRESAMOS AL PATIO SERVIMACONS
C24: =+'CAMABAJA INTERNACIONAL OJT166'!C23 -> VILLAVICENCIO - PATIO GALICIA SERVIMACONS | D24: =+'CAMABAJA INTERNACIONAL OJT166'!D23 -> SAN CARLOS DE GUAROA, PUENTE TRES ARCOS | E24: =+'CAMABAJA INTERNACIONAL OJT166'!E23 -> 45825 | F24: =+'CAMABAJA INTERNACIONAL OJT166'!F23 -> 45825 | G24: =+'CAMABAJA INTERNACIONAL OJT166'!G23 -> 7 | H24: =+'CAMABAJA INTERNACIONAL OJT166'!H23 -> 0 | I24: =+'CAMABAJA INTERNACIONAL OJT166'!I23 -> NOS DIRIJIMOS DEL MUNICIPIO DE VILLAVICENCIO PARA TRANSPORTAR LA EXCAVADORA LINK BELT 2183 #3 DEL PATIO GALICIA SERVIMACONS PARA EL PUNTO DE TRABAJO SAN CARLOS DE GUAROA PUENTE TRES ARCOS
... C27: =+'CAMABAJA INTERNACIONAL OJT166'!C26 -> SAN CARLOS DE GUAROA, PUENTE TRES ARCOS | D27: =+'CAMABAJA INTERNACIONAL OJT166'!D26 -> VILLAVICENCIO - PATIO GALICIA SERVIMACONS | E27: =+'CAMABAJA INTERNACIONAL OJT166'!E26 -> 45839 | F27: =+'CAMABAJA INTERNACIONAL OJT166'!F26 -> 45839 | G27: =+'CAMABAJA INTERNACIONAL OJT166'!G26 -> 6 | H27: =+'CAMABAJA INTERNACIONAL OJT166'!H26 -> 0 | I27: =+'CAMABAJA INTERNACIONAL OJT166'!I26 -> NOS DIRIJIMMOS DEL MUNICIPIO DE VILLAVICENCIO PARA TRANSPORTAR LA EXCAVADORA LINK BELT 2183 #3 DEL PUNTO DE TRABAJO SAN CARLOS DE GUAROA PARA EL PATIO GALICIA SERVIMACONS
B29: SUBTOTAL | H29: =SUM(H10:H28) -> 0
B30: IVA 19% | H30: =+H29*0.19 -> 0
B31: TOTAL | H31: =+H30+H29 -> 0
B36: LUIS MIGUEL ANGEL RAMIREZ ROMERO
B37: Rep. Legal SERVICIOS MAQUINARIA Y CONSTRUCCIONES SAS "SERVIMACONS S.A.S."
B38: CONTRATISTA

Sheet 2
A1: RESUMEN GENERAL DE ACTIVIDADES EJECUTADAS
A2: CONTRATO Nº:
A3: OBJETO:
A4: PERIODO DEL INFORME: | F4: AL
A5: FECHA PRESENTE ACTA:
A8: ITEM | B8: DESCRIPCIÓN / MAQUINA | C8: MUNICIPIO | D8: PUNTO | E8: FECHA INICIO | F8: FECHA FINAL | G8: HORAS EJECUTADAS | H8: VALOR EJECUTADO | I8: ACTIVIDAD REALIZADA
A9: 2 | B9: FUNCIONAMIENTO Y OPERACIÓN DE BULLDOZER SOBRE ORUGA CATERPILLAR D6K XL
B10: =+'EL CALVARIO - CARMEN, BENITO'!B9 -> BULLDOZER CATERPILLAR 2765 #2 | C10: =+'EL CALVARIO - CARMEN, BENITO'!C9 -> nombre municipio | D10: =+'EL CALVARIO - CARMEN, BENITO'!D9 -> nombre punto | E10: =+'EL CALVARIO - CARMEN, BENITO'!E9 -> 45769 | F10: =+'EL CALVARIO - CARMEN, BENITO'!F9 -> 45783 | G10: =+'EL CALVARIO - CARMEN, BENITO'!G9 -> 100 | H10: =+'EL CALVARIO - CARMEN, BENITO'!H9 -> 0 | I10: =+'EL CALVARIO - CARMEN, BENITO'!I9 -> SE REALIZA REHABILITACIÓN DE VIA EN EL PUNTO LA PAILA, RECORRIDO DE LA MAQUINA DEL PUNTO LA PAILA PARA EL DERRUMBE EN LA VEREDA EL CARMEN
B11: =+'BULLDOZER CATERPILLAR 2765 #2.'!B9 -> BULLDOZER CATERPILLAR 2765 #2 | C11: =+'BULLDOZER CATERPILLAR 2765 #2.'!C9 -> EL CALVARIO | D11: =+'BULLDOZER CATERPILLAR 2765 #2.'!D9 -> SECTOR LAS BRUJAS | E11: =+'BULLDOZER CATERPILLAR 2765 #2.'!E9 -> 45814 | F11: =+'BULLDOZER CATERPILLAR 2765 #2.'!F9 -> 45825 | G11: =+'BULLDOZER CATERPILLAR 2765 #2.'!G9 -> 188 | H11: =+'BULLDOZER CATERPILLAR 2765 #2.'!H9 -> 0 | I11: =+'BULLDOZER CATERPILLAR 2765 #2.'!I9 -> MAQUINA DISPONIBLE EN EL PUNTO DE TRABAJO, SE PRESENTAN FUERTES LLUVIAS EN EL SECTOR
B12: =+#REF! -> #REF! | C12: =+#REF! -> #REF! | D12: =+#REF! -> #REF! | E12: =+#REF! -> #REF! | F12: =+#REF! -> #REF! | G12: =+#REF! -> #REF! | H12: =+#REF! -> #REF! | I12: =+#REF! -> #REF!
B13: SUBTOTAL | H13: =SUM(H10:H12) -> #REF!
B14: IVA 19% | H14: =+H13*0.19 -> #REF!
B15: TOTAL | H15: =+H14+H13 -> #REF!
B20: LUIS MIGUEL ANGEL RAMIREZ ROMERO
B21: Rep. Legal SERVICIOS MAQUINARIA Y CONSTRUCCIONES SAS "SERVIMACONS S.A.S."
B22: CONTRATISTA

Sheet 3
A1: RESUMEN GENERAL DE ACTIVIDADES EJECUTADAS
A2: CONTRATO Nº:
A3: OBJETO:
A4: PERIODO DEL INFORME: | F4: AL
A5: FECHA PRESENTE ACTA:
A8: ITEM | B8: DESCRIPCIÓN / MAQUINA | C8: MUNICIPIO | D8: PUNTO | E8: FECHA INICIO | F8: FECHA FINAL | G8: HORAS EJECUTADAS | H8: VALOR EJECUTADO | I8: ACTIVIDAD REALIZADA
A9: 3 | B9: FUNCIONAMIENTO Y OPERACIÓN DE EXCAVADORA SOBRE ORUGA LINK-BELT 210 X2, CAPACIDAD BALDE 1 M3 21 TONELADAS
B10: =+'BAJO POMPEYA - PALMARITO'!B9 -> EXCAVADORA LINK BELT 2181 #1 | C10: =+'BAJO POMPEYA - PALMARITO'!C9 -> VILLAVICENCIO | D10: =+'BAJO POMPEYA - PALMARITO'!D9 -> BAJO POMPEYA SECTOR PALMARITO, RIO GUAYURIBA | E10: =+'BAJO POMPEYA - PALMARITO'!E9 -> 45755 | F10: =+'BAJO POMPEYA - PALMARITO'!F9 -> 45777 | G10: =+'BAJO POMPEYA - PALMARITO'!G9 -> 127.2 | H10: =+'BAJO POMPEYA - PALMARITO'!H9 -> 0 | I10: =+'BAJO POMPEYA - PALMARITO'!I9 -> SE REALIZA EXCAVACIÓN EN EL CANAL PARA CONSTRUCIÓN DEL JARILLON Y PODER DESVIAR EL RIO
B11: =+'BAJO POMPEYA - PALMARITO'!B10 -> EXCAVADORA LINK BELT 2180 #5 | C11: =+'BAJO POMPEYA - PALMARITO'!C10 -> VILLAVICENCIO | D11: =+'BAJO POMPEYA - PALMARITO'!D10 -> BAJO POMPEYA SECTOR PALMARITO, RIO GUAYURIBA | E11: =+'BAJO POMPEYA - PALMARITO'!E10 -> 45755 | F11: =+'BAJO POMPEYA - PALMARITO'!F10 -> 45777 | G11: =+'BAJO POMPEYA - PALMARITO'!G10 -> 122.8 | H11: =+'BAJO POMPEYA - PALMARITO'!H10 -> 0 | I11: =+'BAJO POMPEYA - PALMARITO'!I10 -> SE REALIZA EXCAVACIÓN PARA DESVIAR UN BRAZO DEL RIO QUE ESTA RECOSTADO EN LA MARGEN IZQUIERDA
B12: =+'EXCA LINK BELT 2183 #3'!B9 -> EXCAVADORA LINK BELT 2183 #3 | C12: =+'EXCA LINK BELT 2183 #3'!C9 -> GUAMAL | D12: =+'EXCA LINK BELT 2183 #3'!D9 -> SECTOR LA ISLA, RIO GUAMAL | E12: =+'EXCA LINK BELT 2183 #3'!E9 -> 45757 | F12: =+'EXCA LINK BELT 2183 #3'!F9 -> 45800 | G12: =+'EXCA LINK BELT 2183 #3'!G9 -> 270 | H12: =+'EXCA LINK BELT 2183 #3'!H9 -> 0 | I12: =+'EXCA LINK BELT 2183 #3'!I9 -> SE REALIZA EXCAVACIÓN PARA CONSTRUCCIÓN DE UN JARILLON DE PROTECCIÓN
B13: =+'EXCA LINK BELT 2179 #4'!B9 -> EXCAVADORA LINK BELT 2179 #4 | C13: =+'EXCA LINK BELT 2179 #4'!C9 -> GUAMAL | D13: =+'EXCA LINK BELT 2179 #4'!D9 -> SECTOR PIO XII, RIO GUAMAL | E13: =+'EXCA LINK BELT 2179 #4'!E9 -> 45757 | F13: =+'EXCA LINK BELT 2179 #4'!F9 -> 45784 | G13: =+'EXCA LINK BELT 2179 #4'!G9 -> 130 | H13: =+'EXCA LINK BELT 2179 #4'!H9 -> 0 | I13: =+'EXCA LINK BELT 2179 #4'!I9 -> SE REALIZA CONSTRUCCIÓN DE JARILLON PARA QUITAR PRESION DE LA MARGEN IZQUIERDA AGUAS ABAJO Y SE CENTRA PARTE DEL RIO
B14: =+'EL CASTILLO-PUENTE LA AMISTAD'!B9 -> EXCAVADORA LINK BELT 2181 #1 | C14: =+'EL CASTILLO-PUENTE LA AMISTAD'!C9 -> EL CASTILLO | D14: =+'EL CASTILLO-PUENTE LA AMISTAD'!D9 -> PUENTE LA AMISTAD, RIO ARIARI | E14: =+'EL CASTILLO-PUENTE LA AMISTAD'!E9 -> 45779 | F14: =+'EL CASTILLO-PUENTE LA AMISTAD'!F9 -> 45793 | G14: =+'EL CASTILLO-PUENTE LA AMISTAD'!G9 -> 106.5 | H14: =+'EL CASTILLO-PUENTE LA AMISTAD'!H9 -> 0 | I14: =+'EL CASTILLO-PUENTE LA AMISTAD'!I9 -> SE TRANSPALEA MATERIAL PARA AMPLIACIÓN DE CANAL EN EL RIO ARIARI
B15: =+'EL CASTILLO-PUENTE LA AMISTAD'!B10 -> EXCAVADORA LINK BELT 2180 #5 | C15: =+'EL CASTILLO-PUENTE LA AMISTAD'!C10 -> EL CASTILLO | D15: =+'EL CASTILLO-PUENTE LA AMISTAD'!D10 -> PUENTE LA AMISTAD, RIO ARIARI | E15: =+'EL CASTILLO-PUENTE LA AMISTAD'!E10 -> 45784 | F15: =+'EL CASTILLO-PUENTE LA AMISTAD'!F10 -> 45802 | G15: =+'EL CASTILLO-PUENTE LA AMISTAD'!G10 -> 107.8 | H15: =+'EL CASTILLO-PUENTE LA AMISTAD'!H10 -> 0 | I15: =+'EL CASTILLO-PUENTE LA AMISTAD'!I10 -> SE REALIZA LA CONSTRUCCIÓN DEL CANAL PARA DESVIO DEL CAUCE DEL RIO
B16: =+'EL CASTILLO-PUENTE LA AMISTAD'!B11 -> EXCAVADORA LINK BELT 2179 #4 | C16: =+'EL CASTILLO-PUENTE LA AMISTAD'!C11 -> EL CASTILLO | D16: =+'EL CASTILLO-PUENTE LA AMISTAD'!D11 -> PUENTE LA AMISTAD, RIO ARIARI | E16: =+'EL CASTILLO-PUENTE LA AMISTAD'!E11 -> 45784 | F16: =+'EL CASTILLO-PUENTE LA AMISTAD'!F11 -> 45804 | G16: =+'EL CASTILLO-PUENTE LA AMISTAD'!G11 -> 8.7 | H16: =+'EL CASTILLO-PUENTE LA AMISTAD'!H11 -> 0 | I16: =+'EL CASTILLO-PUENTE LA AMISTAD'!I11 -> SE REALIZA LA CONSTRUCCIÓN DEL CANAL PARA DESVIO DEL CAUCE DEL RIO
B17: =+'EXCA LINK BELT 2181. #1'!B9 -> EXCAVADORA LINK BELT 2181 #1 | C17: =+'EXCA LINK BELT 2181. #1'!C9 -> EL CASTILLO | D17: =+'EXCA LINK BELT 2181. #1'!D9 -> PUERTO ESPERANZA, RIO LA CAL | E17: =+'EXCA LINK BELT 2181. #1'!E9 -> 45794 | F17: =+'EXCA LINK BELT 2181. #1'!F9 -> 45807 | G17: =+'EXCA LINK BELT 2181. #1'!G9 -> 117 | H17: =+'EXCA LINK BELT 2181. #1'!H9 -> 0 | I17: =+'EXCA LINK BELT 2181. #1'!I9 -> EXCAVACIÓN PARA CANAL Y SE CONFORMA JARILLON DE PROTECCIÓN
B18: =+'EXCA LINK BEL T 2179 #.4'!B9 -> EXCAVADORA LINK BELT 2119 #4 | C18: =+'EXCA LINK BEL T 2179 #.4'!C9 -> EL DORADO | D18: =+'EXCA LINK BEL T 2179 #.4'!D9 -> RIO ARIARI | E18: =+'EXCA LINK BEL T 2179 #.4'!E9 -> 45825 | F18: =+'EXCA LINK BEL T 2179 #.4'!F9 -> 45849 | G18: =+'EXCA LINK BEL T 2179 #.4'!G9 -> 100 | H18: =+'EXCA LINK BEL T 2179 #.4'!H9 -> 0 | I18: =+'EXCA LINK BEL T 2179 #.4'!I9 -> SE REALIZA EXCAVACIÓN PARA CONFORMACIÓN DE JARILLON DE PROTECCIÓN
B19: =+'EXCA LINK BEL T 2183 #3'!B9 -> EXCAVADORA LINK BELT 2183 #3 | C19: =+'EXCA LINK BEL T 2183 #3'!C9 -> SAN CARLOS DE GUAROA | D19: =+'EXCA LINK BEL T 2183 #3'!D9 -> SECTOR PUENTE TRES ARCOS | E19: =+'EXCA LINK BEL T 2183 #3'!E9 -> 45821 | F19: =+'EXCA LINK BEL T 2183 #3'!F9 -> 45838 | G19: =+'EXCA LINK BEL T 2183 #3'!G9 -> 100 | H19: =+'EXCA LINK BEL T 2183 #3'!H9 -> 0 | I19: =+'EXCA LINK BEL T 2183 #3'!I9 -> SE REALIZA ENROCADO EN LA MARGEN DERECHA AGUAS ABAJO PARA MITIGAR DESBORDAMIENTO EN EL TERRAPLEN DE LA CARRETERA Y REHABILITAR EL PASO EN EL PUENTE
B20: =+#REF! -> #REF! | C20: =+#REF! -> #REF! | D20: =+#REF! -> #REF! | E20: =+#REF! -> #REF! | F20: =+#REF! -> #REF! | G20: =+#REF! -> #REF! | H20: =+#REF! -> #REF! | I20: =+#REF! -> #REF!
B22: SUBTOTAL | H22: =SUM(H10:H21) -> #REF!
B23: IVA 19% | H23: =+H22*0.19 -> #REF!
B24: TOTAL | H24: =+H23+H22 -> #REF!
B29: LUIS MIGUEL ANGEL RAMIREZ ROMERO
B30: Rep. Legal SERVICIOS MAQUINARIA Y CONSTRUCCIONES SAS "SERVIMACONS S.A.S."
B31: CONTRATISTA

Sheet 4
A1: RESUMEN GENERAL DE ACTIVIDADES EJECUTADAS
A2: CONTRATO Nº:
A3: OBJETO:
A4: PERIODO DEL INFORME: | F4: AL
A5: FECHA PRESENTE ACTA:
A8: ITEM | B8: DESCRIPCIÓN / MAQUINA | C8: MUNICIPIO | D8: PUNTO | E8: FECHA INICIO | F8: FECHA FINAL | G8: HORAS EJECUTADAS | H8: VALOR EJECUTADO | I8: ACTIVIDAD REALIZADA
A9: 4 | B9: FUNCIONAMIENTO Y OPERACIÓN DE VOLQUETA SENCILLA FTR CHEVROLET
B10: =+'VILLAVICENCIO - PARCELAS'!B9 -> VOLQUETA CHEVROLET OJT163 #3 | C10: =+'VILLAVICENCIO - PARCELAS'!C9 -> VILLAVICENCIO | D10: =+'VILLAVICENCIO - PARCELAS'!D9 -> PARCELAS DEL PROGRESO | E10: =+'VILLAVICENCIO - PARCELAS'!E9 -> 45789 | F10: =+'VILLAVICENCIO - PARCELAS'!F9 -> 45796 | G10: =+'VILLAVICENCIO - PARCELAS'!G9 -> 65.4 | H10: =+'VILLAVICENCIO - PARCELAS'!H9 -> 0 | I10: =+'VILLAVICENCIO - PARCELAS'!I9 -> TRANSPORTE DE MATERIAL DEL RIO GUATIQUIA PARA CONSTRUCCIÓN DEL JARILLON
B11: =+'VILLAVICENCIO - PARCELAS'!B10 -> VOLQUETA CHEVROLET OJT165 #5 | C11: =+'VILLAVICENCIO - PARCELAS'!C10 -> VILLAVICENCIO | D11: =+'VILLAVICENCIO - PARCELAS'!D10 -> PARCELAS DEL PROGRESO | E11: =+'VILLAVICENCIO - PARCELAS'!E10 -> 45789 | F11: =+'VILLAVICENCIO - PARCELAS'!F10 -> 45796 | G11: =+'VILLAVICENCIO - PARCELAS'!G10 -> 65 | H11: =+'VILLAVICENCIO - PARCELAS'!H10 -> 0 | I11: =+'VILLAVICENCIO - PARCELAS'!I10 -> TRANSPORTE DE MATERIAL DEL RIO GUATIQUIA PARA CONSTRUCCIÓN DEL JARILLON
B12: =+'VILLAVICENCIO - PARCELAS'!B11 -> VOLQUETA CHEVROLET OJT162 #2 | C12: =+'VILLAVICENCIO - PARCELAS'!C11 -> VILLAVICENCIO | D12: =+'VILLAVICENCIO - PARCELAS'!D11 -> PARCELAS DEL PROGRESO | E12: =+'VILLAVICENCIO - PARCELAS'!E11 -> 45790 | F12: =+'VILLAVICENCIO - PARCELAS'!F11 -> 45793 | G12: =+'VILLAVICENCIO - PARCELAS'!G11 -> 19.6 | H12: =+'VILLAVICENCIO - PARCELAS'!H11 -> 0 | I12: =+'VILLAVICENCIO - PARCELAS'!I11 -> TRANSPORTE DE MATERIAL DEL RIO GUATIQUIA PARA CONSTRUCCIÓN DEL JARILLON
B13: SUBTOTAL | H13: =SUM(H10:H12) -> 0
B14: IVA 19% | H14: =+H13*0.19 -> 0
B15: TOTAL | H15: =+H14+H13 -> 0
B20: LUIS MIGUEL ANGEL RAMIREZ ROMERO
B21: Rep. Legal SERVICIOS MAQUINARIA Y CONSTRUCCIONES SAS "SERVIMACONS S.A.S."
B22: CONTRATISTA

Sheet 5
A1: RESUMEN GENERAL DE ACTIVIDADES EJECUTADAS
A2: CONTRATO Nº:
A3: OBJETO:
A4: PERIODO DEL INFORME: | F4: AL
A5: FECHA PRESENTE ACTA:
A8: ITEM | B8: DESCRIPCIÓN / MAQUINA | C8: MUNICIPIO | D8: PUNTO | E8: FECHA INICIO | F8: FECHA FINAL | G8: HORAS EJECUTADAS | H8: VALOR EJECUTADO | I8: ACTIVIDAD REALIZADA
A9: 5 | B9: FUNCIONAMIENTO Y OPERACIÓN DE RETROEXCAVADORA CATERPILLAR 416 E
B10: =+'EL CALVARIO - VIA MONFORTH'!B9 -> RETROEXCAVADORA CATERPILLAR 8585 416E | C10: =+'EL CALVARIO - VIA MONFORTH'!C9 -> nombre del municipio | D10: =+'EL CALVARIO - VIA MONFORTH'!D9 -> nombre del punto | E10: =+'EL CALVARIO - VIA MONFORTH'!E9 -> 45775 | F10: =+'EL CALVARIO - VIA MONFORTH'!F9 -> 45833 | G10: =+'EL CALVARIO - VIA MONFORTH'!G9 -> 81 | H10: =+'EL CALVARIO - VIA MONFORTH'!H9 -> 0 | I10: =+'EL CALVARIO - VIA MONFORTH'!I9 -> REHABILITACIÓN DE LA VIA MONFORTH Y CONFORMACIÓN DE CUNETAS
B11: =+'RETROEXCAVADORA 8585 416.E'!B9 -> RETROEXCAVADORA CATERPILLAR 8585 416E | C11: =+'RETROEXCAVADORA 8585 416.E'!C9 -> EL CALVARIO | D11: =+'RETROEXCAVADORA 8585 416.E'!D9 -> VIA MONFORTH | E11: =+'RETROEXCAVADORA 8585 416.E'!E9 -> 45833 | F11: =+'RETROEXCAVADORA 8585 416.E'!F9 -> 45839 | G11: =+'RETROEXCAVADORA 8585 416.E'!G9 -> 50 | H11: =+'RETROEXCAVADORA 8585 416.E'!H9 -> 0 | I11: =+'RETROEXCAVADORA 8585 416.E'!I9 -> REHABILITACIÓN DE VIA Y CONFORMACIÓN DE CUNETAS
B12: SUBTOTAL | H12: =SUM(H10:H11) -> 0
B13: IVA 19% | H13: =+H12*0.19 -> 0
B14: TOTAL | H14: =+H13+H12 -> 0
B19: LUIS MIGUEL ANGEL RAMIREZ ROMERO
B20: Rep. Legal SERVICIOS MAQUINARIA Y CONSTRUCCIONES SAS "SERVIMACONS S.A.S."
B21: CONTRATISTA

Sheet CAMABAJA

Sheet CAMABAJA INTERNACIONAL OJT166
A1: RESUMEN GENERAL DE ACTIVIDADES EJECUTADAS
A2: CONTRATO Nº: 1040 DE 2025
A3: OBJETIVO: CONTRATO No: SERVICIO PARA LA OPERACIÓN DE LA MAQUINARIA AMARILLA ADSCRITA A LA DIRECCIÓN DEPARTAMENTAL PARA LA GESTIÓN DEL RIESGO DE DESASTRES PARA LA REDUCCIÓN DEL RIESGO EN LOS VEINTINUEVE (29) MUNICIPIOS DEL DEPARTAMENTO DEL META.
A4: PERIODO DEL INFORME: | F4: AL
A5: FECHA PRESENTE ACTA:
A8: ITEM | B8: D E S C R I P C I Ó N / MAQUINA | C8: MUNICIPIO | D8: PUNTO | E8: FECHA INICIO | F8: FECHA FINAL | G8: HORAS EJECUTADAS | H8: VALOR EJECUTADO | I8: ACTIVIDAD REALIZADA
A9: 1 | B9: =+'CAMABAJA OJT166'!C6 -> CAMABAJA INTERNATIONAL OJT166 | C9: =+'CAMABAJA OJT166'!C10 -> VILLAVICENCIO - PATIO GALICIA SERVIMACONS | D9: =+'CAMABAJA OJT166'!D10 -> BAJO POMPEYA SECTOR PALMARITO, RIO GUAYURIBA | E9: =+'CAMABAJA OJT166'!B10 -> 45755 | F9: =+E9 -> 45755 | G9: =+'CAMABAJA OJT166'!H10 -> 4 | H9: 0 | I9: =+'CAMABAJA OJT166'!I10 -> NOS DIRIJIMOS DEL MUNICIPIO DE VILLAVICENCIO PARA TRANSPORTAR LA EXCAVADORA LINK BELT 2181 #1 DEL PATIO GALICIA SERVIMACONS PARA EL PUNTO DE TRABAJO BAJO POMPEYA SECTOR PALMARITO, RIO GUAYURIBA Y NOS REGRESAMOS AL PATIO SERVIMACONS
C10: =+'CAMABAJA OJT166'!C11 -> VILLAVICENCIO - PATIO GALICIA SERVIMACONS | D10: =+'CAMABAJA OJT166'!D11 -> BAJO POMPEYA SECTOR PALMARITO, RIO GUAYURIBA | E10: =+'CAMABAJA OJT166'!B11 -> 45755 | F10: =+E10 -> 45755 | G10: =+'CAMABAJA OJT166'!H11 -> 4 | H10: 0 | I10: =+'CAMABAJA OJT166'!I11 -> NOS DIRIJIMOS DEL MUNICIPIO DE VILLAVICENCIO PARA TRANSPORTAR LA EXCAVADORA LINK BELT 2180 #5 DEL PATIO GALICIA SERVIMACONS PARA EL PUNTO DE TRABAJO BAJO POMPEYA SECTOR PALMARITO, RIO GUAYURIBA Y NOS REGRESAMOS AL PATIO SERVIMACONS
C11: =+'CAMABAJA OJT166'!C12 -> VILLAVICENCIO - PATIO GALICIA SERVIMACONS | D11: =+'CAMABAJA OJT166'!D12 -> SECTOR LA ISLA, RIO GUAMAL | E11: =+'CAMABAJA OJT166'!B12 -> 45756 | F11: =+E11 -> 45756 | G11: =+'CAMABAJA OJT166'!H12 -> 8 | H11: 0 | I11: =+'CAMABAJA OJT166'!I12 -> NOS DIRIJIMOS DEL MUNICIPIO DE VILLAVICENCIO PARA TRANSPORTAR LA EXCAVADORA LINK BELT 2183 #3 DEL PATIO GALICIA SERVIMACONS PARA EL PUNTO DE TRABAJO SECTOR LA ISLA RIO GUAMAL Y NOS REGRESAMOS AL PATIO SERVIMACONS
C12: =+'CAMABAJA OJT166'!C13 -> VILLAVICENCIO - PATIO GALICIA SERVIMACONS | D12: =+'CAMABAJA OJT166'!D13 -> SECTOR PIO XII, RIO GUAMAL | E12: =+'CAMABAJA OJT166'!B13 -> 45757 | F12: =+'CAMABAJA OJT166'!B13 -> 45757 | G12: =+'CAMABAJA OJT166'!H13 -> 4 | H12: 0 | I12: =+'CAMABAJA OJT166'!I13 -> NOS DIRIJIMOS DEL MUNICIPIO DE VILLAVICENCIO PARA TRANSPORTAR LA EXCAVADORA LINK BELT 2179 #4 DEL PATIO GALICIA SERVIMACONS PARA EL PUNTO DE TRABAJO SECTOR PIO XII RIO GUAMAL Y NOS REGRESAMOS AL PATIO SERVIMACONS
C13: =+'CAMABAJA OJT166'!C14 -> EL CALVARIO | D13: =+'CAMABAJA OJT166'!D14 -> VIA MONFORTH | E13: =+'CAMABAJA OJT166'!B14 -> 45770 | F13: =+'CAMABAJA OJT166'!B14 -> 45770 | G13: =+'CAMABAJA OJT166'!H14 -> 3 | H13: 0 | I13: =+'CAMABAJA OJT166'!I14 -> NOS DIRIJIMOS DEL MUNICIPIO DE VILLAVICENCIO PARA TRANSPORTAR LA RETROEXCAVADORA CATERPILLAR 8585 416E DEL PATIO GALICIA SERVIMACONS PARA LA VIA MONFORTH Y NOS REGRESAMOS AL PATIO SERVIMACONS
C14: =+'CAMABAJA OJT166'!C15 -> BAJO POMPEYA SECTOR PALMARITO, RIO GUAYURIBA | D14: =+'CAMABAJA OJT166'!D15 -> VILLAVICENCIO - PATIO GALICIA SERVIMACONS | E14: =+'CAMABAJA OJT166'!B15 -> 45777 | F14: =+'CAMABAJA OJT166'!B15 -> 45777 | G14: =+'CAMABAJA OJT166'!H15 -> 4 | H14: 0 | I14: =+'CAMABAJA OJT166'!I15 -> NOS DIRIJIMOS DEL MUNICIPIO DE VILLAVICENCIO PARA TRANSPORTAR LA EXCAVADORA LINK BELT 2181 #1 DEL PUNTO DE TRABAJO BAJO POMPEYA PARA EL PATIO GALICIA SERVIMACONS
C15: =+'CAMABAJA OJT166'!C16 -> BAJO POMPEYA SECTOR PALMARITO, RIO GUAYURIBA | D15: =+'CAMABAJA OJT166'!D16 -> VILLAVICENCIO - PATIO GALICIA SERVIMACONS | E15: =+'CAMABAJA OJT166'!B16 -> 45777 | F15: =+'CAMABAJA OJT166'!B16 -> 45777 | G15: =+'CAMABAJA OJT166'!H16 -> 4 | H15: 0 | I15: =+'CAMABAJA OJT166'!I16 -> NOS DIRIJIMOS DEL MUNICIPIO DE VILLAVICENCIO PARA TRANSPORTAR LA EXCAVADORA LINK BELT 2180 #5 DEL PUNTO DE TRABAJO BAJO POMPEYA PARA EL PATIO GALICIA SERVIMACONS
C16: =+'CAMABAJA OJT166'!C17 -> VILLAVICENCIO - PATIO GALICIA SERVIMACONS | D16: =+'CAMABAJA OJT166'!D17 -> EL DORADO, SECTOR LA ISLA RIO ARIARI | E16: =+'CAMABAJA OJT166'!B17 -> 45778 | F16: =+'CAMABAJA OJT166'!B17 -> 45778 | G16: =+'CAMABAJA OJT166'!H17 -> 5 | H16: 0 | I16: =+'CAMABAJA OJT166'!I17 -> NOS DIRIJIMOS DEL MUNICIPIO DE VILLAVICENCIO PARA TRANSPORTAR LA EXCAVADORA LINK BELT 2181 #1 DEL PATIO SERVIMACONS PARA EL PUNTO DE TRABAJO EL DORADO PUENTE LA AMISTAD Y NOS REGRESAMOS AL PATIO SERVIMACONS
C17: =+'CAMABAJA OJT166'!C18 -> VILLAVICENCIO - PATIO GALICIA SERVIMACONS | D17: =+'CAMABAJA OJT166'!D18 -> EL DORADO, SECTOR LA ISLA RIO ARIARI | E17: =+'CAMABAJA OJT166'!B18 -> 45784 | F17: =+'CAMABAJA OJT166'!B18 -> 45784 | G17: =+'CAMABAJA OJT166'!H18 -> 4 | H17: 0 | I17: =+'CAMABAJA OJT166'!I18 -> NOS DIRIJIMOS DEL MUNICIPIO DE VILLAVICENCIO PARA TRANSPORTAR LA EXCAVADORA LINK BELT 2180 #5 DEL PATIO GALICIA SERVIMACONS PARA EL PUNTO DE TRABAJO EL DORADO, SECTOR LA ISLA RIO ARIARI Y NOS DIRIJIMOS AL MUNICIPIO DE GUAMAL
C18: =+'CAMABAJA OJT166'!C19 -> VILLAVICENCIO - PATIO GALICIA SERVIMACONS | D18: =+'CAMABAJA OJT166'!D19 -> EL DORADO, SECTOR LA ISLA RIO ARIARI | E18: =+'CAMABAJA OJT166'!B19 -> 45784 | F18: =+'CAMABAJA OJT166'!B19 -> 45784 | G18: =+'CAMABAJA OJT166'!H19 -> 4 | H18: 0 | I18: =+'CAMABAJA OJT166'!I19 -> NOS DIRIJIMOS DEL MUNICIPIO DE VILLAVICENCIO PARA TRANSPORTAR LA EXCAVADORA LINK BELT 2179 #4 DEL PUNTO DE TRABAJO PIO XII PARA EL PUNTO DE TRABAJO EL DORARO SECTOR LA ISLA RIO ARIARI Y NOS REGRESAMOS AL PATIO SERVIMACONS
C19: =+'CAMABAJA OJT166'!C20 -> EL DORADO, SECTOR LA ISLA RIO ARIARI | D19: =+'CAMABAJA OJT166'!D20 -> SECTOR PUERTO ESPERANZA | E19: =+'CAMABAJA OJT166'!B20 -> 45794 | F19: =+'CAMABAJA OJT166'!B20 -> 45794 | G19: =+'CAMABAJA OJT166'!H20 -> 4 | H19: 0 | I19: =+'CAMABAJA OJT166'!I20 -> NOS DIRIJIMOS DEL MUNICIPIO DE VILLAVICENCIO PARA TRANSPORTAR LA EXCAVADORA LINK BELT 2179 #4 DEL PUNTO DE TRABAJO SECTOR LA ISLA RIO ARIARI PARA EL PUNTO PUERTO ESPERANZA Y NOS REGRESAMOS AL PATIO SERVIMACONS
C20: =+'CAMABAJA OJT166'!C21 -> GUAMAL, SECTOR LA ISLA RIO GUAMAL | D20: =+'CAMABAJA OJT166'!D21 -> VILLAVICENCIO - PATIO GALICIA SERVIMACONS | E20: =+'CAMABAJA OJT166'!B21 -> 45800 | F20: =+'CAMABAJA OJT166'!B21 -> 45800 | G20: =+'CAMABAJA OJT166'!H21 -> 4 | H20: =+G20*'PLAN DE ACCIÓN'!$H$51 -> 0 | I20: =+'CAMABAJA OJT166'!I21 -> NOS DIRIJIMOS DEL MUNICIPIO DE VILLAVICENCIO PARA TRANSPORTAR LA EXCAVADORA LINK BELT 2183 #3 DEL PUNTO DE TRABAJO GUAMAL, SECTOR LA ISLA RIO ARIARI Y NOS REGRESAMOS AL PATIO SERVIMACONS
C21: =+'CAMABAJA OJT166'!C22 -> EL DORADO, SECTOR LA ISLA RIO ARIARI | D21: =+'CAMABAJA OJT166'!D22 -> VILLAVICENCIO - PATIO GALICIA SERVIMACONS | E21: =+'CAMABAJA OJT166'!B22 -> 45801 | F21: =+'CAMABAJA OJT166'!B22 -> 45801 | G21: =+'CAMABAJA OJT166'!H22 -> 5 | H21: =+G21*'PLAN DE ACCIÓN'!$H$51 -> 0 | I21: =+'CAMABAJA OJT166'!I22 -> NOS DIRIJIMOS DEL MUNICIPIO DE VILLAVICENCIO PARA TRANSPORTAR LA EXCAVADORA LINK BELT 2180 #5 DEL PUNTO DE TRABAJO EL DORADO, SECTOR LA ISLA Y NOS REGRESAMOS AL PATIO SERVIMACONS
C22: =+'CAMABAJA OJT166'!C23 -> EL DORADO, SECTOR LA ISLA RIO ARIARI | D22: =+'CAMABAJA OJT166'!D23 -> VILLAVICENCIO - PATIO GALICIA SERVIMACONS | E22: =+'CAMABAJA OJT166'!B23 -> 45804 | F22: =+'CAMABAJA OJT166'!B23 -> 45804 | G22: =+'CAMABAJA OJT166'!H23 -> 4 | H22: =+G22*'PLAN DE ACCIÓN'!$H$51 -> 0 | I22: =+'CAMABAJA OJT166'!I23 -> NOS DIRIJIMOS DEL MUNICIPIO DE VILLAVICENCIO PARA TRANSPORTAR LA EXCAVADORA LINK BELT 2179 #4 DEL PUNTO DE TRABAJO EL DORADO SECTOR LA ISLA Y NOS REGRESAMOS AL PATIO SERVIMACONS
C23: =+'CAMABAJA OJT166'!C24 -> VILLAVICENCIO - PATIO GALICIA SERVIMACONS | D23: =+'CAMABAJA OJT166'!D24 -> SAN CARLOS DE GUAROA, PUENTE TRES ARCOS | E23: =+'CAMABAJA OJT166'!B24 -> 45825 | F23: =+'CAMABAJA OJT166'!B24 -> 45825 | G23: =+'CAMABAJA OJT166'!H24 -> 7 | H23: =+G23*'PLAN DE ACCIÓN'!$H$51 -> 0 | I23: =+'CAMABAJA OJT166'!I24 -> NOS DIRIJIMOS DEL MUNICIPIO DE VILLAVICENCIO PARA TRANSPORTAR LA EXCAVADORA LINK BELT 2183 #3 DEL PATIO GALICIA SERVIMACONS PARA EL PUNTO DE TRABAJO SAN CARLOS DE GUAROA PUENTE TRES ARCOS
C24: =+'CAMABAJA OJT166'!C25 -> VILLAVICENCIO - PATIO GALICIA SERVIMACONS | D24: =+'CAMABAJA OJT166'!D25 -> SAN CARLOS DE GUAROA, PUENTE TRES ARCOS | E24: =+'CAMABAJA OJT166'!B25 -> 45826 | F24: =+'CAMABAJA OJT166'!B25 -> 45826 | G24: =+'CAMABAJA OJT166'!H25 -> 6 | H24: =+G24*'PLAN DE ACCIÓN'!$H$51 -> 0 | I24: =+'CAMABAJA OJT166'!I25 -> NOS DIRIJIMOS DEL MUNICIPIO DE VILLAVICENCIO PARA TRANSPORTAR LA EXCAVADORA LINK BELT 2179 #4 DEL PATIO GALICIA SERVIMACONS PARA EL PUNTO DE TRABAJO PUENNTE LA AMISTAD Y NOS REGRESAMOS AL PATIO SERVIMACONS
C25: =+'CAMABAJA OJT166'!C26 -> SECTOR PUERTO ESPERANZA | D25: =+'CAMABAJA OJT166'!D26 -> PUERTO LLERAS, CAÑO IRACA | E25: =+'CAMABAJA OJT166'!B26 -> 45827 | F25: =+'CAMABAJA OJT166'!B26 -> 45827 | G25: =+'CAMABAJA OJT166'!H26 -> 10 | H25: =+G25*'PLAN DE ACCIÓN'!$H$51 -> 0 | I25: =+'CAMABAJA OJT166'!I26 -> NOS DIRIJIMOS DEL MUNICIPIO DE VILLAVICENCIO PARA TRANSPORTAR LA EXCAVADORA LINK BELT 2181 #1 DEL PUNTO PUERTO ESPERANZA PARA EL PUNTO DE TRABAJO PUERTO LLERAS Y NOS REGRESAMOS AL PATIO SERVIMACONS
C26: =+'CAMABAJA OJT166'!C27 -> SAN CARLOS DE GUAROA, PUENTE TRES ARCOS | D26: =+'CAMABAJA OJT166'!D27 -> VILLAVICENCIO - PATIO GALICIA SERVIMACONS | E26: =+'CAMABAJA OJT166'!B27 -> 45839 | F26: =+'CAMABAJA OJT166'!B27 -> 45839 | G26: =+'CAMABAJA OJT166'!H27 -> 6 | H26: =+G26*'PLAN DE ACCIÓN'!$H$51 -> 0 | I26: =+'CAMABAJA OJT166'!I27 -> NOS DIRIJIMMOS DEL MUNICIPIO DE VILLAVICENCIO PARA TRANSPORTAR LA EXCAVADORA LINK BELT 2183 #3 DEL PUNTO DE TRABAJO SAN CARLOS DE GUAROA PARA EL PATIO GALICIA SERVIMACONS
C27: =+'CAMABAJA OJT166'!C28 -> VILLAVICENCIO - PATIO GALICIA SERVIMACONS | D27: =+'CAMABAJA OJT166'!D28 -> GUAMAL - SECTOR PIO XII, RIO GUAMAL | E27: =+'CAMABAJA OJT166'!B28 -> 45840 | F27: =+'CAMABAJA OJT166'!B28 -> 45840 | G27: =+'CAMABAJA OJT166'!H28 -> 6 | H27: =+G27*'PLAN DE ACCIÓN'!$H$51 -> 0 | I27: =+'CAMABAJA OJT166'!I28 -> NOS DIRIJIMOS DEL MUNICIPIO DE VILLAVICENCIO PARA TRANSPORTAR LA EXCAVADORA LINK BELT 2180 #5 DEL PATIO GALICIA SERVIMACONS PARA EL PUNTO DE TRABAJO GUAMAL SECTOR PIO XII Y NOS REGRESAMOS AL PATIO SERVIMACONS
C28: =+'CAMABAJA OJT166'!C29 -> GUAMAL - SECTOR PIO XII, RIO GUAMAL | D28: =+'CAMABAJA OJT166'!D29 -> VILLAVICENCIO - PATIO GALICIA SERVIMACONS | E28: =+'CAMABAJA OJT166'!B29 -> 45847 | F28: =+'CAMABAJA OJT166'!B29 -> 45847 | G28: =+'CAMABAJA OJT166'!H29 -> 6 | H28: =+G28*'PLAN DE ACCIÓN'!$H$51 -> 0 | I28: =+'CAMABAJA OJT166'!I29 -> NOS DIRIJIMOS DEL MUNICIPIO DE VILLAVICENCIO PARA TRANSPORTAR LA EXCAVADORA LINK BELT 2180 #5 DEL PUNTO DE TRABAJO GUAMAL PIO XII PARA EL PATIO GALICIA SERVIMACONS
B31: SUBTOTAL | H31: =SUM(H9:H30) -> 0
B32: IVA 19% | H32: =+H31*0.19 -> 0
B33: TOTAL | H33: =+H32+H31 -> 0
B45: LUIS MIGUEL ANGEL RAMIREZ ROMERO
B46: Rep. Legal SERVICIOS MAQUINARIA Y CONSTRUCCIONES SAS "SERVIMACONS S.A.S."
B47: CONTRATISTA

Sheet CAMABAJA OJT166
A1: REPORTE DIARIO DE HORAS
A2: CONTRATO No.
A3: OBJETIVO:
A5: REPORTE DE MAQUINARIA
A6: MAQUINA: | C6: CAMABAJA INTERNATIONAL OJT166
A8: N° | B8: FECHA | C8: LUGAR DE TRABAJO | E8: OPERADOR | F8: HOROMETRO | H8: HORAS DE TRABAJO | I8: ACTIVIDAD REALIZADA
C9: MUNICIPIO | D9: PUNTO | F9: INICIO | G9: FIN
A10: 1 | B10: 45755 | C10: VILLAVICENCIO - PATIO GALICIA SERVIMACONS | D10: BAJO POMPEYA SECTOR PALMARITO, RIO GUAYURIBA | E10: JAIRO CARDENAS | F10: 7527 | G10: =+F10+4 -> 7531 | H10: =+G10-F10 -> 4 | I10: NOS DIRIJIMOS DEL MUNICIPIO DE VILLAVICENCIO PARA TRANSPORTAR LA EXCAVADORA LINK BELT 2181 #1 DEL PATIO GALICIA SERVIMACONS PARA EL PUNTO DE TRABAJO BAJO POMPEYA SECTOR PALMARITO, RIO GUAYURIBA Y NOS REGRESAMOS AL PATIO SERVIMACONS
A11: 2 | B11: 45755 | C11: VILLAVICENCIO - PATIO GALICIA SERVIMACONS | D11: BAJO POMPEYA SECTOR PALMARITO, RIO GUAYURIBA | E11: JAIRO CARDENAS | F11: =+G10 -> 7531 | G11: =+F11+4 -> 7535 | H11: =+G11-F11 -> 4 | I11: NOS DIRIJIMOS DEL MUNICIPIO DE VILLAVICENCIO PARA TRANSPORTAR LA EXCAVADORA LINK BELT 2180 #5 DEL PATIO GALICIA SERVIMACONS PARA EL PUNTO DE TRABAJO BAJO POMPEYA SECTOR PALMARITO, RIO GUAYURIBA Y NOS REGRESAMOS AL PATIO SERVIMACONS
A12: 3 | B12: 45756 | C12: VILLAVICENCIO - PATIO GALICIA SERVIMACONS | D12: SECTOR LA ISLA, RIO GUAMAL | E12: JAIRO CARDENAS | F12: =+G11 -> 7535 | G12: =+F12+8 -> 7543 | H12: =+G12-F12 -> 8 | I12: NOS DIRIJIMOS DEL MUNICIPIO DE VILLAVICENCIO PARA TRANSPORTAR LA EXCAVADORA LINK BELT 2183 #3 DEL PATIO GALICIA SERVIMACONS PARA EL PUNTO DE TRABAJO SECTOR LA ISLA RIO GUAMAL Y NOS REGRESAMOS AL PATIO SERVIMACONS
A13: 4 | B13: 45757 | C13: VILLAVICENCIO - PATIO GALICIA SERVIMACONS | D13: SECTOR PIO XII, RIO GUAMAL | E13: JAIRO CARDENAS | F13: =+G12 -> 7543 | G13: =+F13+4 -> 7547 | H13: =+G13-F13 -> 4 | I13: NOS DIRIJIMOS DEL MUNICIPIO DE VILLAVICENCIO PARA TRANSPORTAR LA EXCAVADORA LINK BELT 2179 #4 DEL PATIO GALICIA SERVIMACONS PARA EL PUNTO DE TRABAJO SECTOR PIO XII RIO GUAMAL Y NOS REGRESAMOS AL PATIO SERVIMACONS
A14: 5 | B14: 45770 | C14: EL CALVARIO | D14: VIA MONFORTH | E14: JAIRO CARDENAS | F14: =+G13 -> 7547 | G14: =+F14+3 -> 7550 | H14: =+G14-F14 -> 3 | I14: NOS DIRIJIMOS DEL MUNICIPIO DE VILLAVICENCIO PARA TRANSPORTAR LA RETROEXCAVADORA CATERPILLAR 8585 416E DEL PATIO GALICIA SERVIMACONS PARA LA VIA MONFORTH Y NOS REGRESAMOS AL PATIO SERVIMACONS
A15: 6 | B15: 45777 | C15: BAJO POMPEYA SECTOR PALMARITO, RIO GUAYURIBA | D15: VILLAVICENCIO - PATIO GALICIA SERVIMACONS | E15: JAIRO CARDENAS | F15: =+G14 -> 7550 | G15: =+F15+4 -> 7554 | H15: =+G15-F15 -> 4 | I15: NOS DIRIJIMOS DEL MUNICIPIO DE VILLAVICENCIO PARA TRANSPORTAR LA EXCAVADORA LINK BELT 2181 #1 DEL PUNTO DE TRABAJO BAJO POMPEYA PARA EL PATIO GALICIA SERVIMACONS
A16: 7 | B16: 45777 | C16: BAJO POMPEYA SECTOR PALMARITO, RIO GUAYURIBA | D16: VILLAVICENCIO - PATIO GALICIA SERVIMACONS | E16: JAIRO CARDENAS | F16: =+G15 -> 7554 | G16: =+F16+4 -> 7558 | H16: =+G16-F16 -> 4 | I16: NOS DIRIJIMOS DEL MUNICIPIO DE VILLAVICENCIO PARA TRANSPORTAR LA EXCAVADORA LINK BELT 2180 #5 DEL PUNTO DE TRABAJO BAJO POMPEYA PARA EL PATIO GALICIA SERVIMACONS
A17: 8 | B17: 45778 | C17: VILLAVICENCIO - PATIO GALICIA SERVIMACONS | D17: EL DORADO, SECTOR LA ISLA RIO ARIARI | E17: JAIRO CARDENAS | F17: =+G16 -> 7558 | G17: =+F17+5 -> 7563 | H17: =+G17-F17 -> 5 | I17: NOS DIRIJIMOS DEL MUNICIPIO DE VILLAVICENCIO PARA TRANSPORTAR LA EXCAVADORA LINK BELT 2181 #1 DEL PATIO SERVIMACONS PARA EL PUNTO DE TRABAJO EL DORADO PUENTE LA AMISTAD Y NOS REGRESAMOS AL PATIO SERVIMACONS
A18: 9 | B18: 45784 | C18: VILLAVICENCIO - PATIO GALICIA SERVIMACONS | D18: EL DORADO, SECTOR LA ISLA RIO ARIARI | E18: JAIRO CARDENAS | F18: =+G17 -> 7563 | G18: =+F18+4 -> 7567 | H18: =+G18-F18 -> 4 | I18: NOS DIRIJIMOS DEL MUNICIPIO DE VILLAVICENCIO PARA TRANSPORTAR LA EXCAVADORA LINK BELT 2180 #5 DEL PATIO GALICIA SERVIMACONS PARA EL PUNTO DE TRABAJO EL DORADO, SECTOR LA ISLA RIO ARIARI Y NOS DIRIJIMOS AL MUNICIPIO DE GUAMAL
A19: 10 | B19: 45784 | C19: VILLAVICENCIO - PATIO GALICIA SERVIMACONS | D19: EL DORADO, SECTOR LA ISLA RIO ARIARI | E19: JAIRO CARDENAS | F19: =+G18 -> 7567 | G19: =+F19+4 -> 7571 | H19: =+G19-F19 -> 4 | I19: NOS DIRIJIMOS DEL MUNICIPIO DE VILLAVICENCIO PARA TRANSPORTAR LA EXCAVADORA LINK BELT 2179 #4 DEL PUNTO DE TRABAJO PIO XII PARA EL PUNTO DE TRABAJO EL DORARO SECTOR LA ISLA RIO ARIARI Y NOS REGRESAMOS AL PATIO SERVIMACONS
A20: 11 | B20: 45794 | C20: EL DORADO, SECTOR LA ISLA RIO ARIARI | D20: SECTOR PUERTO ESPERANZA | E20: JAIRO CARDENAS | F20: =+G19 -> 7571 | G20: =+F20+4 -> 7575 | H20: =+G20-F20 -> 4 | I20: NOS DIRIJIMOS DEL MUNICIPIO DE VILLAVICENCIO PARA TRANSPORTAR LA EXCAVADORA LINK BELT 2179 #4 DEL PUNTO DE TRABAJO SECTOR LA ISLA RIO ARIARI PARA EL PUNTO PUERTO ESPERANZA Y NOS REGRESAMOS AL PATIO SERVIMACONS
A21: 12 | B21: 45800 | C21: GUAMAL, SECTOR LA ISLA RIO GUAMAL | D21: VILLAVICENCIO - PATIO GALICIA SERVIMACONS | E21: JAIRO CARDENAS | F21: =+G20 -> 7575 | G21: =+F21+4 -> 7579 | H21: =+G21-F21 -> 4 | I21: NOS DIRIJIMOS DEL MUNICIPIO DE VILLAVICENCIO PARA TRANSPORTAR LA EXCAVADORA LINK BELT 2183 #3 DEL PUNTO DE TRABAJO GUAMAL, SECTOR LA ISLA RIO ARIARI Y NOS REGRESAMOS AL PATIO SERVIMACONS
A22: 13 | B22: 45801 | C22: EL DORADO, SECTOR LA ISLA RIO ARIARI | D22: VILLAVICENCIO - PATIO GALICIA SERVIMACONS | E22: JAIRO CARDENAS | F22: =+G21 -> 7579 | G22: =+F22+5 -> 7584 | H22: =+G22-F22 -> 5 | I22: NOS DIRIJIMOS DEL MUNICIPIO DE VILLAVICENCIO PARA TRANSPORTAR LA EXCAVADORA LINK BELT 2180 #5 DEL PUNTO DE TRABAJO EL DORADO, SECTOR LA ISLA Y NOS REGRESAMOS AL PATIO SERVIMACONS
A23: 14 | B23: 45804 | C23: EL DORADO, SECTOR LA ISLA RIO ARIARI | D23: VILLAVICENCIO - PATIO GALICIA SERVIMACONS | E23: JAIRO CARDENAS | F23: =+G22 -> 7584 | G23: =+F23+4 -> 7588 | H23: =+G23-F23 -> 4 | I23: NOS DIRIJIMOS DEL MUNICIPIO DE VILLAVICENCIO PARA TRANSPORTAR LA EXCAVADORA LINK BELT 2179 #4 DEL PUNTO DE TRABAJO EL DORADO SECTOR LA ISLA Y NOS REGRESAMOS AL PATIO SERVIMACONS
A24: 15 | B24: 45825 | C24: VILLAVICENCIO - PATIO GALICIA SERVIMACONS | D24: SAN CARLOS DE GUAROA, PUENTE TRES ARCOS | E24: JAIRO CARDENAS | F24: =+G23 -> 7588 | G24: =+F24+7 -> 7595 | H24: =+G24-F24 -> 7 | I24: NOS DIRIJIMOS DEL MUNICIPIO DE VILLAVICENCIO PARA TRANSPORTAR LA EXCAVADORA LINK BELT 2183 #3 DEL PATIO GALICIA SERVIMACONS PARA EL PUNTO DE TRABAJO SAN CARLOS DE GUAROA PUENTE TRES ARCOS
A25: 16 | B25: 45826 | C25: VILLAVICENCIO - PATIO GALICIA SERVIMACONS | D25: SAN CARLOS DE GUAROA, PUENTE TRES ARCOS | E25: JAIRO CARDENAS | F25: =+G24 -> 7595 | G25: =+F25+6 -> 7601 | H25: =+G25-F25 -> 6 | I25: NOS DIRIJIMOS DEL MUNICIPIO DE VILLAVICENCIO PARA TRANSPORTAR LA EXCAVADORA LINK BELT 2179 #4 DEL PATIO GALICIA SERVIMACONS PARA EL PUNTO DE TRABAJO PUENNTE LA AMISTAD Y NOS REGRESAMOS AL PATIO SERVIMACONS
A26: 17 | B26: 45827 | C26: SECTOR PUERTO ESPERANZA | D26: PUERTO LLERAS, CAÑO IRACA | E26: JAIRO CARDENAS | F26: =+G25 -> 7601 | G26: =+F26+10 -> 7611 | H26: =+G26-F26 -> 10 | I26: NOS DIRIJIMOS DEL MUNICIPIO DE VILLAVICENCIO PARA TRANSPORTAR LA EXCAVADORA LINK BELT 2181 #1 DEL PUNTO PUERTO ESPERANZA PARA EL PUNTO DE TRABAJO PUERTO LLERAS Y NOS REGRESAMOS AL PATIO SERVIMACONS
A27: 19 | B27: 45839 | C27: SAN CARLOS DE GUAROA, PUENTE TRES ARCOS | D27: VILLAVICENCIO - PATIO GALICIA SERVIMACONS | E27: JAIRO CARDENAS | F27: =+G26 -> 7611 | G27: =+F27+6 -> 7617 | H27: =+G27-F27 -> 6 | I27: NOS DIRIJIMMOS DEL MUNICIPIO DE VILLAVICENCIO PARA TRANSPORTAR LA EXCAVADORA LINK BELT 2183 #3 DEL PUNTO DE TRABAJO SAN CARLOS DE GUAROA PARA EL PATIO GALICIA SERVIMACONS
A28: 18 | B28: 45840 | C28: VILLAVICENCIO - PATIO GALICIA SERVIMACONS | D28: GUAMAL - SECTOR PIO XII, RIO GUAMAL | E28: JAIRO CARDENAS | F28: =+G27 -> 7617 | G28: =+F28+6 -> 7623 | H28: =+G28-F28 -> 6 | I28: NOS DIRIJIMOS DEL MUNICIPIO DE VILLAVICENCIO PARA TRANSPORTAR LA EXCAVADORA LINK BELT 2180 #5 DEL PATIO GALICIA SERVIMACONS PARA EL PUNTO DE TRABAJO GUAMAL SECTOR PIO XII Y NOS REGRESAMOS AL PATIO SERVIMACONS
A29: 20 | B29: 45847 | C29: GUAMAL - SECTOR PIO XII, RIO GUAMAL | D29: VILLAVICENCIO - PATIO GALICIA SERVIMACONS | E29: JAIRO CARDENAS | F29: =+G28 -> 7623 | G29: =+F29+6 -> 7629 | H29: =+G29-F29 -> 6 | I29: NOS DIRIJIMOS DEL MUNICIPIO DE VILLAVICENCIO PARA TRANSPORTAR LA EXCAVADORA LINK BELT 2180 #5 DEL PUNTO DE TRABAJO GUAMAL PIO XII PARA EL PATIO GALICIA SERVIMACONS
A30: 21 | B30: 45849 | C30: EL DORADO, RIO ARIARI | D30: VILLAVICENCIO - PATIO GALICIA SERVIMACONS | E30: JAIRO CARDENAS | F30: =+G29 -> 7629 | G30: =+F30+5 -> 7634 | H30: =+G30-F30 -> 5 | I30: NOS DIRIJIMOS DEL MUNICIPIO DE VILLAVICENCIO PARA TRANSPORTAR LA EXCAVADORA LINK BELT 2179 #4 DEL PUNTO DE TRABAJO EL DORADO Y NOS REGRESAMOS AL PATIO GALICIA SERVIMACONS
G41: TOTAL | H41: =SUM(H10:H40) -> 107
B44: Inicio | C44: Fin | D44: Horometro inicio | E44: Horometro fin | F44: Total
B45: =+SMALL(B10:B40,1) -> 45755 | C45: =LARGE(B10:B40,1) -> 45849 | D45: =SMALL(F10:F40,1) -> 7527 | E45: =LARGE(G10:G40,1) -> 7634 | F45: =+E45-D45 -> 107
E46: TOTAL | F46: =SUM(F45) -> 107
B52: LUIS MIGUEL ANGEL RAMIREZ ROMERO | G52: CARMEN LUCIA AGUILAR GOMEZ
B53: Rep. Legal SERVICIOS MAQUINARIA Y CONSTRUCCIONES SAS "SERVIMACONS S.A.S." | G53: SERVICIOS MAQUINARIA Y CONSTRUCCIONES SAS "SERVIMACONS S.A.S."
B55: REPRESENTANTE LEGAL | G55: DIRECTORA

Sheet EL CALVARIO - CARMEN, BENITO
A1: RESUMEN GENERAL DE ACTIVIDADES EJECUTADAS
A2: CONTRATO Nº: 1040 DE 2025
A3: OBJETIVO: SERVICIO PARA LA OPERACIÓN DE LA MAQUINARIA AMARILLA ADSCRITA A LA DIRECCIÓN DEPARTAMENTAL PARA LA GESTIÓN DEL RIESGO DE DESASTRES PARA LA REDUCCIÓN DEL RIESGO EN LOS VEINTINUEVE (29) MUNICIPIOS DEL DEPARTAMENTO DEL META.
A4: PERIODO DEL INFORME: | F4: AL
A5: FECHA PRESENTE ACTA:
A8: ITEM | B8: D E S C R I P C I Ó N / MAQUINA | C8: MUNICIPIO | D8: PUNTO | E8: FECHA INICIO | F8: FECHA FINAL | G8: HORAS EJECUTADAS | H8: VALOR EJECUTADO | I8: ACTIVIDAD REALIZADA
A9: 2 | B9: =+'BULLDOZER CATERPILLAR 2765 #2'!B9 -> BULLDOZER CATERPILLAR 2765 #2 | C9: =+'BULLDOZER CATERPILLAR 2765 #2'!C9 -> nombre municipio | D9: =+'BULLDOZER CATERPILLAR 2765 #2'!D9 -> nombre punto | E9: =+'BULLDOZER CATERPILLAR 2765 #2'!E9 -> 45769 | F9: =+'BULLDOZER CATERPILLAR 2765 #2'!F9 -> 45783 | G9: =+'BULLDOZER CATERPILLAR 2765 #2'!G9 -> 100 | H9: =+'BULLDOZER CATERPILLAR 2765 #2'!H9 -> 0 | I9: =+'BULLDOZER CATERPILLAR 2765 #2'!I9 -> SE REALIZA REHABILITACIÓN DE VIA EN EL PUNTO LA PAILA, RECORRIDO DE LA MAQUINA DEL PUNTO LA PAILA PARA EL DERRUMBE EN LA VEREDA EL CARMEN
B10: SUBTOTAL | H10: =+H9 -> 0
B11: IVA 19% | H11: =+H10*0.19 -> 0
B12: TOTAL | H12: =+H11+H10 -> 0
B24: LUIS MIGUEL ANGEL RAMIREZ ROMERO
B25: Rep. Legal SERVICIOS MAQUINARIA Y CONSTRUCCIONES SAS "SERVIMACONS S.A.S."
B26: CONTRATISTA

Sheet BULLDOZER CATERPILLAR 2765 #2
A1: RESUMEN GENERAL DE ACTIVIDADES EJECUTADAS
A2: CONTRATO Nº: 1040 DE 2025
A3: OBJETIVO:
A4: PERIODO DEL INFORME: | F4: AL
A5: FECHA PRESENTE ACTA:
A8: ITEM | B8: D E S C R I P C I Ó N / MAQUINA | C8: MUNICIPIO | D8: PUNTO | E8: FECHA INICIO | F8: FECHA FINAL | G8: HORAS EJECUTADAS | H8: VALOR EJECUTADO | I8: ACTIVIDAD REALIZADA
A9: 2 | B9: =+'BULLDOZER #2'!C6 -> BULLDOZER CATERPILLAR 2765 #2 | C9: =+'BULLDOZER #2'!C10 -> nombre municipio | D9: =+'BULLDOZER #2'!D10 -> nombre punto | E9: =+'BULLDOZER #2'!B29 -> 45769 | F9: =+'BULLDOZER #2'!C29 -> 45783 | G9: =+'BULLDOZER #2'!F30 -> 100 | H9: =+G9*'PLAN DE ACCIÓN'!H11 -> 0 | I9: =+'BULLDOZER #2'!I11 -> SE REALIZA REHABILITACIÓN DE VIA EN EL PUNTO LA PAILA, RECORRIDO DE LA MAQUINA DEL PUNTO LA PAILA PARA EL DERRUMBE EN LA VEREDA EL CARMEN
B10: SUBTOTAL | H10: =+H9 -> 0
B11: IVA 19% | H11: =+H10*0.19 -> 0
B12: TOTAL | H12: =+H11+H10 -> 0
B24: LUIS MIGUEL ANGEL RAMIREZ ROMERO
B25: Rep. Legal SERVICIOS MAQUINARIA Y CONSTRUCCIONES SAS "SERVIMACONS S.A.S."
B26: CONTRATISTA

Sheet BULLDOZER #2
A1: REPORTE DIARIO DE HORAS
A2: CONTRATO No.
A3: OBJETIVO:
A5: REPORTE DE MAQUINARIA
A6: MAQUINA: | C6: BULLDOZER CATERPILLAR 2765 #2
A8: N° | B8: FECHA | C8: LUGAR DE TRABAJO | E8: OPERADOR | F8: HOROMETRO | H8: HORAS DE TRABAJO | I8: ACTIVIDAD REALIZADA
C9: MUNICIPIO | D9: PUNTO | F9: INICIO | G9: FIN
A10: 1 | B10: 45769 | C10: nombre municipio | D10: nombre punto | E10: nombre operador | F10: 10330.7 | G10: 10334.5 | H10: =+G10-F10 -> 3.8 | I10: SE REALIZA REHABILITACIÓN DE VIA EN EL PUNTO LA PAILA
A11: 2 | B11: 45770 | C11: nombre municipio | D11: nombre punto | E11: nombre operador | F11: =+G10 -> 10334.5 | G11: 10344.1 | H11: =+G11-F11 -> 9.6 | I11: SE REALIZA REHABILITACIÓN DE VIA EN EL PUNTO LA PAILA, RECORRIDO DE LA MAQUINA DEL PUNTO LA PAILA PARA EL DERRUMBE EN LA VEREDA EL CARMEN
A12: 3 | B12: 45771 | C12: nombre municipio | D12: nombre punto | E12: nombre operador | F12: =+G11 -> 10344.1 | G12: 10352.1 | H12: =+G12-F12 -> 8 | I12: SE REALIZA REHABILITACIÓN DE LA VIA EN LA VEREDA EL CARMEN
A13: 4 | B13: 45772 | C13: nombre municipio | D13: nombre punto | E13: nombre operador | F13: =+G12 -> 10352.1 | G13: 10360.8 | H13: =+G13-F13 -> 8.7 | I13: SE REALIZA REHABILITACIÓN DE LA VIA EN EL PUNTO JERICO
A14: 5 | B14: 45773 | C14: nombre municipio | D14: nombre punto | E14: nombre operador | F14: =+G13 -> 10360.8 | G14: 10368.2 | H14: =+G14-F14 -> 7.4 | I14: SE REALIZA REHABILITACIÓN DE LA VIA EN EL PUNTO JERICO
A15: 6 | B15: 45774 | C15: nombre municipio | D15: nombre punto | E15: nombre operador | F15: =+G14 -> 10368.2 | G15: 10376.7 | H15: =+G15-F15 -> 8.5 | I15: SE REALIZA REHABILITACIÓN DE LA VIA EN EL PUNTO JERICO
A16: 7 | B16: 45775 | C16: nombre municipio | D16: nombre punto | E16: nombre operador | F16: =+G15 -> 10376.7 | G16: 10385.8 | H16: =+G16-F16 -> 9.1 | I16: SE REALIZA REHABILITACIÓN DE LA VIA EN EL PUNTO JERICO
A17: 8 | B17: 45776 | C17: nombre municipio | D17: nombre punto | E17: nombre operador | F17: =+G16 -> 10385.8 | G17: 10394.2 | H17: =+G17-F17 -> 8.4 | I17: SE REALIZA REHABILITACIÓN DE LA VIA EN EL PUNTO JERICO
A18: 9 | B18: 45777 | C18: nombre municipio | D18: nombre punto | E18: nombre operador | F18: =+G17 -> 10394.2 | G18: 10402.6 | H18: =+G18-F18 -> 8.4 | I18: SE REALIZA REHABILITACIÓN DE LA VIA EN EL PUNTO JERICO
A19: 10 | B19: 45778 | C19: nombre municipio | D19: nombre punto | E19: nombre operador | F19: =+G18 -> 10402.6 | G19: 10405.7 | H19: =+G19-F19 -> 3.1 | I19: SE REALIZA REHABILITACIÓN DE LA VIA EN EL PUNTO JERICO, MAQUINA PARQUEADA EN EL PUNTO DE TRABAJO
A20: 11 | B20: 45779 | C20: nombre municipio | D20: nombre punto | E20: nombre operador | F20: =+G19 -> 10405.7 | G20: 10412 | H20: =+G20-F20 -> 6.3 | I20: REHABILITACIÓN Y AMPLIACIÓN DE LA VIA
A21: 12 | B21: 45780 | C21: nombre municipio | D21: nombre punto | E21: nombre operador | F21: =+G20 -> 10412 | G21: 10417.7 | H21: =+G21-F21 -> 5.7 | I21: REHABILITACIÓN Y AMPLIACIÓN DE LA VIA
A22: 13 | B22: 45781 | C22: nombre municipio | D22: nombre punto | E22: nombre operador | F22: =+G21 -> 10417.7 | G22: =+F22 -> 10417.7 | H22: =+G22-F22 -> 0 | I22: DIA DE DESCANSO, MAQUINA DISPONIBLE EN EL PUNTO DE TRABAJO
A23: 14 | B23: 45782 | C23: nombre municipio | D23: nombre punto | E23: nombre operador | F23: =+G22 -> 10417.7 | G23: 10423.5 | H23: =+G23-F23 -> 5.8 | I23: REHABILITACIÓN DE LA VIA EN EL PUNTO LAS BRUJAS
A24: 15 | B24: 45783 | C24: nombre municipio | D24: nombre punto | E24: nombre operador | F24: =+G23 -> 10423.5 | G24: 10430.7 | H24: =+G24-F24 -> 7.2 | I24: REHABILITACIÓN DE VIA EN EL PUNTO LA PAILA. LA MAQUINA QUEDA PARQUEADA EN UN LUGAR SEGURO
G25: TOTAL | H25: =SUM(H10:H24) -> 100
B28: Inicio | C28: Fin | D28: Horometro inicio | E28: Horometro fin | F28: Total
B29: =+SMALL(B10:B24,1) -> 45769 | C29: =LARGE(B10:B24,1) -> 45783 | D29: =SMALL(F10:F24,1) -> 10330.7 | E29: =LARGE(G10:G24,1) -> 10430.7 | F29: =+E29-D29 -> 100
E30: TOTAL | F30: =SUM(F29) -> 100
B36: LUIS MIGUEL ANGEL RAMIREZ ROMERO | G36: CARMEN LUCIA AGUILAR GOMEZ
B37: Rep. Legal SERVICIOS MAQUINARIA Y CONSTRUCCIONES SAS "SERVIMACONS S.A.S." | G37: SERVICIOS MAQUINARIA Y CONSTRUCCIONES SAS "SERVIMACONS S.A.S."
B39: REPRESENTANTE LEGAL | G39: DIRECTORA

Sheet EL CALVARIO - VIA MONFORTH
A1: RESUMEN GENERAL DE ACTIVIDADES EJECUTADAS
A2: CONTRATO Nº: 1040 DE 2025
A3: OBJETIVO:
A4: PERIODO DEL INFORME: | F4: AL
A5: FECHA PRESENTE ACTA:
A8: ITEM | B8: D E S C R I P C I Ó N / MAQUINA | C8: MUNICIPIO | D8: PUNTO | E8: FECHA INICIO | F8: FECHA FINAL | G8: HORAS EJECUTADAS | H8: VALOR EJECUTADO | I8: ACTIVIDAD REALIZADA
A9: 5 | B9: =+'RETROEXCAVADORA 8585 416E'!B9 -> RETROEXCAVADORA CATERPILLAR 8585 416E | C9: =+'RETROEXCAVADORA 8585 416E'!C9 -> nombre del municipio | D9: =+'RETROEXCAVADORA 8585 416E'!D9 -> nombre del punto | E9: =+'RETROEXCAVADORA 8585 416E'!E9 -> 45775 | F9: =+'RETROEXCAVADORA 8585 416E'!F9 -> 45833 | G9: =+'RETROEXCAVADORA 8585 416E'!G9 -> 81 | H9: =+'RETROEXCAVADORA 8585 416E'!H9 -> 0 | I9: =+'RETROEXCAVADORA 8585 416E'!I9 -> REHABILITACIÓN DE LA VIA MONFORTH Y CONFORMACIÓN DE CUNETAS
B10: SUBTOTAL | H10: =+H9 -> 0
B11: IVA 19% | H11: =+H10*0.19 -> 0
B12: TOTAL | H12: =+H11+H10 -> 0
B24: LUIS MIGUEL ANGEL RAMIREZ ROMERO
B25: Rep. Legal SERVICIOS MAQUINARIA Y CONSTRUCCIONES SAS "SERVIMACONS S.A.S."
B26: CONTRATISTA

Sheet RETROEXCAVADORA 8585 416E
A1: RESUMEN GENERAL DE ACTIVIDADES EJECUTADAS
A2: CONTRATO Nº: 1040 DE 2025
A3: OBJETIVO:
A4: PERIODO DEL INFORME: | F4: AL
A5: FECHA PRESENTE ACTA:
A8: ITEM | B8: D E S C R I P C I Ó N / MAQUINA | C8: MUNICIPIO | D8: PUNTO | E8: FECHA INICIO | F8: FECHA FINAL | G8: HORAS EJECUTADAS | H8: VALOR EJECUTADO | I8: ACTIVIDAD REALIZADA
A9: 5 | B9: =+'RETRO 416E'!C6 -> RETROEXCAVADORA CATERPILLAR 8585 416E | C9: =+'RETRO 416E'!C10 -> nombre del municipio | D9: =+'RETRO 416E'!D10 -> nombre del punto | E9: =+'RETRO 416E'!B26 -> 45775 | F9: =+'RETRO 416E'!C26 -> 45833 | G9: =+'RETRO 416E'!F27 -> 81 | H9: =+G9*'PLAN DE ACCIÓN'!H19 -> 0 | I9: =+'RETRO 416E'!I11 -> REHABILITACIÓN DE LA VIA MONFORTH Y CONFORMACIÓN DE CUNETAS
B10: SUBTOTAL | H10: =+H9 -> 0
B11: IVA 19% | H11: =+H10*0.19 -> 0
B12: TOTAL | H12: =+H11+H10 -> 0
B24: LUIS MIGUEL ANGEL RAMIREZ ROMERO
B25: Rep. Legal SERVICIOS MAQUINARIA Y CONSTRUCCIONES SAS "SERVIMACONS S.A.S."
B26: CONTRATISTA

Sheet RETRO 416E
A1: REPORTE DIARIO DE HORAS
A2: CONTRATO No.
A3: OBJETIVO: SERVICIO PARA LA OPERACIÓN DE LA MAQUINARIA AMARILLA ADSCRITA A LA DIRECCIÓN DEPARTAMENTAL PARA LA GESTIÓN DEL RIESGO DE DESASTRES PARA LA REDUCCIÓN DEL RIESGO EN LOS VEINTINUEVE (29) MUNICIPIOS DEL DEPARTAMENTO DEL META.
A5: REPORTE DE MAQUINARIA
A6: MAQUINA: | C6: RETROEXCAVADORA CATERPILLAR 8585 416E
A8: N° | B8: FECHA | C8: LUGAR DE TRABAJO | E8: OPERADOR | F8: HOROMETRO | H8: HORAS DE TRABAJO | I8: ACTIVIDAD REALIZADA
C9: MUNICIPIO | D9: PUNTO | F9: INICIO | G9: FIN
A10: 1 | B10: 45775 | C10: nombre del municipio | D10: nombre del punto | E10: nombre operador | F10: 9252.5 | G10: 9257.3 | H10: =+G10-F10 -> 4.8 | I10: SE REALIZA DESPLAZAMIENTO DE LA MAQUINA HASTA EL PUNTO DE TRABAJO VIA MONFORTH
A11: 2 | B11: 45776 | C11: nombre del municipio | D11: nombre del punto | E11: nombre operador | F11: =+G10 -> 9257.3 | G11: 9267.3 | H11: =+G11-F11 -> 10 | I11: REHABILITACIÓN DE LA VIA MONFORTH Y CONFORMACIÓN DE CUNETAS
A12: 3 | B12: 45777 | C12: nombre del municipio | D12: nombre del punto | E12: nombre operador | F12: =+G11 -> 9267.3 | G12: 9275.7 | H12: =+G12-F12 -> 8.4 | I12: SE TRANSPORTA TUBO PARA CANALIZAR AGUAS EN LA VIA MONFORTH
A13: 4 | B13: 45778 | C13: nombre del municipio | D13: nombre del punto | E13: nombre operador | F13: =+G12 -> 9275.7 | G13: 9286 | H13: =+G13-F13 -> 10.3 | I13: REHABILITACIÓN DE VIA MONFORTH Y CONFORMACIÓN DE CUNETAS
A14: 5 | B14: 45779 | C14: nombre del municipio | D14: nombre del punto | E14: nombre operador | F14: =+G13 -> 9286 | G14: 9293 | H14: =+G14-F14 -> 7 | I14: REHABILITACIÓIN DE VIA A MONFORTH, CONFORMACIÓN DE VIAS Y CUNETAS, SE ENTIRRA TUBERIA PARA CANALIZAR EL AGUA DE LLUVIAS
A15: 6 | B15: 45780 | C15: nombre del municipio | D15: nombre del punto | E15: nombre operador | F15: =+G14 -> 9293 | G15: 9302 | H15: =+G15-F15 -> 9 | I15: REHABILITAVIÓN DE VIA Y CONFORMACIÓN DE CUNETAS
A16: 7 | B16: 45781 | C16: nombre del municipio | D16: nombre del punto | E16: nombre operador | F16: =+G15 -> 9302 | G16: 9312 | H16: =+G16-F16 -> 10 | I16: REHABILITAVIÓN DE VIA Y CONFORMACIÓN DE CUNETAS
A17: 8 | B17: 45782 | C17: nombre del municipio | D17: nombre del punto | E17: nombre operador | F17: =+G16 -> 9312 | G17: 9320.1 | H17: =+G17-F17 -> 8.1 | I17: REHABILITAVIÓN DE VIA Y CONFORMACIÓN DE CUNETAS
A18: 9 | B18: 45783 | C18: nombre del municipio | D18: nombre del punto | E18: nombre operador | F18: =+G17 -> 9320.1 | G18: =+F18 -> 9320.1 | H18: =+G18-F18 -> 0 | I18: MAQUINA DISPONIBLE EN EL PUNTO DE TRABAJO
A19: 10 | B19: 7/05/2025 AL 23/06/2025 | C19: nombre del municipio | D19: nombre del punto | E19: nombre operador | F19: =+G18 -> 9320.1 | G19: =+F19 -> 9320.1 | H19: =+G19-F19 -> 0 | I19: MAQUINA DISPONIBLE EN EL PUNTO DE TRABAJO
A20: 11 | B20: 45832 | C20: nombre del municipio | D20: nombre del punto | E20: nombre operador | F20: =+G19 -> 9320.1 | G20: 9325.5 | H20: =+G20-F20 -> 5.4 | I20: REHABILITACIÓN DE LA VIA A MONFORTH Y CONFORMACIÓN DE CUNETAS
A21: 12 | B21: 45833 | C21: nombre del municipio | D21: nombre del punto | E21: nombre operador | F21: =+G20 -> 9325.5 | G21: 9333.5 | H21: =+G21-F21 -> 8 | I21: REHABILITACIÓN DE LA VIA A MONFORTH Y CONFORMACIÓN DE CUNETAS
G22: TOTAL | H22: =SUM(H10:H21) -> 81
B25: Inicio | C25: Fin | D25: Horometro inicio | E25: Horometro fin | F25: Total
B26: =+SMALL(B10:B21,1) -> 45775 | C26: =LARGE(B10:B21,1) -> 45833 | D26: =SMALL(F10:F21,1) -> 9252.5 | E26: =LARGE(G10:G21,1) -> 9333.5 | F26: =+E26-D26 -> 81
E27: TOTAL | F27: =SUM(F26) -> 81
B33: LUIS MIGUEL ANGEL RAMIREZ ROMERO | G33: CARMEN LUCIA AGUILAR GOMEZ
B34: Rep. Legal SERVICIOS MAQUINARIA Y CONSTRUCCIONES SAS "SERVIMACONS S.A.S." | G34: SERVICIOS MAQUINARIA Y CONSTRUCCIONES SAS "SERVIMACONS S.A.S."
B36: REPRESENTANTE LEGAL | G36: DIRECTORA

Sheet BAJO POMPEYA - PALMARITO
A1: RESUMEN GENERAL DE ACTIVIDADES EJECUTADAS
A2: CONTRATO Nº: 1040 DE 2025
A3: OBJETIVO: SERVICIO PARA LA OPERACIÓN DE LA MAQUINARIA AMARILLA ADSCRITA A LA DIRECCIÓN DEPARTAMENTAL PARA LA GESTIÓN DEL RIESGO DE DESASTRES PARA LA REDUCCIÓN DEL RIESGO EN LOS VEINTINUEVE (29) MUNICIPIOS DEL DEPARTAMENTO DEL META.
A4: PERIODO DEL INFORME: | F4: AL
A5: FECHA PRESENTE ACTA:
A8: ITEM | B8: D E S C R I P C I Ó N / MAQUINA | C8: MUNICIPIO | D8: PUNTO | E8: FECHA INICIO | F8: FECHA FINAL | G8: HORAS EJECUTADAS | H8: VALOR EJECUTADO | I8: ACTIVIDAD REALIZADA
A9: =+'EXCA LINK BELT 2181 #1'!A9 -> 3 | B9: =+'EXCA LINK BELT 2181 #1'!B9 -> EXCAVADORA LINK BELT 2181 #1 | C9: =+'EXCA LINK BELT 2181 #1'!C9 -> VILLAVICENCIO | D9: =+'EXCA LINK BELT 2181 #1'!D9 -> BAJO POMPEYA SECTOR PALMARITO, RIO GUAYURIBA | E9: =+'EXCA LINK BELT 2181 #1'!E9 -> 45755 | F9: =+'EXCA LINK BELT 2181 #1'!F9 -> 45777 | G9: =+'EXCA LINK BELT 2181 #1'!G9 -> 127.2 | H9: 0 | I9: =+'EXCA LINK BELT 2181 #1'!I9 -> SE REALIZA EXCAVACIÓN EN EL CANAL PARA CONSTRUCIÓN DEL JARILLON Y PODER DESVIAR EL RIO
A10: =+'EXCA LINK BELT 2180 #5'!A9 -> 3 | B10: =+'EXCA LINK BELT 2180 #5'!B9 -> EXCAVADORA LINK BELT 2180 #5 | C10: =+'EXCA LINK BELT 2180 #5'!C9 -> VILLAVICENCIO | D10: =+'EXCA LINK BELT 2180 #5'!D9 -> BAJO POMPEYA SECTOR PALMARITO, RIO GUAYURIBA | E10: =+'EXCA LINK BELT 2180 #5'!E9 -> 45755 | F10: =+'EXCA LINK BELT 2180 #5'!F9 -> 45777 | G10: =+'EXCA LINK BELT 2180 #5'!G9 -> 122.8 | H10: =+'EXCA LINK BELT 2180 #5'!H9 -> 0 | I10: =+'EXCA LINK BELT 2180 #5'!I9 -> SE REALIZA EXCAVACIÓN PARA DESVIAR UN BRAZO DEL RIO QUE ESTA RECOSTADO EN LA MARGEN IZQUIERDA
B11: SUBTOTAL | H11: =+H10+H9 -> 0
B12: IVA 19% | H12: =+H11*0.19 -> 0
B13: TOTAL | H13: =+H12+H11 -> 0
B25: LUIS MIGUEL ANGEL RAMIREZ ROMERO
B26: Rep. Legal SERVICIOS MAQUINARIA Y CONSTRUCCIONES SAS "SERVIMACONS S.A.S."
B27: CONTRATISTA

Sheet EXCA LINK BELT 2181 #1
A1: RESUMEN GENERAL DE ACTIVIDADES EJECUTADAS
A2: CONTRATO Nº: 1040 DE 2025
A3: OBJETIVO:
A4: PERIODO DEL INFORME: | F4: AL
A5: FECHA PRESENTE ACTA:
A8: ITEM | B8: D E S C R I P C I Ó N / MAQUINA | C8: MUNICIPIO | D8: PUNTO | E8: FECHA INICIO | F8: FECHA FINAL | G8: HORAS EJECUTADAS | H8: VALOR EJECUTADO | I8: ACTIVIDAD REALIZADA
A9: 3 | B9: =+'EXCA LINK BELT #1'!C6 -> EXCAVADORA LINK BELT 2181 #1 | C9: =+'EXCA LINK BELT #1'!C10 -> VILLAVICENCIO | D9: =+'EXCA LINK BELT #1'!D10 -> BAJO POMPEYA SECTOR PALMARITO, RIO GUAYURIBA | E9: =+'EXCA LINK BELT #1'!B37 -> 45755 | F9: =+'EXCA LINK BELT #1'!C37 -> 45777 | G9: =+'EXCA LINK BELT #1'!F38 -> 127.2 | H9: 0 | I9: =+'EXCA LINK BELT #1'!I11 -> SE REALIZA EXCAVACIÓN EN EL CANAL PARA CONSTRUCIÓN DEL JARILLON Y PODER DESVIAR EL RIO
B10: SUBTOTAL | H10: =+H9 -> 0
B11: IVA 19% | H11: =+H10*0.19 -> 0
B12: TOTAL | H12: =+H11+H10 -> 0
B24: LUIS MIGUEL ANGEL RAMIREZ ROMERO
B25: Rep. Legal SERVICIOS MAQUINARIA Y CONSTRUCCIONES SAS "SERVIMACONS S.A.S."
B26: CONTRATISTA

Sheet EXCA LINK BELT #1
A1: REPORTE DIARIO DE HORAS
A2: CONTRATO No.
A3: OBJETIVO:
A5: REPORTE DE MAQUINARIA
A6: MAQUINA: | C6: EXCAVADORA LINK BELT 2181 #1
A8: N° | B8: FECHA | C8: LUGAR DE TRABAJO | E8: OPERADOR | F8: HOROMETRO | H8: HORAS DE TRABAJO | I8: ACTIVIDAD REALIZADA
C9: MUNICIPIO | D9: PUNTO | F9: INICIO | G9: FIN
A10: 1 | B10: 45755 | C10: VILLAVICENCIO | D10: BAJO POMPEYA SECTOR PALMARITO, RIO GUAYURIBA | E10: DUBERNEY RINCON | F10: 13413.2 | G10: 13414 | H10: =+G10-F10 -> 0.8 | I10: DESPLAZAMIENTO DE LA MAQUINA DESDE EL PUNTO DE DESENBARQUE HASTA EL PUTO DE TRABAJO
A11: 2 | B11: 45756 | C11: VILLAVICENCIO | D11: BAJO POMPEYA SECTOR PALMARITO, RIO GUAYURIBA | E11: DUBERNEY RINCON | F11: =+G10 -> 13414 | G11: 13424 | H11: =+G11-F11 -> 10 | I11: SE REALIZA EXCAVACIÓN EN EL CANAL PARA CONSTRUCIÓN DEL JARILLON Y PODER DESVIAR EL RIO
A12: 3 | B12: 45757 | C12: VILLAVICENCIO | D12: BAJO POMPEYA SECTOR PALMARITO, RIO GUAYURIBA | E12: DUBERNEY RINCON | F12: =+G11 -> 13424 | G12: 13434 | H12: =+G12-F12 -> 10 | I12: SE REALIZA EXCAVACIÓN EN EL CANAL PARA CONSTRUCIÓN DEL JARILLON Y PODER DESVIAR EL RIO
A13: 4 | B13: 45758 | C13: VILLAVICENCIO | D13: BAJO POMPEYA SECTOR PALMARITO, RIO GUAYURIBA | E13: DUBERNEY RINCON | F13: =+G12 -> 13434 | G13: 13444 | H13: =+G13-F13 -> 10 | I13: SE REALIZA EXCAVACIÓN EN EL RIO PARA CONFORMACIÓN DEL JARILLON DE PROTECCIÓN
A14: 5 | B14: 45759 | C14: VILLAVICENCIO | D14: BAJO POMPEYA SECTOR PALMARITO, RIO GUAYURIBA | E14: DUBERNEY RINCON | F14: =+G13 -> 13444 | G14: 13454 | H14: =+G14-F14 -> 10 | I14: SE TRANSPALEA MATERIAL PARA LA CONFORMACIÓN DEL JARILLON DE PROTECCIÓN
A15: 6 | B15: 45760 | C15: VILLAVICENCIO | D15: BAJO POMPEYA SECTOR PALMARITO, RIO GUAYURIBA | E15: DUBERNEY RINCON | F15: =+G14 -> 13454 | G15: 13464 | H15: =+G15-F15 -> 10 | I15: SE HACE EXCAVACIÓN DEL RIO PARA CONFORMACIÓN DEL JARILLON DE PROTECCIÓN
A16: 7 | B16: 45761 | C16: VILLAVICENCIO | D16: BAJO POMPEYA SECTOR PALMARITO, RIO GUAYURIBA | E16: DUBERNEY RINCON | F16: =+G15 -> 13464 | G16: 13474 | H16: =+G16-F16 -> 10 | I16: SE HACE EXCAVACIÓN DEL RIO PARA CONFORMACIÓN DEL JARILLON DE PROTECCIÓN
A17: 8 | B17: 45762 | C17: VILLAVICENCIO | D17: BAJO POMPEYA SECTOR PALMARITO, RIO GUAYURIBA | E17: DUBERNEY RINCON | F17: =+G16 -> 13474 | G17: 13484 | H17: =+G17-F17 -> 10 | I17: SE REALIZA EXCAVACIÓN, TRANSPALEO Y CONFORMACIÓN JARILLON DE PROTECCIÓN
A18: 9 | B18: 45763 | C18: VILLAVICENCIO | D18: BAJO POMPEYA SECTOR PALMARITO, RIO GUAYURIBA | E18: DUBERNEY RINCON | F18: =+G17 -> 13484 | G18: 13489.6 | H18: =+G18-F18 -> 5.6 | I18: SE REALIZA CONFORMACIÓN Y PAISAJEO EN EL JARILLON
A19: 10 | B19: 45764 | C19: VILLAVICENCIO | D19: BAJO POMPEYA SECTOR PALMARITO, RIO GUAYURIBA | E19: DUBERNEY RINCON | F19: =+G18 -> 13489.6 | G19: =+F19 -> 13489.6 | H19: =+G19-F19 -> 0 | I19: MAQUINA DISPONIBLE EN EL PUNTO DE TRABAJO, DIA DE DESCANSO POR MOTIVO DE LA SEMANA SANTA
A20: 11 | B20: 45765 | C20: VILLAVICENCIO | D20: BAJO POMPEYA SECTOR PALMARITO, RIO GUAYURIBA | E20: DUBERNEY RINCON | F20: =+G19 -> 13489.6 | G20: =+F20 -> 13489.6 | H20: =+G20-F20 -> 0 | I20: MAQUINA DISPONIBLE EN EL PUNTO DE TRABAJO, DIA DE DESCANSO POR MOTIVO DE LA SEMANA SANTA
A21: 12 | B21: 45766 | C21: VILLAVICENCIO | D21: BAJO POMPEYA SECTOR PALMARITO, RIO GUAYURIBA | E21: DUBERNEY RINCON | F21: =+G20 -> 13489.6 | G21: =+F21 -> 13489.6 | H21: =+G21-F21 -> 0 | I21: MAQUINA DISPONIBLE EN EL PUNTO DE TRABAJO, DIA DE DESCANSO POR MOTIVO DE LA SEMANA SANTA
A22: 13 | B22: 45767 | C22: VILLAVICENCIO | D22: BAJO POMPEYA SECTOR PALMARITO, RIO GUAYURIBA | E22: DUBERNEY RINCON | F22: =+G21 -> 13489.6 | G22: =+F22 -> 13489.6 | H22: =+G22-F22 -> 0 | I22: MAQUINA DISPONIBLE EN EL PUNTO DE TRABAJO, DIA DE DESCANSO POR MOTIVO DE LA SEMANA SANTA
A23: 14 | B23: 45768 | C23: VILLAVICENCIO | D23: BAJO POMPEYA SECTOR PALMARITO, RIO GUAYURIBA | E23: DUBERNEY RINCON | F23: =+G22 -> 13489.6 | G23: 13490.3 | H23: =+G23-F23 -> 0.7 | I23: SE VERIFICA EL ESTADO DEL RIO, PERO NO SE PUEDE INGRESAR POR AUMENTO DEL CAUCE DEL RIO
A24: 15 | B24: 45769 | C24: VILLAVICENCIO | D24: BAJO POMPEYA SECTOR PALMARITO, RIO GUAYURIBA | E24: DUBERNEY RINCON | F24: =+G23 -> 13490.3 | G24: 13499.8 | H24: =+G24-F24 -> 9.5 | I24: SE REALIZA EXCAVACIÓN EN EL RIO PARA CONFORMACIÓN DEL JARILLON DE PROTECCIÓN
A25: 16 | B25: 45770 | C25: VILLAVICENCIO | D25: BAJO POMPEYA SECTOR PALMARITO, RIO GUAYURIBA | E25: DUBERNEY RINCON | F25: =+G24 -> 13499.8 | G25: 13509.3 | H25: =+G25-F25 -> 9.5 | I25: SE REALIZA CANALIZACIÓN DEL RIO
A26: 17 | B26: 45771 | C26: VILLAVICENCIO | D26: BAJO POMPEYA SECTOR PALMARITO, RIO GUAYURIBA | E26: DUBERNEY RINCON | F26: =+G25 -> 13509.3 | G26: 13519.7 | H26: =+G26-F26 -> 10.4 | I26: SE REALIZA EXCAVACIÓN PARA CONFORMACIÓN DE JARILLON Y SE REALIZA CANALIZACIÓN
A27: 18 | B27: 45772 | C27: VILLAVICENCIO | D27: BAJO POMPEYA SECTOR PALMARITO, RIO GUAYURIBA | E27: DUBERNEY RINCON | F27: =+G26 -> 13519.7 | G27: 13529.8 | H27: =+G27-F27 -> 10.1 | I27: SE REALIZA EXCAVACIÓN EN EL RIO PARA CONFORMAR JARILLON
A28: 19 | B28: 45773 | C28: VILLAVICENCIO | D28: BAJO POMPEYA SECTOR PALMARITO, RIO GUAYURIBA | E28: DUBERNEY RINCON | F28: =+G27 -> 13529.8 | G28: 13529.8 | H28: =+G28-F28 -> 0 | I28: MAQUINA DISPONIBLE EN EL PUNTO DE TRABAJO, SE PRESENTO UN AUMENTO EN EL CAUCE DEL RIO
A29: 20 | B29: 45774 | C29: VILLAVICENCIO | D29: BAJO POMPEYA SECTOR PALMARITO, RIO GUAYURIBA | E29: DUBERNEY RINCON | F29: =+G28 -> 13529.8 | G29: =+F29 -> 13529.8 | H29: =+G29-F29 -> 0 | I29: DIA DE DESCANSO, MAQUINA DISPONIBLE EN EL PUNTO DE TRABAJO
A30: 21 | B30: 45775 | C30: VILLAVICENCIO | D30: BAJO POMPEYA SECTOR PALMARITO, RIO GUAYURIBA | E30: DUBERNEY RINCON | F30: =+G29 -> 13529.8 | G30: 13530.5 | H30: =+G30-F30 -> 0.7 | I30: SE VERIFICA EL ESTADO DEL RIO, PERO NO SE PUEDE INGRESAR POR AUMENTO DEL CAUCE DEL RIO
A31: 22 | B31: 45776 | C31: VILLAVICENCIO | D31: BAJO POMPEYA SECTOR PALMARITO, RIO GUAYURIBA | E31: DUBERNEY RINCON | F31: =+G30 -> 13530.5 | G31: 13539.1 | H31: =+G31-F31 -> 8.6 | I31: SE REALIZA CANALIZACIÓN PARA CONFORMAR JARILLON Y DESVIAR EL CAUCE DEL RIO
A32: 23 | B32: 45777 | C32: VILLAVICENCIO | D32: BAJO POMPEYA SECTOR PALMARITO, RIO GUAYURIBA | E32: DUBERNEY RINCON | F32: =+G31 -> 13539.1 | G32: 13540.4 | H32: =+G32-F32 -> 1.3 | I32: DESPLAZAMIENTO DE LA MAQUINA DEL PUNTO DE TRABAJO HASTA EL PATIO GALICIA SERVIMACONS
G33: TOTAL | H33: =SUM(H10:H32) -> 127.2
B36: Inicio | C36: Fin | D36: Horometro inicio | E36: Horometro fin | F36: Total
B37: =+SMALL(B10:B32,1) -> 45755 | C37: =LARGE(B10:B32,1) -> 45777 | D37: =SMALL(F10:F32,1) -> 13413.2 | E37: =LARGE(G10:G32,1) -> 13540.4 | F37: =+E37-D37 -> 127.2
E38: TOTAL | F38: =SUM(F37) -> 127.2
B44: LUIS MIGUEL ANGEL RAMIREZ ROMERO | G44: CARMEN LUCIA AGUILAR GOMEZ
B45: Rep. Legal SERVICIOS MAQUINARIA Y CONSTRUCCIONES SAS "SERVIMACONS S.A.S." | G45: SERVICIOS MAQUINARIA Y CONSTRUCCIONES SAS "SERVIMACONS S.A.S."
B47: REPRESENTANTE LEGAL | G47: DIRECTORA

Sheet EXCA LINK BELT 2180 #5
A1: RESUMEN GENERAL DE ACTIVIDADES EJECUTADAS
A2: CONTRATO Nº: 1040 DE 2025
A3: OBJETIVO:
A4: PERIODO DEL INFORME: | F4: AL
A5: FECHA PRESENTE ACTA:
A8: ITEM | B8: D E S C R I P C I Ó N / MAQUINA | C8: MUNICIPIO | D8: PUNTO | E8: FECHA INICIO | F8: FECHA FINAL | G8: HORAS EJECUTADAS | H8: VALOR EJECUTADO | I8: ACTIVIDAD REALIZADA
A9: 3 | B9: =+'EXCA LINK BELT #5'!C6 -> EXCAVADORA LINK BELT 2180 #5 | C9: =+'EXCA LINK BELT #5'!C10 -> VILLAVICENCIO | D9: =+'EXCA LINK BELT #5'!D10 -> BAJO POMPEYA SECTOR PALMARITO, RIO GUAYURIBA | E9: =+'EXCA LINK BELT #5'!B37 -> 45755 | F9: =+'EXCA LINK BELT #5'!C37 -> 45777 | G9: =+'EXCA LINK BELT #5'!F38 -> 122.8 | H9: 0 | I9: =+'EXCA LINK BELT #5'!I11 -> SE REALIZA EXCAVACIÓN PARA DESVIAR UN BRAZO DEL RIO QUE ESTA RECOSTADO EN LA MARGEN IZQUIERDA
B10: SUBTOTAL | H10: =+H9 -> 0
B11: IVA 19% | H11: =+H10*0.19 -> 0
B12: TOTAL | H12: =+H11+H10 -> 0
B24: LUIS MIGUEL ANGEL RAMIREZ ROMERO
B25: Rep. Legal SERVICIOS MAQUINARIA Y CONSTRUCCIONES SAS "SERVIMACONS S.A.S."
B26: CONTRATISTA

Sheet EXCA LINK BELT #5
A1: REPORTE DIARIO DE HORAS
A2: CONTRATO No.
A3: OBJETIVO: SERVICIO PARA LA OPERACIÓN DE LA MAQUINARIA AMARILLA ADSCRITA A LA DIRECCIÓN DEPARTAMENTAL PARA LA GESTIÓN DEL RIESGO DE DESASTRES PARA LA REDUCCIÓN DEL RIESGO EN LOS VEINTINUEVE (29) MUNICIPIOS DEL DEPARTAMENTO DEL META.
A5: REPORTE DE MAQUINARIA
A6: MAQUINA: | C6: EXCAVADORA LINK BELT 2180 #5
A8: N° | B8: FECHA | C8: LUGAR DE TRABAJO | E8: OPERADOR | F8: HOROMETRO | H8: HORAS DE TRABAJO | I8: ACTIVIDAD REALIZADA
C9: MUNICIPIO | D9: PUNTO | F9: INICIO | G9: FIN
A10: 1 | B10: 45755 | C10: VILLAVICENCIO | D10: BAJO POMPEYA SECTOR PALMARITO, RIO GUAYURIBA | E10: JHONAL VAQUIRO | F10: 12345.1 | G10: 12346 | H10: =+G10-F10 -> 0.9 | I10: DESPLAZAMIENTO DE LA MAQUINA DESDE EL PUNTO DE DESEMBARQUE HASTA EL PUNTO DE TRABAJO
A11: 2 | B11: 45756 | C11: VILLAVICENCIO | D11: BAJO POMPEYA SECTOR PALMARITO, RIO GUAYURIBA | E11: JHONAL VAQUIRO | F11: =+G10 -> 12346 | G11: 12356 | H11: =+G11-F11 -> 10 | I11: SE REALIZA EXCAVACIÓN PARA DESVIAR UN BRAZO DEL RIO QUE ESTA RECOSTADO EN LA MARGEN IZQUIERDA
A12: 3 | B12: 45757 | C12: VILLAVICENCIO | D12: BAJO POMPEYA SECTOR PALMARITO, RIO GUAYURIBA | E12: JHONAL VAQUIRO | F12: =+G11 -> 12356 | G12: 12366.2 | H12: =+G12-F12 -> 10.2 | I12: SE REALIZA EXCAVACIÓN PARA DESVIAR UN BRAZO DEL RIO QUE ESTA RECOSTADO EN LA MARGUEN IZQUIERDA
A13: 4 | B13: 45758 | C13: VILLAVICENCIO | D13: BAJO POMPEYA SECTOR PALMARITO, RIO GUAYURIBA | E13: JHONAL VAQUIRO | F13: =+G12 -> 12366.2 | G13: 12376.6 | H13: =+G13-F13 -> 10.4 | I13: SE REALIZA EXCAVACIÓN PARA DESVIAR UN BRAZO DEL RIO QUE ESTA RECOSTADO EN LA MARGEN IZQUIERDA
A14: 5 | B14: 45759 | C14: VILLAVICENCIO | D14: BAJO POMPEYA SECTOR PALMARITO, RIO GUAYURIBA | E14: JHONAL VAQUIRO | F14: =+G13 -> 12376.6 | G14: 12386.7 | H14: =+G14-F14 -> 10.1 | I14: SE REALIZA EXCAVACIÓN PARA DESVIAR UN BRAZO DEL RIO QUE ESTA RECOSTADO EN LA MARGEN IZQUIERDA
A15: 6 | B15: 45760 | C15: VILLAVICENCIO | D15: BAJO POMPEYA SECTOR PALMARITO, RIO GUAYURIBA | E15: JHONAL VAQUIRO | F15: =+G14 -> 12386.7 | G15: 12396.7 | H15: =+G15-F15 -> 10 | I15: SE REALIZA EXCAVACIÓN PARA DESVIAR UN BRAZO DEL RIO QUE ESTA RECOSTADO EN LA MARGEN IZQUIERDA
A16: 7 | B16: 45761 | C16: VILLAVICENCIO | D16: BAJO POMPEYA SECTOR PALMARITO, RIO GUAYURIBA | E16: JHONAL VAQUIRO | F16: =+G15 -> 12396.7 | G16: 12406.7 | H16: =+G16-F16 -> 10 | I16: SE REALIZA EXCAVACIÓN PARA REFORZAR EL JARILLON, QUE SE CONSTRUYO PARA DESVIAR UN BRAZO DEL RIO
A17: 8 | B17: 45762 | C17: VILLAVICENCIO | D17: BAJO POMPEYA SECTOR PALMARITO, RIO GUAYURIBA | E17: JHONAL VAQUIRO | F17: =+G16 -> 12406.7 | G17: 12416.7 | H17: =+G17-F17 -> 10 | I17: SE REALIZA EXCAVACIÓN PARA REFORZAR EL JARILLON
A18: 9 | B18: 45763 | C18: VILLAVICENCIO | D18: BAJO POMPEYA SECTOR PALMARITO, RIO GUAYURIBA | E18: JHONAL VAQUIRO | F18: =+G17 -> 12416.7 | G18: =+F18 -> 12416.7 | H18: =+G18-F18 -> 0 | I18: MAQUINA DISPONIBLE EN EL PUNTO DE TRABAJO
A19: 10 | B19: 45764 | C19: VILLAVICENCIO | D19: BAJO POMPEYA SECTOR PALMARITO, RIO GUAYURIBA | E19: JHONAL VAQUIRO | F19: =+G18 -> 12416.7 | G19: =+F19 -> 12416.7 | H19: =+G19-F19 -> 0 | I19: MAQUINA DISPONIBLE EN EL PUNTO DE TRABAJO, DIA DE DESCANSO POR MOTIVO DE LA SEMANA SANTA
A20: 11 | B20: 45765 | C20: VILLAVICENCIO | D20: BAJO POMPEYA SECTOR PALMARITO, RIO GUAYURIBA | E20: JHONAL VAQUIRO | F20: =+G19 -> 12416.7 | G20: =+F20 -> 12416.7 | H20: =+G20-F20 -> 0 | I20: MAQUINA DISPONIBLE EN EL PUNTO DE TRABAJO, DIA DE DESCANSO POR MOTIVO DE LA SEMANA SANTA
A21: 12 | B21: 45766 | C21: VILLAVICENCIO | D21: BAJO POMPEYA SECTOR PALMARITO, RIO GUAYURIBA | E21: JHONAL VAQUIRO | F21: =+G20 -> 12416.7 | G21: =+F21 -> 12416.7 | H21: =+G21-F21 -> 0 | I21: MAQUINA DISPONIBLE EN EL PUNTO DE TRABAJO, DIA DE DESCANSO POR MOTIVO DE LA SEMANA SANTA
A22: 13 | B22: 45767 | C22: VILLAVICENCIO | D22: BAJO POMPEYA SECTOR PALMARITO, RIO GUAYURIBA | E22: JHONAL VAQUIRO | F22: =+G21 -> 12416.7 | G22: =+F22 -> 12416.7 | H22: =+G22-F22 -> 0 | I22: MAQUINA DISPONIBLE EN EL PUNTO DE TRABAJO, DIA DE DESCANSO POR MOTIVO DE LA SEMANA SANTA
A23: 14 | B23: 45768 | C23: VILLAVICENCIO | D23: BAJO POMPEYA SECTOR PALMARITO, RIO GUAYURIBA | E23: JHONAL VAQUIRO | F23: =+G22 -> 12416.7 | G23: =+F23 -> 12416.7 | H23: =+G23-F23 -> 0 | I23: MAQUINA DISPONIBLE EN EL PUNTO DE TRABAJO
A24: 15 | B24: 45769 | C24: VILLAVICENCIO | D24: BAJO POMPEYA SECTOR PALMARITO, RIO GUAYURIBA | E24: JHONAL VAQUIRO | F24: =+G23 -> 12416.7 | G24: 12426.8 | H24: =+G24-F24 -> 10.1 | I24: SE REFUERZA EL CIERRE DEL JARILLON
A25: 16 | B25: 45770 | C25: VILLAVICENCIO | D25: BAJO POMPEYA SECTOR PALMARITO, RIO GUAYURIBA | E25: JHONAL VAQUIRO | F25: =+G24 -> 12426.8 | G25: 12436.8 | H25: =+G25-F25 -> 10 | I25: SE REALIZA EXCAVACIÓN PARA AMPLIAR UN CANAL Y QUITAR PRESIÓN AL LADO IZQUIERDO
A26: 17 | B26: 45771 | C26: VILLAVICENCIO | D26: BAJO POMPEYA SECTOR PALMARITO, RIO GUAYURIBA | E26: JHONAL VAQUIRO | F26: =+G25 -> 12436.8 | G26: 12447 | H26: =+G26-F26 -> 10.2 | I26: SE REALIZA EXCAVACIÓN PARA CERRAR UN BRAZO DEL RIO QUE ESTA RECOSTADO EN LA MARGEN IZQUIERDA
A27: 18 | B27: 45772 | C27: VILLAVICENCIO | D27: BAJO POMPEYA SECTOR PALMARITO, RIO GUAYURIBA | E27: JHONAL VAQUIRO | F27: =+G26 -> 12447 | G27: 12457 | H27: =+G27-F27 -> 10 | I27: SE REALIZA EXCAVACIÓN PARA CERRAR UN BRAZO DEL RIO QUE ESTA RECOSTADO EN LA MARGEN IZQUIERDA
A28: 19 | B28: 45773 | C28: VILLAVICENCIO | D28: BAJO POMPEYA SECTOR PALMARITO, RIO GUAYURIBA | E28: JHONAL VAQUIRO | F28: =+G27 -> 12457 | G28: =+F28 -> 12457 | H28: =+G28-F28 -> 0 | I28: MAQUINA DISPONIBLE EN EL PUNTO DE TRABAJO, SE PRESENTO UN AUMENTO EN EL CAUCE DEL RIO
A29: 20 | B29: 45774 | C29: VILLAVICENCIO | D29: BAJO POMPEYA SECTOR PALMARITO, RIO GUAYURIBA | E29: JHONAL VAQUIRO | F29: =+G28 -> 12457 | G29: =+F29 -> 12457 | H29: =+G29-F29 -> 0 | I29: DIA DE DESCANSO, MAQUINA DISPONIBLE EN EL PUNTO DE TRABAJO
A30: 21 | B30: 45775 | C30: VILLAVICENCIO | D30: BAJO POMPEYA SECTOR PALMARITO, RIO GUAYURIBA | E30: WILLIAM GARAVITO | F30: =+G29 -> 12457 | G30: 12457.7 | H30: =+G30-F30 -> 0.7 | I30: SE VERIFICA EL ESTADO DEL RIO, PERO NO SE PUEDE INGRESAR POR AUMENTO DEL CAUCE DEL RIO
A31: 22 | B31: 45776 | C31: VILLAVICENCIO | D31: BAJO POMPEYA SECTOR PALMARITO, RIO GUAYURIBA | E31: WILLIAM GARAVITO | F31: =+G30 -> 12457.7 | G31: 12466.4 | H31: =+G31-F31 -> 8.7 | I31: SE REALIZA CANALIZACIÓN Y CONSTRUCCIÓN DE JARILLON ÁRA PROTECCIÓN DE LA MARGEN DERECHA DEL RIO
A32: 23 | B32: 45777 | C32: VILLAVICENCIO | D32: BAJO POMPEYA SECTOR PALMARITO, RIO GUAYURIBA | E32: WILLIAM GARAVITO | F32: =+G31 -> 12466.4 | G32: 12467.9 | H32: =+G32-F32 -> 1.5 | I32: DESPLAZAMIENTO DE LA MAQUINA DEL PUNTO DE TRABAJO AL PATIO GALICIA SERVIMACONS
G33: TOTAL | H33: =SUM(H10:H32) -> 122.8
B36: Inicio | C36: Fin | D36: Horometro inicio | E36: Horometro fin | F36: Total
B37: =+SMALL(B10:B32,1) -> 45755 | C37: =LARGE(B10:B32,1) -> 45777 | D37: =SMALL(F10:F32,1) -> 12345.1 | E37: =LARGE(G10:G32,1) -> 12467.9 | F37: =+E37-D37 -> 122.8
E38: TOTAL | F38: =SUM(F37) -> 122.8
B46: LUIS MIGUEL ANGEL RAMIREZ ROMERO | G46: CARMEN LUCIA AGUILAR GOMEZ
B47: Rep. Legal SERVICIOS MAQUINARIA Y CONSTRUCCIONES SAS "SERVIMACONS S.A.S." | G47: SERVICIOS MAQUINARIA Y CONSTRUCCIONES SAS "SERVIMACONS S.A.S."
B49: REPRESENTANTE LEGAL | G49: DIRECTORA

Sheet GUAMAL - SECTOR LA ISLA
H9: 0

Sheet EXCA LINK BELT 2183 #3
A1: RESUMEN GENERAL DE ACTIVIDADES EJECUTADAS
A2: CONTRATO Nº: 1040 DE 2025
A3: OBJETIVO:
A4: PERIODO DEL INFORME: | F4: AL
A5: FECHA PRESENTE ACTA:
A8: ITEM | B8: D E S C R I P C I Ó N / MAQUINA | C8: MUNICIPIO | D8: PUNTO | E8: FECHA INICIO | F8: FECHA FINAL | G8: HORAS EJECUTADAS | H8: VALOR EJECUTADO | I8: ACTIVIDAD REALIZADA
A9: 3 | B9: =+'EXCA LINK BELT #3'!C6 -> EXCAVADORA LINK BELT 2183 #3 | C9: =+'EXCA LINK BELT #3'!C10 -> GUAMAL | D9: =+'EXCA LINK BELT #3'!D10 -> SECTOR LA ISLA, RIO GUAMAL | E9: =+'EXCA LINK BELT #3'!B58 -> 45757 | F9: =+'EXCA LINK BELT #3'!C58 -> 45800 | G9: =+'EXCA LINK BELT #3'!F59 -> 270 | H9: 0 | I9: =+'EXCA LINK BELT #3'!I11 -> SE REALIZA EXCAVACIÓN PARA CONSTRUCCIÓN DE UN JARILLON DE PROTECCIÓN
B10: SUBTOTAL | H10: =+H9 -> 0
B11: IVA 19% | H11: =+H10*0.19 -> 0
B12: TOTAL | H12: =+H11+H10 -> 0
B24: LUIS MIGUEL ANGEL RAMIREZ ROMERO
B25: Rep. Legal SERVICIOS MAQUINARIA Y CONSTRUCCIONES SAS "SERVIMACONS S.A.S."
B26: CONTRATISTA

Sheet EXCA LINK BELT #3
A1: REPORTE DIARIO DE HORAS
A2: CONTRATO No.
A3: OBJETIVO:
A5: REPORTE DE MAQUINARIA
A6: MAQUINA: | C6: EXCAVADORA LINK BELT 2183 #3
A8: N° | B8: FECHA | C8: LUGAR DE TRABAJO | E8: OPERADOR | F8: HOROMETRO | H8: HORAS DE TRABAJO | I8: ACTIVIDAD REALIZADA
C9: MUNICIPIO | D9: PUNTO | F9: INICIO | G9: FIN
A10: 1 | B10: 45757 | C10: GUAMAL | D10: SECTOR LA ISLA, RIO GUAMAL | E10: OSCAR AHUMADA | F10: 15270 | G10: 15280 | H10: =+G10-F10 -> 10 | I10: DESPLAZAMIENTO DE LA MAQUINA HASTA EL PUNTO DE TRABAJO, SE INICIAN TRABAJOS DE EXCAVACION PARA LA CONSTRUCCIÓN DE UN JARILLON DE PROTECCIÓN
A11: 2 | B11: 45758 | C11: GUAMAL | D11: SECTOR LA ISLA, RIO GUAMAL | E11: OSCAR AHUMADA | F11: =+G10 -> 15280 | G11: 15290 | H11: =+G11-F11 -> 10 | I11: SE REALIZA EXCAVACIÓN PARA CONSTRUCCIÓN DE UN JARILLON DE PROTECCIÓN
A12: 3 | B12: 45759 | C12: GUAMAL | D12: SECTOR LA ISLA, RIO GUAMAL | E12: OSCAR AHUMADA | F12: =+G11 -> 15290 | G12: 15300 | H12: =+G12-F12 -> 10 | I12: SE REALIZA EXCAVACIÓN PARA CONSTRUCCIÓN DE UN JARILLON DE PROTECCIÓN
A13: 4 | B13: 45760 | C13: GUAMAL | D13: SECTOR LA ISLA, RIO GUAMAL | E13: OSCAR AHUMADA | F13: =+G12 -> 15300 | G13: 15306 | H13: =+G13-F13 -> 6 | I13: SE REALIZA EXCAVACIÓN PARA CONSTRUCCIÓN DE UN JARILLON DE PROTECCIÓN
A14: 5 | B14: 45761 | C14: GUAMAL | D14: SECTOR LA ISLA, RIO GUAMAL | E14: OSCAR AHUMADA | F14: =+G13 -> 15306 | G14: 15313.9 | H14: =+G14-F14 -> 7.9 | I14: SE REALIZA EXCAVACIÓN PARA CONSTRUCCIÓN DE UN JARILLON DE PROTECCIÓN
A15: 6 | B15: 45762 | C15: GUAMAL | D15: SECTOR LA ISLA, RIO GUAMAL | E15: OSCAR AHUMADA | F15: =+G14 -> 15313.9 | G15: 15324 | H15: =+G15-F15 -> 10.1 | I15: SE FINALIZA EL ESPOLON EN LA PARTE BAJA Y SE REALIZA ENROCADO DE PROTECCIÓN EN LA PARTE ALTA DE LA VEREDA LA ISLA
A16: 7 | B16: 45763 | C16: GUAMAL | D16: SECTOR LA ISLA, RIO GUAMAL | E16: OSCAR AHUMADA | F16: =+G15 -> 15324 | G16: 15333.8 | H16: =+G16-F16 -> 9.8 | I16: SE REALIZA CANALIZACIÓN, REPALEO DE MATERIAL, RECONSTRUCCIÓN DEL JARILLON Y ENROCADO DE PROTECCIÓN
A17: 8 | B17: 45764 | C17: GUAMAL | D17: SECTOR LA ISLA, RIO GUAMAL | E17: OSCAR AHUMADA | F17: =+G16 -> 15333.8 | G17: 15338.5 | H17: =+G17-F17 -> 4.7 | I17: SE REALIZA REFUERZO EN EL ENROCADO PARA PROTECCIÓN EN LA PARTE MAS ALTA DEL TRAMO A INTERVENIR
A18: 9 | B18: 45765 | C18: GUAMAL | D18: SECTOR LA ISLA, RIO GUAMAL | E18: OSCAR AHUMADA | F18: =+G17 -> 15338.5 | G18: =+F18 -> 15338.5 | H18: =+G18-F18 -> 0 | I18: MAQUINA DISPONIBLE EN EL PUNTO DE TRABAJO, DIA DE DESCANSO POR MOTIVO DE LA SEMANA SANTA
A19: 10 | B19: 45766 | C19: GUAMAL | D19: SECTOR LA ISLA, RIO GUAMAL | E19: OSCAR AHUMADA | F19: =+G18 -> 15338.5 | G19: =+F19 -> 15338.5 | H19: =+G19-F19 -> 0 | I19: MAQUINA DISPONIBLE EN EL PUNTO DE TRABAJO, DIA DE DESCANSO POR MOTIVO DE LA SEMANA SANTA
A20: 11 | B20: 45767 | C20: GUAMAL | D20: SECTOR LA ISLA, RIO GUAMAL | E20: OSCAR AHUMADA | F20: =+G19 -> 15338.5 | G20: =+F20 -> 15338.5 | H20: =+G20-F20 -> 0 | I20: MAQUINA DISPONIBLE EN EL PUNTO DE TRABAJO, DIA DE DESCANSO POR MOTIVO DE LA SEMANA SANTA
A21: 12 | B21: 45768 | C21: GUAMAL | D21: SECTOR LA ISLA, RIO GUAMAL | E21: OSCAR AHUMADA | F21: =+G20 -> 15338.5 | G21: =+F21 -> 15338.5 | H21: =+G21-F21 -> 0 | I21: MAQUINA DISPONIBLE EN EL PUNTO DE TRABAJO, ESPERANDO MAS HORAS MAQUINA PARA SEGUIR INTERVINIENDO EL PUNTO
A22: 13 | B22: 45769 | C22: GUAMAL | D22: SECTOR LA ISLA, RIO GUAMAL | E22: OSCAR AHUMADA | F22: =+G21 -> 15338.5 | G22: =+F22 -> 15338.5 | H22: =+G22-F22 -> 0 | I22: NO SE TRABAJA, YA QUE LA MAQUINA ESTUVO EN MANTENIMIENTO
A23: 14 | B23: 45770 | C23: GUAMAL | D23: SECTOR LA ISLA, RIO GUAMAL | E23: OSCAR AHUMADA | F23: =+G22 -> 15338.5 | G23: 15342.7 | H23: =+G23-F23 -> 4.2 | I23: SE REALIZA CARRETEABLE PARA INGRESO AL PUNTO DE TRABAJO, SE PRESENTAN LLUVIAS EN LA TARDE Y NO SE PUEDE CONTINUAR TRABAJANDO
A24: 15 | B24: 45771 | C24: GUAMAL | D24: SECTOR LA ISLA, RIO GUAMAL | E24: OSCAR AHUMADA | F24: =+G23 -> 15342.7 | G24: 15352.8 | H24: =+G24-F24 -> 10.1 | I24: SE REALIA EXCAVACIÓN DEL CANAL PARA DESVIO DE UN BRAZO DEL RIO
A25: 16 | B25: 45772 | C25: GUAMAL | D25: SECTOR LA ISLA, RIO GUAMAL | E25: OSCAR AHUMADA | F25: =+G24 -> 15352.8 | G25: 15362.9 | H25: =+G25-F25 -> 10.1 | I25: SELECCIÓN Y RECOLECCIÓN DE ROCA PARA ENROCADO, EXCAVACIÓN DEL CANAL PARA DESVIO DEL CAUCE
A26: 17 | B26: 45773 | C26: GUAMAL | D26: SECTOR LA ISLA, RIO GUAMAL | E26: OSCAR AHUMADA | F26: =+G25 -> 15362.9 | G26: 15371.6 | H26: =+G26-F26 -> 8.7 | I26: SE REALIA EXCAVACIÓN DEL CANAL PARA DESVIO DE UN BRAZO DEL RIO
A27: 18 | B27: 45774 | C27: GUAMAL | D27: SECTOR LA ISLA, RIO GUAMAL | E27: OSCAR AHUMADA | F27: =+G26 -> 15371.6 | G27: 15381.6 | H27: =+G27-F27 -> 10 | I27: SE REALIZA EXCAVACIÓN DEL CANAL PARA DESVIO DE UN BRAZO DEL RIO, SE LOGRA CAUSAR UN 40%
A28: 19 | B28: 45775 | C28: GUAMAL | D28: SECTOR LA ISLA, RIO GUAMAL | E28: OSCAR AHUMADA | F28: =+G27 -> 15381.6 | G28: 15391.7 | H28: =+G28-F28 -> 10.1 | I28: SE REALIZA REPALEO DE MATERIAL Y EXCAVACIÓN DEL CANAL PARA DESVIAR UN BRAZO DEL RIO
A29: 20 | B29: 45776 | C29: GUAMAL | D29: SECTOR LA ISLA, RIO GUAMAL | E29: OSCAR AHUMADA | F29: =+G28 -> 15391.7 | G29: 15401.3 | H29: =+G29-F29 -> 9.6 | I29: SE REALIZA CIERRE EN LA PARTE ALTA DEL TERRAPLEN PARA CONTINUAR CON LA EXCAVACIÓN DEL CANAL Y PODER DESVIAR EL RIO
A30: 21 | B30: 45777 | C30: GUAMAL | D30: SECTOR LA ISLA, RIO GUAMAL | E30: OSCAR AHUMADA | F30: =+G29 -> 15401.3 | G30: =+F30 -> 15401.3 | H30: =+G30-F30 -> 0 | I30: MAQUINA VARADA EN EL PUNTO DE TRABAJO, EN ESPERA DE AUTORIZACIÓN PARA LA REPARACIÓN
A31: 22 | B31: 45778 | C31: GUAMAL | D31: SECTOR LA ISLA, RIO GUAMAL | E31: OSCAR AHUMADA | F31: =+G30 -> 15401.3 | G31: =+F31 -> 15401.3 | H31: =+G31-F31 -> 0 | I31: MAQUINA VARADA EN EL PUNTO DE TRABAJO, EN ESPERA DE AUTORIZACIÓN PARA LA REPARACIÓN
A32: 23 | B32: 45779 | C32: GUAMAL | D32: SECTOR LA ISLA, RIO GUAMAL | E32: OSCAR AHUMADA | F32: =+G31 -> 15401.3 | G32: =+F32 -> 15401.3 | H32: =+G32-F32 -> 0 | I32: MAQUINA VARADA EN EL PUNTO DE TRABAJO, EN ESPERA DE AUTORIZACIÓN PARA LA REPARACIÓN
A33: 24 | B33: 45780 | C33: GUAMAL | D33: SECTOR LA ISLA, RIO GUAMAL | E33: OSCAR AHUMADA | F33: =+G32 -> 15401.3 | G33: =+F33 -> 15401.3 | H33: =+G33-F33 -> 0 | I33: MAQUINA VARADA EN EL PUNTO DE TRABAJO, EN ESPERA DE AUTORIZACIÓN PARA LA REPARACIÓN
A34: 25 | B34: 45781 | C34: GUAMAL | D34: SECTOR LA ISLA, RIO GUAMAL | E34: OSCAR AHUMADA | F34: =+G33 -> 15401.3 | G34: =+F34 -> 15401.3 | H34: =+G34-F34 -> 0 | I34: MAQUINA VARADA EN EL PUNTO DE TRABAJO, EN ESPERA DE AUTORIZACIÓN PARA LA REPARACIÓN
A35: 26 | B35: 45782 | C35: GUAMAL | D35: SECTOR LA ISLA, RIO GUAMAL | E35: OSCAR AHUMADA | F35: =+G34 -> 15401.3 | G35: =+F35 -> 15401.3 | H35: =+G35-F35 -> 0 | I35: MAQUINA VARADA EN EL PUNTO DE TRABAJO, EN ESPERA DE AUTORIZACIÓN PARA LA REPARACIÓN
A36: 27 | B36: 45783 | C36: GUAMAL | D36: SECTOR LA ISLA, RIO GUAMAL | E36: OSCAR AHUMADA | F36: =+G35 -> 15401.3 | G36: 15412.5 | H36: =+G36-F36 -> 11.2 | I36: SE INICIA ENROCADO DE PROTECCIÓN Y SE CONTINUA CON CANAL PARA REALIZAR EL TRANSVASE DEL RIO
A37: 28 | B37: 45784 | C37: GUAMAL | D37: SECTOR LA ISLA, RIO GUAMAL | E37: OSCAR AHUMADA | F37: =+G36 -> 15412.5 | G37: 15423 | H37: =+G37-F37 -> 10.5 | I37: SE REALIZA AMPLIACIÓN DEL CANAL Y SE HACE EL TRASVASE DEL RIO AL CANAL
A38: 29 | B38: 45785 | C38: GUAMAL | D38: SECTOR LA ISLA, RIO GUAMAL | E38: OSCAR AHUMADA | F38: =+G37 -> 15423 | G38: 15433.2 | H38: =+G38-F38 -> 10.2 | I38: SE REALIZA RESTAURACIÓN DEL JARILLON Y REFUERZO DEL MISMO
A39: 30 | B39: 45786 | C39: GUAMAL | D39: SECTOR LA ISLA, RIO GUAMAL | E39: OSCAR AHUMADA | F39: =+G38 -> 15433.2 | G39: 15440.6 | H39: =+G39-F39 -> 7.4 | I39: SE REALIZA REFUERZO DEL JARILLON, SE PRESENTA AUMENTO DEL CAUCE DEL RIO
A40: 31 | B40: 45787 | C40: GUAMAL | D40: SECTOR LA ISLA, RIO GUAMAL | E40: OSCAR AHUMADA | F40: =+G39 -> 15440.6 | G40: 15450.9 | H40: =+G40-F40 -> 10.3 | I40: SE REALIZA EL CIERRE DEL CHORRO DEL RIO Y SE REFUERZA EL JARILLON DEL TRASVASE
A41: 32 | B41: 45788 | C41: GUAMAL | D41: SECTOR LA ISLA, RIO GUAMAL | E41: OSCAR AHUMADA | F41: =+G40 -> 15450.9 | G41: 15461.4 | H41: =+G41-F41 -> 10.5 | I41: SELECCIÓN, REPALEO Y CONFORMACIÓN DE PIEDRA PARA FORTALECER EL JARILLON
A42: 33 | B42: 45789 | C42: GUAMAL | D42: SECTOR LA ISLA, RIO GUAMAL | E42: OSCAR AHUMADA | F42: =+G41 -> 15461.4 | G42: 15470.4 | H42: =+G42-F42 -> 9 | I42: SE REALIZA REPALEO Y CONFORMACIÓN DE PIEDRA PARA PROTECIÓN DEL JARILLON
A43: 34 | B43: 45790 | C43: GUAMAL | D43: SECTOR LA ISLA, RIO GUAMAL | E43: OSCAR AHUMADA | F43: =+G42 -> 15470.4 | G43: 15480 | H43: =+G43-F43 -> 9.6 | I43: REPALEO Y CONFORMACIÓN DE PIEDRA PARA ENROCADO DEL JARILLON
A44: 35 | B44: 45791 | C44: GUAMAL | D44: SECTOR LA ISLA, RIO GUAMAL | E44: OSCAR AHUMADA | F44: =+G43 -> 15480 | G44: 15490 | H44: =+G44-F44 -> 10 | I44: RECOLECCIÓN, REPALEO Y CONFORMACIÓN DE PIEDRA PARA COSNTRUCCIÓN DE JARILLON DE PROTECCIÓN
A45: 36 | B45: 45792 | C45: GUAMAL | D45: SECTOR LA ISLA, RIO GUAMAL | E45: OSCAR AHUMADA | F45: =+G44 -> 15490 | G45: 15499.2 | H45: =+G45-F45 -> 9.2 | I45: RECOLECCIÓN, REPALEO Y CONFORMACIÓN DE PIEDRA PARA COSNTRUCCIÓN DE JARILLON DE PROTECCIÓN
A46: 37 | B46: 45793 | C46: GUAMAL | D46: SECTOR LA ISLA, RIO GUAMAL | E46: OSCAR AHUMADA | F46: =+G45 -> 15499.2 | G46: 15510 | H46: =+G46-F46 -> 10.8 | I46: CONFORMACIÓN Y CARGUE DE PIEDRA PARA JARILLON ENRROCADO
A47: 38 | B47: 45794 | C47: GUAMAL | D47: SECTOR LA ISLA, RIO GUAMAL | E47: OSCAR AHUMADA | F47: =+G46 -> 15510 | G47: 15518.6 | H47: =+G47-F47 -> 8.6 | I47: CARGUE DE PIEDRA Y CONFORMACIÓN DE ENRROCADO
A48: 39 | B48: 45795 | C48: GUAMAL | D48: SECTOR LA ISLA, RIO GUAMAL | E48: OSCAR AHUMADA | F48: =+G47 -> 15518.6 | G48: =+F48 -> 15518.6 | H48: =+G48-F48 -> 0 | I48: DIA DE DESCANSO, MAQUINA DISPONIBLE EN EL PUNTO DE TRABAJO
A49: 40 | B49: 45796 | C49: GUAMAL | D49: SECTOR LA ISLA, RIO GUAMAL | E49: OSCAR AHUMADA | F49: =+G48 -> 15518.6 | G49: 15526.4 | H49: =+G49-F49 -> 7.8 | I49: CARGUE DE PIEDRA Y CONFORMACIÓN DE ENRROCADO
A50: 41 | B50: 45797 | C50: GUAMAL | D50: SECTOR LA ISLA, RIO GUAMAL | E50: OSCAR AHUMADA | F50: =+G49 -> 15526.4 | G50: 15534 | H50: =+G50-F50 -> 7.6 | I50: CARGUE DE PIEDRA PARA EL ENRROCADO Y SE REALIZA CANAL PARA UN CIERRE DE UN BRAZO DEL RIO
A51: 42 | B51: 45798 | C51: GUAMAL | D51: SECTOR LA ISLA, RIO GUAMAL | E51: OSCAR AHUMADA | F51: =+G50 -> 15534 | G51: 15538.8 | H51: =+G51-F51 -> 4.8 | I51: CONFORMACIÓN DE ENRROCADO DE PROTECCIÓN
A52: 43 | B52: 45799 | C52: GUAMAL | D52: SECTOR LA ISLA, RIO GUAMAL | E52: OSCAR AHUMADA | F52: =+G51 -> 15538.8 | G52: =+F52 -> 15538.8 | H52: =+G52-F52 -> 0 | I52: MAQUINA DISPONIBLE EN EL PUNTO DE TRABAJO
A53: 44 | B53: 45800 | C53: GUAMAL | D53: SECTOR LA ISLA, RIO GUAMAL | E53: OSCAR AHUMADA | F53: =+G52 -> 15538.8 | G53: 15540 | H53: =+G53-F53 -> 1.2 | I53: DESPLAZAMIENTO DE LA MAQUINA HASTA EL PATIO GALICIA SERVIAMCONS
G54: TOTAL | H54: =SUM(H10:H53) -> 270
B57: Inicio | C57: Fin | D57: Horometro inicio | E57: Horometro fin | F57: Total
B58: =+SMALL(B10:B53,1) -> 45757 | C58: =LARGE(B10:B53,1) -> 45800 | D58: =SMALL(F10:F53,1) -> 15270 | E58: =LARGE(G10:G53,1) -> 15540 | F58: =+E58-D58 -> 270
E59: TOTAL | F59: =SUM(F58) -> 270
B67: LUIS MIGUEL ANGEL RAMIREZ ROMERO | G67: CARMEN LUCIA AGUILAR GOMEZ
B68: Rep. Legal SERVICIOS MAQUINARIA Y CONSTRUCCIONES SAS "SERVIMACONS S.A.S." | G68: SERVICIOS MAQUINARIA Y CONSTRUCCIONES SAS "SERVIMACONS S.A.S."
B70: REPRESENTANTE LEGAL | G70: DIRECTORA

Sheet GUAMAL - SECTOR PIO XII
H9: 0

Sheet EXCA LINK BELT 2179 #4
A1: RESUMEN GENERAL DE ACTIVIDADES EJECUTADAS
A2: CONTRATO Nº: 1040 DE 2025
A3: OBJETIVO:
A4: PERIODO DEL INFORME: | F4: AL
A5: FECHA PRESENTE ACTA:
A8: ITEM | B8: D E S C R I P C I Ó N / MAQUINA | C8: MUNICIPIO | D8: PUNTO | E8: FECHA INICIO | F8: FECHA FINAL | G8: HORAS EJECUTADAS | H8: VALOR EJECUTADO | I8: ACTIVIDAD REALIZADA
A9: 3 | B9: =+'EXCA LINK BELT #4'!C6 -> EXCAVADORA LINK BELT 2179 #4 | C9: =+'EXCA LINK BELT #4'!C10 -> GUAMAL | D9: =+'EXCA LINK BELT #4'!D10 -> SECTOR PIO XII, RIO GUAMAL | E9: =+'EXCA LINK BELT #4'!B42 -> 45757 | F9: =+'EXCA LINK BELT #4'!C42 -> 45784 | G9: =+'EXCA LINK BELT #4'!F43 -> 130 | H9: 0 | I9: =+'EXCA LINK BELT #4'!I11 -> SE REALIZA CONSTRUCCIÓN DE JARILLON PARA QUITAR PRESION DE LA MARGEN IZQUIERDA AGUAS ABAJO Y SE CENTRA PARTE DEL RIO
B10: SUBTOTAL | H10: =+H9 -> 0
B11: IVA 19% | H11: =+H10*0.19 -> 0
B12: TOTAL | H12: =+H11+H10 -> 0
B24: LUIS MIGUEL ANGEL RAMIREZ ROMERO
B25: Rep. Legal SERVICIOS MAQUINARIA Y CONSTRUCCIONES SAS "SERVIMACONS S.A.S."
B26: CONTRATISTA

Sheet EXCA LINK BELT #4
A1: REPORTE DIARIO DE HORAS
A2: CONTRATO No.
A3: OBJETIVO:
A5: REPORTE DE MAQUINARIA
A6: MAQUINA: | C6: EXCAVADORA LINK BELT 2179 #4
A8: N° | B8: FECHA | C8: LUGAR DE TRABAJO | E8: OPERADOR | F8: HOROMETRO | H8: HORAS DE TRABAJO | I8: ACTIVIDAD REALIZADA
C9: MUNICIPIO | D9: PUNTO | F9: INICIO | G9: FIN
A10: 1 | B10: 45757 | C10: GUAMAL | D10: SECTOR PIO XII, RIO GUAMAL | E10: NESTOR CORTES | F10: 13662 | G10: 13666.1 | H10: =+G10-F10 -> 4.1 | I10: DESPLAZAMIENTO DE LA MAQUINA HASTA EL PUNTO DE TRABAJO, SE INICIAN TRABAJOS DE CONSTRUCCIÓN DE JARILLON EN LA MARGEN DERECHA, PARA QUITAR PRESIÓN Y CENTRAR UN BRAZO DEL RIO
A11: 2 | B11: 45758 | C11: GUAMAL | D11: SECTOR PIO XII, RIO GUAMAL | E11: NESTOR CORTES | F11: =+G10 -> 13666.1 | G11: 13675.9 | H11: =+G11-F11 -> 9.8 | I11: SE REALIZA CONSTRUCCIÓN DE JARILLON PARA QUITAR PRESION DE LA MARGEN IZQUIERDA AGUAS ABAJO Y SE CENTRA PARTE DEL RIO
A12: 3 | B12: 45759 | C12: GUAMAL | D12: SECTOR PIO XII, RIO GUAMAL | E12: NESTOR CORTES | F12: =+G11 -> 13675.9 | G12: 13685.9 | H12: =+G12-F12 -> 10 | I12: SE REALIZA CONSTRUCCIÓN DE JARILLON PARA QUITAR PRESION DE LA MARGEN IZQUIERDA AGUAS ABAJO
A13: 4 | B13: 45760 | C13: GUAMAL | D13: SECTOR PIO XII, RIO GUAMAL | E13: NESTOR CORTES | F13: =+G12 -> 13685.9 | G13: 13695.9 | H13: =+G13-F13 -> 10 | I13: SE REALIZA CONSTRUCCIÓN DE JARILLON PARA QUITAR PRESION DE LA MARGEN IZQUIERDA AGUAS ABAJO Y EVITAR DESBORDAMIENTO DEL JARILLON ACTUAL
A14: 5 | B14: 45761 | C14: GUAMAL | D14: SECTOR PIO XII, RIO GUAMAL | E14: NESTOR CORTES | F14: =+G13 -> 13695.9 | G14: 13703.9 | H14: =+G14-F14 -> 8 | I14: SE REALIZA REFUERZO AL JARILLON Y SE ENCAUSA PARTE DEL RIO
A15: 6 | B15: 45762 | C15: GUAMAL | D15: SECTOR PIO XII, RIO GUAMAL | E15: NESTOR CORTES | F15: =+G14 -> 13703.9 | G15: 13713.9 | H15: =+G15-F15 -> 10 | I15: SE REALIZA REFORZAMIENTO AL JARILLON CON ENROCADO, SE INICIA CIERRE DE UN BRAZO DEL RIO PARA MITIGAR LA MARGEN IZQUIERDA AGUAS ABAJO
A16: 7 | B16: 45763 | C16: GUAMAL | D16: SECTOR PIO XII, RIO GUAMAL | E16: NESTOR CORTES | F16: =+G15 -> 13713.9 | G16: 13718.1 | H16: =+G16-F16 -> 4.2 | I16: SE REALIZA REFUERZO AL JARILLON Y SE ENCAUSA PARTE DEL RIO, LA MAQUINA PRESENTA UNA FUGA DE ACEITE HIDRAULICO POR UNA MANGUERA QUE SE ESTALLO
A17: 8 | B17: 45764 | C17: GUAMAL | D17: SECTOR PIO XII, RIO GUAMAL | E17: NESTOR CORTES | F17: =+G16 -> 13718.1 | G17: =+F17 -> 13718.1 | H17: =+G17-F17 -> 0 | I17: MAQUINA DISPONIBLE EN EL PUNTO DE TRABAJO, DIA DE DESCANSO POR MOTIVO DE LA SEMANA SANTA
A18: 9 | B18: 45765 | C18: GUAMAL | D18: SECTOR PIO XII, RIO GUAMAL | E18: NESTOR CORTES | F18: =+G17 -> 13718.1 | G18: =+F18 -> 13718.1 | H18: =+G18-F18 -> 0 | I18: MAQUINA DISPONIBLE EN EL PUNTO DE TRABAJO, DIA DE DESCANSO POR MOTIVO DE LA SEMANA SANTA
A19: 10 | B19: 45766 | C19: GUAMAL | D19: SECTOR PIO XII, RIO GUAMAL | E19: NESTOR CORTES | F19: =+G18 -> 13718.1 | G19: =+F19 -> 13718.1 | H19: =+G19-F19 -> 0 | I19: MAQUINA DISPONIBLE EN EL PUNTO DE TRABAJO, DIA DE DESCANSO POR MOTIVO DE LA SEMANA SANTA
A20: 11 | B20: 45767 | C20: GUAMAL | D20: SECTOR PIO XII, RIO GUAMAL | E20: NESTOR CORTES | F20: =+G19 -> 13718.1 | G20: =+F20 -> 13718.1 | H20: =+G20-F20 -> 0 | I20: MAQUINA DISPONIBLE EN EL PUNTO DE TRABAJO, DIA DE DESCANSO POR MOTIVO DE LA SEMANA SANTA
A21: 12 | B21: 45768 | C21: GUAMAL | D21: SECTOR PIO XII, RIO GUAMAL | E21: NESTOR CORTES | F21: =+G20 -> 13718.1 | G21: 13726.2 | H21: =+G21-F21 -> 8.1 | I21: SE REALIZA RECONSTRUCCION DE JARILLÓN
A22: 13 | B22: 45769 | C22: GUAMAL | D22: SECTOR PIO XII, RIO GUAMAL | E22: NESTOR CORTES | F22: =+G21 -> 13726.2 | G22: 13735 | H22: =+G22-F22 -> 8.8 | I22: SE REALIZA RECONSTRUCCIÓN DEL JARILLON PARA MITIGAR LA MARGEN IZQUIERDA AGUAS ABAJO Y SE INICA CANAL PARA CENTRAR PARTE DEL RIO
A23: 14 | B23: 45770 | C23: GUAMAL | D23: SECTOR PIO XII, RIO GUAMAL | E23: NESTOR CORTES | F23: =+G22 -> 13735 | G23: 13745 | H23: =+G23-F23 -> 10 | I23: SE REALIZA RECONSTRUCCIÓN DEL JARILLON PARA MITIGAR LA MARGEN IZQUIERDA AGUAS ABAJO Y CENTRAR PARTE DEL RIO
A24: 15 | B24: 45771 | C24: GUAMAL | D24: SECTOR PIO XII, RIO GUAMAL | E24: NESTOR CORTES | F24: =+G23 -> 13745 | G24: =+F24 -> 13745 | H24: =+G24-F24 -> 0 | I24: MAQUINA VARADA EN EL PUNTO DE TRABAJO, EN ESPERA DE LOS REPUESTOS
A25: 16 | B25: 45772 | C25: GUAMAL | D25: SECTOR PIO XII, RIO GUAMAL | E25: NESTOR CORTES | F25: =+G24 -> 13745 | G25: =+F25 -> 13745 | H25: =+G25-F25 -> 0 | I25: MAQUINA VARADA EN EL PUNTO DE TRABAJO, EN ESPERA DE LOS REPUESTOS
A26: 17 | B26: 45773 | C26: GUAMAL | D26: SECTOR PIO XII, RIO GUAMAL | E26: NESTOR CORTES | F26: =+G25 -> 13745 | G26: =+F26 -> 13745 | H26: =+G26-F26 -> 0 | I26: LOS MECANICOS REPARAN LA MAQUINA, QUEDA OPERATIVA EN EL PUNTO DE TRABAJO
A27: 18 | B27: 45774 | C27: GUAMAL | D27: SECTOR PIO XII, RIO GUAMAL | E27: NESTOR CORTES | F27: =+G26 -> 13745 | G27: =+F27 -> 13745 | H27: =+G27-F27 -> 0 | I27: DIA DE DESCANSO, MAQUINA DISPONIBLE EN EL PUNTO DE TRABAJO
A28: 19 | B28: 45775 | C28: GUAMAL | D28: SECTOR PIO XII, RIO GUAMAL | E28: NESTOR CORTES | F28: =+G27 -> 13745 | G28: 13755 | H28: =+G28-F28 -> 10 | I28: SE REALIZA CONSTRUCCIÓN DE JARILLON EN LA MARGEN IZQUIERDA AGUAS ABAJO PARA PODER CENTRAR EL RIO
A29: 20 | B29: 45776 | C29: GUAMAL | D29: SECTOR PIO XII, RIO GUAMAL | E29: NESTOR CORTES | F29: =+G28 -> 13755 | G29: 13764.6 | H29: =+G29-F29 -> 9.6 | I29: SE REALIZA CONSTRUCCIÓN DE JARILLON PARA MITIGAR LA MARGEN IZQUIERDA AGUAS ABAJO Y CENTRAR PARTE DEL RIO
A30: 21 | B30: 45777 | C30: GUAMAL | D30: SECTOR PIO XII, RIO GUAMAL | E30: NESTOR CORTES | F30: =+G29 -> 13764.6 | G30: 13767.4 | H30: =+G30-F30 -> 2.8 | I30: SE INICIA EL TRABAJO DESPUES DE LAS 2 PM, ESPERANDO QUE EL NIVEL DEL CAUCE BAJE. SE INICIA CON UN CIERRE EN LA MARGEN IZQUIERDA AGUAS ABAJO Y QUITAR PRESIÓN SOBRE EL COSTADO IZQUIERDO
A31: 22 | B31: 45778 | C31: GUAMAL | D31: SECTOR PIO XII, RIO GUAMAL | E31: OSCAR AHUMADA | F31: =+G30 -> 13767.4 | G31: =+F31 -> 13767.4 | H31: =+G31-F31 -> 0 | I31: MAQUINA DISPONIBLE EN EL PUNTO DE TRABAJO, DIA DE DESCANSO
A32: 23 | B32: 45779 | C32: GUAMAL | D32: SECTOR PIO XII, RIO GUAMAL | E32: OSCAR AHUMADA | F32: =+G31 -> 13767.4 | G32: =+F32 -> 13767.4 | H32: =+G32-F32 -> 0 | I32: MAQUINA DISPONIBLE EN EL PUNTO DE TRABAJO, SE PRESENTA UN AUMENTO EN EL CAUCE DEL RIO
A33: 24 | B33: 45780 | C33: GUAMAL | D33: SECTOR PIO XII, RIO GUAMAL | E33: OSCAR AHUMADA | F33: =+G32 -> 13767.4 | G33: 13778.5 | H33: =+G33-F33 -> 11.1 | I33: SE REALIZA CIERRE DEL RO Y SE INICIA REPALEO DE MATERIAL PARA PROTECCIÓN DEL JARILLON ANTIGUO
A34: 25 | B34: 45781 | C34: GUAMAL | D34: SECTOR PIO XII, RIO GUAMAL | E34: OSCAR AHUMADA | F34: =+G33 -> 13778.5 | G34: 13789.5 | H34: =+G34-F34 -> 11 | I34: REPALEO DE MATERIAL PARA REFUERZO DEL JARILLON ANTIGUO
A35: 26 | B35: 45782 | C35: GUAMAL | D35: SECTOR PIO XII, RIO GUAMAL | E35: OSCAR AHUMADA | F35: =+G34 -> 13789.5 | G35: 13791.3 | H35: =+G35-F35 -> 1.8 | I35: REPALEO DE MATERIAL PARA ESPOLON DE PROTECCIÓN
A36: 27 | B36: 45783 | C36: GUAMAL | D36: SECTOR PIO XII, RIO GUAMAL | E36: OSCAR AHUMADA | F36: =+G35 -> 13791.3 | G36: =+F36 -> 13791.3 | H36: =+G36-F36 -> 0 | I36: MAQUINA DISPONIBLE EN EL PUNTO DE TRABAJO, EN ESPERA DE MOVIMIENTO
A37: 28 | B37: 45784 | C37: GUAMAL | D37: SECTOR PIO XII, RIO GUAMAL | E37: OSCAR AHUMADA | F37: =+G36 -> 13791.3 | G37: 13792 | H37: =+G37-F37 -> 0.7 | I37: DESPLAZAMIENTO DE LA MAQUINA HASTA EL PUNTO DE EMBARQUE
G38: TOTAL | H38: =SUM(H10:H37) -> 130
B41: Inicio | C41: Fin | D41: Horometro inicio | E41: Horometro fin | F41: Total
B42: =+SMALL(B10:B37,1) -> 45757 | C42: =LARGE(B10:B37,1) -> 45784 | D42: =SMALL(F10:F37,1) -> 13662 | E42: =LARGE(G10:G37,1) -> 13792 | F42: =+E42-D42 -> 130
E43: TOTAL | F43: =SUM(F42) -> 130
B51: LUIS MIGUEL ANGEL RAMIREZ ROMERO | G51: CARMEN LUCIA AGUILAR GOMEZ
B52: Rep. Legal SERVICIOS MAQUINARIA Y CONSTRUCCIONES SAS "SERVIMACONS S.A.S." | G52: SERVICIOS MAQUINARIA Y CONSTRUCCIONES SAS "SERVIMACONS S.A.S."
B54: REPRESENTANTE LEGAL | G54: DIRECTORA

Sheet VILLAVICENCIO - PARCELAS
A1: RESUMEN GENERAL DE ACTIVIDADES EJECUTADAS
A2: CONTRATO Nº: 1040 DE 2025
A3: OBJETIVO: SERVICIO PARA LA OPERACIÓN DE LA MAQUINARIA AMARILLA ADSCRITA A LA DIRECCIÓN DEPARTAMENTAL PARA LA GESTIÓN DEL RIESGO DE DESASTRES PARA LA REDUCCIÓN DEL RIESGO EN LOS VEINTINUEVE (29) MUNICIPIOS DEL DEPARTAMENTO DEL META.
A4: PERIODO DEL INFORME: | F4: AL
A5: FECHA PRESENTE ACTA:
A8: ITEM | B8: D E S C R I P C I Ó N / MAQUINA | C8: MUNICIPIO | D8: PUNTO | E8: FECHA INICIO | F8: FECHA FINAL | G8: HORAS EJECUTADAS | H8: VALOR EJECUTADO | I8: ACTIVIDAD REALIZADA
B9: =+'VOLQUETA CHEVROLET OJT163 #3'!B10 -> VOLQUETA CHEVROLET OJT163 #3 | C9: =+'VOLQUETA CHEVROLET OJT163 #3'!C10 -> VILLAVICENCIO | D9: =+'VOLQUETA CHEVROLET OJT163 #3'!D10 -> PARCELAS DEL PROGRESO | E9: =+'VOLQUETA CHEVROLET OJT163 #3'!E10 -> 45789 | F9: =+'VOLQUETA CHEVROLET OJT163 #3'!F10 -> 45796 | G9: =+'VOLQUETA CHEVROLET OJT163 #3'!G10 -> 65.4 | H9: 0 | I9: =+'VOLQUETA CHEVROLET OJT163 #3'!I10 -> TRANSPORTE DE MATERIAL DEL RIO GUATIQUIA PARA CONSTRUCCIÓN DEL JARILLON
B10: =+'VOLQUETA CHEVROLET OJT165 #5'!B10 -> VOLQUETA CHEVROLET OJT165 #5 | C10: =+'VOLQUETA CHEVROLET OJT165 #5'!C10 -> VILLAVICENCIO | D10: =+'VOLQUETA CHEVROLET OJT165 #5'!D10 -> PARCELAS DEL PROGRESO | E10: =+'VOLQUETA CHEVROLET OJT165 #5'!E10 -> 45789 | F10: =+'VOLQUETA CHEVROLET OJT165 #5'!F10 -> 45796 | G10: =+'VOLQUETA CHEVROLET OJT165 #5'!G10 -> 65 | H10: =+'VOLQUETA CHEVROLET OJT165 #5'!H10 -> 0 | I10: =+'VOLQUETA CHEVROLET OJT165 #5'!I10 -> TRANSPORTE DE MATERIAL DEL RIO GUATIQUIA PARA CONSTRUCCIÓN DEL JARILLON
B11: =+'VOLQUETA CHEVROLET OJT162 #2'!B10 -> VOLQUETA CHEVROLET OJT162 #2 | C11: =+'VOLQUETA CHEVROLET OJT162 #2'!C10 -> VILLAVICENCIO | D11: =+'VOLQUETA CHEVROLET OJT162 #2'!D10 -> PARCELAS DEL PROGRESO | E11: =+'VOLQUETA CHEVROLET OJT162 #2'!E10 -> 45790 | F11: =+'VOLQUETA CHEVROLET OJT162 #2'!F10 -> 45793 | G11: =+'VOLQUETA CHEVROLET OJT162 #2'!G10 -> 19.6 | H11: =+'VOLQUETA CHEVROLET OJT162 #2'!H10 -> 0 | I11: =+'VOLQUETA CHEVROLET OJT162 #2'!I10 -> TRANSPORTE DE MATERIAL DEL RIO GUATIQUIA PARA CONSTRUCCIÓN DEL JARILLON
B12: SUBTOTAL | H12: =+H9+H10+H11 -> 0
B13: IVA 19% | H13: =+H12*0.19 -> 0
B14: TOTAL | H14: =+H13+H12 -> 0
B26: LUIS MIGUEL ANGEL RAMIREZ ROMERO
B27: Rep. Legal SERVICIOS MAQUINARIA Y CONSTRUCCIONES SAS "SERVIMACONS S.A.S."
B28: CONTRATISTA

Sheet VOLQUETA CHEVROLET OJT163 #3
A1: RESUMEN GENERAL DE ACTIVIDADES EJECUTADAS
A2: CONTRATO Nº: 1064 DE 2024
A3: OBJETO: SERVICIO PARA LA OPERACIÓN DE LA MAQUINARIA AMARILLA ADSCRITA A LA DIRECCIÓN DEPARTAMENTAL PARA LA GESTIÓN DEL RIESGO DE DESASTRES EN LA ATENCIÓN DE SITUACIONES DE EMERGENCIA Y/O DESASTRES EN EL DEPARTAMENTO DEL META
A4: PERIODO DEL INFORME: | F4: AL
A5: FECHA PRESENTE ACTA:
A8: ITEM | B8: DESCRIPCIÓN / MAQUINA | C8: MUNICIPIO | D8: PUNTO | E8: FECHA INICIO | F8: FECHA FINAL | G8: HORAS EJECUTADAS | H8: VALOR EJECUTADO | I8: ACTIVIDAD REALIZADA
A9: 1.4 | B9: FUNCIONAMIENTO Y OPERACIÓN DE VOLQUETA SENCILLA FTR CHEVROLET CAPACIDAD DE CARGUE DE 6 M3 | H9: 0
B10: =+'OJT163 #3'!C6 -> VOLQUETA CHEVROLET OJT163 #3 | C10: =+'OJT163 #3'!C10 -> VILLAVICENCIO | D10: =+'OJT163 #3'!D10 -> PARCELAS DEL PROGRESO | E10: =+'OJT163 #3'!B21 -> 45789 | F10: =+'OJT163 #3'!C21 -> 45796 | G10: =+'OJT163 #3'!H18 -> 65.4 | H10: =+G10*'PLAN DE ACCIÓN'!H38 -> 0 | I10: =+'OJT163 #3'!L10 -> TRANSPORTE DE MATERIAL DEL RIO GUATIQUIA PARA CONSTRUCCIÓN DEL JARILLON
B11: SUBTOTAL | H11: =+H10 -> 0
B12: IVA 19% | H12: =+H11*0.19 -> 0
B13: TOTAL | H13: =+H12+H11 -> 0
B18: LUIS MIGUEL ANGEL RAMIREZ ROMERO
B19: Rep. Legal SERVICIOS MAQUINARIA Y CONSTRUCCIONES SAS "SERVIMACONS S.A.S."
B20: CONTRATISTA

Sheet OJT163 #3
A1: REPORTE DIARIO DE HORAS
A2: CONTRATO No. 1064 DE 2024
A3: OBJETO: SERVICIO PARA LA OPERACIÓN DE LA MAQUINARIA AMARILLA ADSCRITA A LA DIRECCIÓN DEPARTAMENTAL PARA LA GESTIÓN DEL RIESGO DE DESASTRES EN LA ATENCIÓN DE SITUACIONES DE EMERGENCIA Y/O DESASTRES EN EL DEPARTAMENTO DEL META
A5: REPORTE DE MAQUINARIA
A6: MAQUINA: | C6: VOLQUETA CHEVROLET OJT163 #3
A8: N° | B8: FECHA | C8: LUGAR DE TRABAJO | E8: OPERADOR | F8: HOROMETRO | H8: HORAS DE TRABAJO | I8: KM INICIAL | J8: KM FINAL | K8: TOTAL KM | L8: ACTIVIDAD REALIZADA | M8: VIAJES
C9: MUNICIPIO | D9: PUNTO | F9: INICIO | G9: FIN
A10: 1 | B10: 45789 | C10: VILLAVICENCIO | D10: PARCELAS DEL PROGRESO | E10: RODRIGO BERNAL | F10: 735.5 | G10: 741.9 | H10: =+G10-F10 -> 6.4 | I10: 106112 | J10: 106132 | K10: =+J10-I10 -> 20 | L10: TRANSPORTE DE MATERIAL DEL RIO GUATIQUIA PARA CONSTRUCCIÓN DEL JARILLON | M10: 16
A11: 2 | B11: 45790 | C11: VILLAVICENCIO | D11: PARCELAS DEL PROGRESO | E11: RODRIGO BERNAL | F11: =+G10 -> 741.9 | G11: 751.6 | H11: =+G11-F11 -> 9.7 | I11: =+J10 -> 106132 | J11: 106155 | K11: =+J11-I11 -> 23 | L11: TRANSPORTE DE MATERIAL DEL RIO GUATIQUIA PARA CONSTRUCCIÓN DEL JARILLON | M11: 42
A12: 3 | B12: 45791 | C12: VILLAVICENCIO | D12: PARCELAS DEL PROGRESO | E12: RODRIGO BERNAL | F12: =+G11 -> 751.6 | G12: 760.6 | H12: =+G12-F12 -> 9 | I12: =+J11 -> 106155 | J12: 106177 | K12: =+J12-I12 -> 22 | L12: TRANSPORTE DE MATERIAL DEL RIO GUATIQUIA PARA CONSTRUCCIÓN DEL JARILLON | M12: 39
A13: 4 | B13: 45792 | C13: VILLAVICENCIO | D13: PARCELAS DEL PROGRESO | E13: RODRIGO BERNAL | F13: =+G12 -> 760.6 | G13: 770.8 | H13: =+G13-F13 -> 10.2 | I13: =+J12 -> 106177 | J13: 106197 | K13: =+J13-I13 -> 20 | L13: TRANSPORTE DE MATERIAL DEL RIO GUATIQUIA PARA CONSTRUCCIÓN DEL JARILLON | M13: 40
A14: 5 | B14: 45793 | C14: VILLAVICENCIO | D14: PARCELAS DEL PROGRESO | E14: RODRIGO BERNAL | F14: =+G13 -> 770.8 | G14: 781.3 | H14: =+G14-F14 -> 10.5 | I14: =+J13 -> 106197 | J14: 106222 | K14: =+J14-I14 -> 25 | L14: TRANSPORTE DE MATERIAL DEL RIO GUATIQUIA PARA CONSTRUCCIÓN DEL JARILLON | M14: 39
A15: 6 | B15: 45794 | C15: VILLAVICENCIO | D15: PARCELAS DEL PROGRESO | E15: RODRIGO BERNAL | F15: =+G14 -> 781.3 | G15: 791 | H15: =+G15-F15 -> 9.7 | I15: =+J14 -> 106222 | J15: 106251 | K15: =+J15-I15 -> 29 | L15: TRANSPORTE DE MATERIAL DEL RIO GUATIQUIA PARA CONSTRUCCIÓN DEL JARILLON | M15: 45
A16: 7 | B16: 45795 | C16: VILLAVICENCIO | D16: PARCELAS DEL PROGRESO | E16: RODRIGO BERNAL | F16: =+G15 -> 791 | G16: =+F16 -> 791 | H16: =+G16-F16 -> 0 | I16: =+J15 -> 106251 | J16: =+I16 -> 106251 | K16: =+J16-I16 -> 0 | L16: DIA DE DESCANSO, MAQUINA DISPONIBLE EN EL PUNTO DE TRABAJO | M16: 0
A17: 8 | B17: 45796 | C17: VILLAVICENCIO | D17: PARCELAS DEL PROGRESO | E17: RODRIGO BERNAL | F17: =+G16 -> 791 | G17: 800.9 | H17: =+G17-F17 -> 9.9 | I17: =+J16 -> 106251 | J17: 106273 | K17: =+J17-I17 -> 22 | L17: TRANSPORTE DE MATERIAL DEL RIO GUATIQUIA PARA CONSTRUCCIÓN DEL JARILLON | M17: 40 | N17: 45827
G18: TOTAL | H18: =SUM(H10:H17) -> 65.4
B20: Inicio | C20: Fin | D20: Horometro inicio | E20: Horometro fin | F20: Total
B21: =SMALL(B10:B17,1) -> 45789 | C21: =LARGE(B10:B17,1) -> 45796 | D21: =SMALL(F10:F17,1) -> 735.5 | E21: =LARGE(G10:G17,1) -> 800.9 | F21: =+E21-D21 -> 65.4
E22: TOTAL | F22: =SUM(F21:F21) -> 65.4
B29: LUIS MIGUEL ANGEL RAMIREZ ROMERO | I29: CARMEN LUCIA AGUILAR GOMEZ
B30: Rep. Legal SERVICIOS MAQUINARIA Y CONSTRUCCIONES SAS "SERVIMACONS S.A.S." | I30: SERVICIOS MAQUINARIA Y CONSTRUCCIONES SAS "SERVIMACONS S.A.S."
B32: REPRESENTANTE LEGAL | I32: DIRECTORA

Sheet VOLQUETA CHEVROLET OJT165 #5
A1: RESUMEN GENERAL DE ACTIVIDADES EJECUTADAS
A2: CONTRATO Nº: 1064 DE 2024
A3: OBJETO: SERVICIO PARA LA OPERACIÓN DE LA MAQUINARIA AMARILLA ADSCRITA A LA DIRECCIÓN DEPARTAMENTAL PARA LA GESTIÓN DEL RIESGO DE DESASTRES EN LA ATENCIÓN DE SITUACIONES DE EMERGENCIA Y/O DESASTRES EN EL DEPARTAMENTO DEL META
A4: PERIODO DEL INFORME: | F4: AL
A5: FECHA PRESENTE ACTA:
A8: ITEM | B8: DESCRIPCIÓN / MAQUINA | C8: MUNICIPIO | D8: PUNTO | E8: FECHA INICIO | F8: FECHA FINAL | G8: HORAS EJECUTADAS | H8: VALOR EJECUTADO | I8: ACTIVIDAD REALIZADA
A9: 1.4 | B9: FUNCIONAMIENTO Y OPERACIÓN DE VOLQUETA SENCILLA FTR CHEVROLET CAPACIDAD DE CARGUE DE 6 M3 | H9: 0
B10: =+'OJT165 #5'!C6 -> VOLQUETA CHEVROLET OJT165 #5 | C10: =+'OJT165 #5'!C10 -> VILLAVICENCIO | D10: =+'OJT165 #5'!D10 -> PARCELAS DEL PROGRESO | E10: =+'OJT165 #5'!B21 -> 45789 | F10: =+'OJT165 #5'!C21 -> 45796 | G10: =+'OJT165 #5'!H18 -> 65 | H10: =+G10*'PLAN DE ACCIÓN'!H38 -> 0 | I10: =+'OJT165 #5'!L10 -> TRANSPORTE DE MATERIAL DEL RIO GUATIQUIA PARA CONSTRUCCIÓN DEL JARILLON
B11: SUBTOTAL | H11: =+H10 -> 0
B12: IVA 19% | H12: =+H11*0.19 -> 0
B13: TOTAL | H13: =+H12+H11 -> 0
B18: LUIS MIGUEL ANGEL RAMIREZ ROMERO
B19: Rep. Legal SERVICIOS MAQUINARIA Y CONSTRUCCIONES SAS "SERVIMACONS S.A.S."
B20: CONTRATISTA

Sheet OJT165 #5
A1: REPORTE DIARIO DE HORAS
A2: CONTRATO No. 1064 DE 2024
A3: OBJETO: SERVICIO PARA LA OPERACIÓN DE LA MAQUINARIA AMARILLA ADSCRITA A LA DIRECCIÓN DEPARTAMENTAL PARA LA GESTIÓN DEL RIESGO DE DESASTRES EN LA ATENCIÓN DE SITUACIONES DE EMERGENCIA Y/O DESASTRES EN EL DEPARTAMENTO DEL META
A5: REPORTE DE MAQUINARIA
A6: MAQUINA: | C6: VOLQUETA CHEVROLET OJT165 #5
A8: N° | B8: FECHA | C8: LUGAR DE TRABAJO | E8: OPERADOR | F8: HOROMETRO | H8: HORAS DE TRABAJO | I8: KM INICIAL | J8: KM FINAL | K8: TOTAL KM | L8: ACTIVIDAD REALIZADA | M8: VIAJES
C9: MUNICIPIO | D9: PUNTO | F9: INICIO | G9: FIN
A10: 1 | B10: 45789 | C10: VILLAVICENCIO | D10: PARCELAS DEL PROGRESO | E10: JAIME TURRIAGO | F10: 645.9 | G10: 651.4 | H10: =+G10-F10 -> 5.5 | I10: 112067 | J10: 112084 | K10: =+J10-I10 -> 17 | L10: TRANSPORTE DE MATERIAL DEL RIO GUATIQUIA PARA CONSTRUCCIÓN DEL JARILLON | M10: 16
A11: 2 | B11: 45790 | C11: VILLAVICENCIO | D11: PARCELAS DEL PROGRESO | E11: JAIME TURRIAGO | F11: =+G10 -> 651.4 | G11: 661.4 | H11: =+G11-F11 -> 10 | I11: =+J10 -> 112084 | J11: 112115 | K11: =+J11-I11 -> 31 | L11: TRANSPORTE DE MATERIAL DEL RIO GUATIQUIA PARA CONSTRUCCIÓN DEL JARILLON | M11: 42
A12: 3 | B12: 45791 | C12: VILLAVICENCIO | D12: PARCELAS DEL PROGRESO | E12: JAIME TURRIAGO | F12: =+G11 -> 661.4 | G12: 670.4 | H12: =+G12-F12 -> 9 | I12: =+J11 -> 112115 | J12: 112142 | K12: =+J12-I12 -> 27 | L12: TRANSPORTE DE MATERIAL DEL RIO GUATIQUIA PARA CONSTRUCCIÓN DEL JARILLON | M12: 40
A13: 4 | B13: 45792 | C13: VILLAVICENCIO | D13: PARCELAS DEL PROGRESO | E13: JAIME TURRIAGO | F13: =+G12 -> 670.4 | G13: 680.5 | H13: =+G13-F13 -> 10.1 | I13: =+J12 -> 112142 | J13: 112170 | K13: =+J13-I13 -> 28 | L13: TRANSPORTE DE MATERIAL DEL RIO GUATIQUIA PARA CONSTRUCCIÓN DEL JARILLON | M13: 40
A14: 5 | B14: 45793 | C14: VILLAVICENCIO | D14: PARCELAS DEL PROGRESO | E14: JAIME TURRIAGO | F14: =+G13 -> 680.5 | G14: 691.3 | H14: =+G14-F14 -> 10.8 | I14: =+J13 -> 112170 | J14: 112200 | K14: =+J14-I14 -> 30 | L14: TRANSPORTE DE MATERIAL DEL RIO GUATIQUIA PARA CONSTRUCCIÓN DEL JARILLON
A15: 6 | B15: 45794 | C15: VILLAVICENCIO | D15: PARCELAS DEL PROGRESO | E15: JAIME TURRIAGO | F15: =+G14 -> 691.3 | G15: 701 | H15: =+G15-F15 -> 9.7 | I15: =+J14 -> 112200 | J15: 112236 | K15: =+J15-I15 -> 36 | L15: TRANSPORTE DE MATERIAL DEL RIO GUATIQUIA PARA CONSTRUCCIÓN DEL JARILLON
A16: 7 | B16: 45795 | C16: VILLAVICENCIO | D16: PARCELAS DEL PROGRESO | E16: JAIME TURRIAGO | F16: =+G15 -> 701 | G16: =+F16 -> 701 | H16: =+G16-F16 -> 0 | I16: =+J15 -> 112236 | J16: =+I16 -> 112236 | K16: =+J16-I16 -> 0 | L16: DIA DE DESCANSO, MAQUINA DISPONIBLE EN EL PUNTO DE TRABAJO | M16: 0
A17: 8 | B17: 45796 | C17: VILLAVICENCIO | D17: PARCELAS DEL PROGRESO | E17: JAIME TURRIAGO | F17: =+G16 -> 701 | G17: 710.9 | H17: =+G17-F17 -> 9.9 | I17: =+J16 -> 112236 | J17: 112266 | K17: =+J17-I17 -> 30 | L17: TRANSPORTE DE MATERIAL DEL RIO GUATIQUIA PARA CONSTRUCCIÓN DEL JARILLON | M17: 40 | N17: 45827
G18: TOTAL | H18: =SUM(H10:H17) -> 65
B20: Inicio | C20: Fin | D20: Horometro inicio | E20: Horometro fin | F20: Total
B21: =SMALL(B10:B17,1) -> 45789 | C21: =LARGE(B10:B17,1) -> 45796 | D21: =SMALL(F10:F17,1) -> 645.9 | E21: =LARGE(G10:G17,1) -> 710.9 | F21: =+E21-D21 -> 65
E22: TOTAL | F22: =SUM(F21:F21) -> 65
B29: LUIS MIGUEL ANGEL RAMIREZ ROMERO | I29: CARMEN LUCIA AGUILAR GOMEZ
B30: Rep. Legal SERVICIOS MAQUINARIA Y CONSTRUCCIONES SAS "SERVIMACONS S.A.S." | I30: SERVICIOS MAQUINARIA Y CONSTRUCCIONES SAS "SERVIMACONS S.A.S."
B32: REPRESENTANTE LEGAL | I32: DIRECTORA

Sheet VOLQUETA CHEVROLET OJT162 #2
A1: RESUMEN GENERAL DE ACTIVIDADES EJECUTADAS
A2: CONTRATO Nº: 1064 DE 2024
A3: OBJETO: SERVICIO PARA LA OPERACIÓN DE LA MAQUINARIA AMARILLA ADSCRITA A LA DIRECCIÓN DEPARTAMENTAL PARA LA GESTIÓN DEL RIESGO DE DESASTRES EN LA ATENCIÓN DE SITUACIONES DE EMERGENCIA Y/O DESASTRES EN EL DEPARTAMENTO DEL META
A4: PERIODO DEL INFORME: | F4: AL
A5: FECHA PRESENTE ACTA:
A8: ITEM | B8: DESCRIPCIÓN / MAQUINA | C8: MUNICIPIO | D8: PUNTO | E8: FECHA INICIO | F8: FECHA FINAL | G8: HORAS EJECUTADAS | H8: VALOR EJECUTADO | I8: ACTIVIDAD REALIZADA
A9: 1.4 | B9: FUNCIONAMIENTO Y OPERACIÓN DE VOLQUETA SENCILLA FTR CHEVROLET CAPACIDAD DE CARGUE DE 6 M3 | H9: 0
B10: =+'OJT162 #2'!C6 -> VOLQUETA CHEVROLET OJT162 #2 | C10: =+'OJT162 #2'!C10 -> VILLAVICENCIO | D10: =+'OJT162 #2'!D10 -> PARCELAS DEL PROGRESO | E10: =+'OJT162 #2'!B17 -> 45790 | F10: =+'OJT162 #2'!C17 -> 45793 | G10: =+'OJT162 #2'!H14 -> 19.6 | H10: =+G10*'PLAN DE ACCIÓN'!H38 -> 0 | I10: =+'OJT162 #2'!L10 -> TRANSPORTE DE MATERIAL DEL RIO GUATIQUIA PARA CONSTRUCCIÓN DEL JARILLON
B11: SUBTOTAL | H11: =+H10 -> 0
B12: IVA 19% | H12: =+H11*0.19 -> 0
B13: TOTAL | H13: =+H12+H11 -> 0
B18: LUIS MIGUEL ANGEL RAMIREZ ROMERO
B19: Rep. Legal SERVICIOS MAQUINARIA Y CONSTRUCCIONES SAS "SERVIMACONS S.A.S."
B20: CONTRATISTA

Sheet OJT162 #2
A1: REPORTE DIARIO DE HORAS
A2: CONTRATO No. 1064 DE 2024
A3: OBJETO: SERVICIO PARA LA OPERACIÓN DE LA MAQUINARIA AMARILLA ADSCRITA A LA DIRECCIÓN DEPARTAMENTAL PARA LA GESTIÓN DEL RIESGO DE DESASTRES EN LA ATENCIÓN DE SITUACIONES DE EMERGENCIA Y/O DESASTRES EN EL DEPARTAMENTO DEL META
A5: REPORTE DE MAQUINARIA
A6: MAQUINA: | C6: VOLQUETA CHEVROLET OJT162 #2
A8: N° | B8: FECHA | C8: LUGAR DE TRABAJO | E8: OPERADOR | F8: HOROMETRO | H8: HORAS DE TRABAJO | I8: KM INICIAL | J8: KM FINAL | K8: TOTAL KM | L8: ACTIVIDAD REALIZADA | M8: VIAJES
C9: MUNICIPIO | D9: PUNTO | F9: INICIO | G9: FIN
A10: 1 | B10: 45790 | C10: VILLAVICENCIO | D10: PARCELAS DEL PROGRESO | E10: ALEXANDER VARELA | F10: 856.2 | G10: 859.3 | H10: =+G10-F10 -> 3.1 | I10: 106209 | J10: 106222 | K10: =+J10-I10 -> 13 | L10: TRANSPORTE DE MATERIAL DEL RIO GUATIQUIA PARA CONSTRUCCIÓN DEL JARILLON | M10: 6 | N10: HORAS DE RODRIGO BERNAL
A11: 2 | B11: 45791 | C11: VILLAVICENCIO | D11: PARCELAS DEL PROGRESO | E11: ALEXANDER VARELA | F11: =+G10 -> 859.3 | G11: 859.3 | H11: =+G11-F11 -> 0 | I11: =+J10 -> 106222 | J11: 106222 | K11: =+J11-I11 -> 0 | L11: VOLQUETA DISPONIBLE EN EL PUNTO DE TRABAJO | M11: 0
A12: 3 | B12: 45792 | C12: VILLAVICENCIO | D12: PARCELAS DEL PROGRESO | E12: ALEXANDER VARELA | F12: =+G11 -> 859.3 | G12: 868.2 | H12: =+G12-F12 -> 8.9 | I12: =+J11 -> 106222 | J12: 106239 | K12: =+J12-I12 -> 17 | L12: TRANSPORTE DE MATERIAL DEL RIO GUATIQUIA PARA CONSTRUCCIÓN DEL JARILLON | M12: 30
A13: 4 | B13: 45793 | C13: VILLAVICENCIO | D13: PARCELAS DEL PROGRESO | E13: ALEXANDER VARELA | F13: =+G12 -> 868.2 | G13: 875.8 | H13: =+G13-F13 -> 7.6 | I13: =+J12 -> 106239 | J13: 106260 | K13: =+J13-I13 -> 21 | L13: TRANSPORTE DE MATERIAL DEL RIO GUATIQUIA PARA CONSTRUCCIÓN DEL JARILLON | M13: 19
G14: TOTAL | H14: =SUM(H10:H13) -> 19.6
B16: Inicio | C16: Fin | D16: Horometro inicio | E16: Horometro fin | F16: Total
B17: =SMALL(B10:B13,1) -> 45790 | C17: =LARGE(B10:B13,1) -> 45793 | D17: =SMALL(F10:F13,1) -> 856.2 | E17: =LARGE(G10:G13,1) -> 875.8 | F17: =+E17-D17 -> 19.6
E18: TOTAL | F18: =SUM(F17:F17) -> 19.6
B25: LUIS MIGUEL ANGEL RAMIREZ ROMERO | I25: CARMEN LUCIA AGUILAR GOMEZ
B26: Rep. Legal SERVICIOS MAQUINARIA Y CONSTRUCCIONES SAS "SERVIMACONS S.A.S." | I26: SERVICIOS MAQUINARIA Y CONSTRUCCIONES SAS "SERVIMACONS S.A.S."
B28: REPRESENTANTE LEGAL | I28: DIRECTORA

Sheet EL CASTILLO-PUENTE LA AMISTAD
A1: RESUMEN GENERAL DE ACTIVIDADES EJECUTADAS
A2: CONTRATO Nº: 1040 DE 2025
A3: OBJETIVO: SERVICIO PARA LA OPERACIÓN DE LA MAQUINARIA AMARILLA ADSCRITA A LA DIRECCIÓN DEPARTAMENTAL PARA LA GESTIÓN DEL RIESGO DE DESASTRES PARA LA REDUCCIÓN DEL RIESGO EN LOS VEINTINUEVE (29) MUNICIPIOS DEL DEPARTAMENTO DEL META.
A4: PERIODO DEL INFORME: | F4: AL
A5: FECHA PRESENTE ACTA:
A8: ITEM | B8: D E S C R I P C I Ó N / MAQUINA | C8: MUNICIPIO | D8: PUNTO | E8: FECHA INICIO | F8: FECHA FINAL | G8: HORAS EJECUTADAS | H8: VALOR EJECUTADO | I8: ACTIVIDAD REALIZADA
A9: 3 | B9: =+'EXCA LINK BELT 2181 #.1'!B9 -> EXCAVADORA LINK BELT 2181 #1 | C9: =+'EXCA LINK BELT 2181 #.1'!C9 -> EL CASTILLO | D9: =+'EXCA LINK BELT 2181 #.1'!D9 -> PUENTE LA AMISTAD, RIO ARIARI | E9: =+'EXCA LINK BELT 2181 #.1'!E9 -> 45779 | F9: =+'EXCA LINK BELT 2181 #.1'!F9 -> 45793 | G9: =+'EXCA LINK BELT 2181 #.1'!G9 -> 106.5 | H9: 0 | I9: =+'EXCA LINK BELT 2181 #.1'!I9 -> SE TRANSPALEA MATERIAL PARA AMPLIACIÓN DE CANAL EN EL RIO ARIARI
B10: =+'EXCA LINK BELT 2180.. #5'!B9 -> EXCAVADORA LINK BELT 2180 #5 | C10: =+'EXCA LINK BELT 2180.. #5'!C9 -> EL CASTILLO | D10: =+'EXCA LINK BELT 2180.. #5'!D9 -> PUENTE LA AMISTAD, RIO ARIARI | E10: =+'EXCA LINK BELT 2180.. #5'!E9 -> 45784 | F10: =+'EXCA LINK BELT 2180.. #5'!F9 -> 45802 | G10: =+'EXCA LINK BELT 2180.. #5'!G9 -> 107.8 | H10: =+'EXCA LINK BELT 2180.. #5'!H9 -> 0 | I10: =+'EXCA LINK BELT 2180.. #5'!I9 -> SE REALIZA LA CONSTRUCCIÓN DEL CANAL PARA DESVIO DEL CAUCE DEL RIO
B11: =+'EXCA LINK BELT 2179 #4.'!B9 -> EXCAVADORA LINK BELT 2179 #4 | C11: =+'EXCA LINK BELT 2179 #4.'!C9 -> EL CASTILLO | D11: =+'EXCA LINK BELT 2179 #4.'!D9 -> PUENTE LA AMISTAD, RIO ARIARI | E11: =+'EXCA LINK BELT 2179 #4.'!E9 -> 45784 | F11: =+'EXCA LINK BELT 2179 #4.'!F9 -> 45804 | G11: =+'EXCA LINK BELT 2179 #4.'!G9 -> 8.7 | H11: =+'EXCA LINK BELT 2179 #4.'!H9 -> 0 | I11: =+'EXCA LINK BELT 2179 #4.'!I9 -> SE REALIZA LA CONSTRUCCIÓN DEL CANAL PARA DESVIO DEL CAUCE DEL RIO
B12: SUBTOTAL | H12: =+H11+H9+H10 -> 0
B13: IVA 19% | H13: =+H12*0.19 -> 0
B14: TOTAL | H14: =+H13+H12 -> 0
B26: LUIS MIGUEL ANGEL RAMIREZ ROMERO
B27: Rep. Legal SERVICIOS MAQUINARIA Y CONSTRUCCIONES SAS "SERVIMACONS S.A.S."
B28: CONTRATISTA

Sheet EXCA LINK BELT 2181 #.1
A1: RESUMEN GENERAL DE ACTIVIDADES EJECUTADAS
A2: CONTRATO Nº: 1040 DE 2025
A3: OBJETIVO:
A4: PERIODO DEL INFORME: | F4: AL
A5: FECHA PRESENTE ACTA:
A8: ITEM | B8: D E S C R I P C I Ó N / MAQUINA | C8: MUNICIPIO | D8: PUNTO | E8: FECHA INICIO | F8: FECHA FINAL | G8: HORAS EJECUTADAS | H8: VALOR EJECUTADO | I8: ACTIVIDAD REALIZADA
A9: 3 | B9: =+'EXCA LINK BELT #1..'!C6 -> EXCAVADORA LINK BELT 2181 #1 | C9: =+'EXCA LINK BELT #1..'!C10 -> EL CASTILLO | D9: =+'EXCA LINK BELT #1..'!D10 -> PUENTE LA AMISTAD, RIO ARIARI | E9: =+'EXCA LINK BELT #1..'!B29 -> 45779 | F9: =+'EXCA LINK BELT #1..'!C29 -> 45793 | G9: =+'EXCA LINK BELT #1..'!F30 -> 106.5 | H9: 0 | I9: =+'EXCA LINK BELT #1..'!I11 -> SE TRANSPALEA MATERIAL PARA AMPLIACIÓN DE CANAL EN EL RIO ARIARI
B10: SUBTOTAL | H10: =+H9 -> 0
B11: IVA 19% | H11: =+H10*0.19 -> 0
B12: TOTAL | H12: =+H11+H10 -> 0
B24: LUIS MIGUEL ANGEL RAMIREZ ROMERO
B25: Rep. Legal SERVICIOS MAQUINARIA Y CONSTRUCCIONES SAS "SERVIMACONS S.A.S."
B26: CONTRATISTA

Sheet EXCA LINK BELT #1..
A1: REPORTE DIARIO DE HORAS
A2: CONTRATO No.
A3: OBJETIVO:
A5: REPORTE DE MAQUINARIA
A6: MAQUINA: | C6: EXCAVADORA LINK BELT 2181 #1
A8: N° | B8: FECHA | C8: LUGAR DE TRABAJO | E8: OPERADOR | F8: HOROMETRO | H8: HORAS DE TRABAJO | I8: ACTIVIDAD REALIZADA
C9: MUNICIPIO | D9: PUNTO | F9: INICIO | G9: FIN
A10: 1 | B10: 45779 | C10: EL CASTILLO | D10: PUENTE LA AMISTAD, RIO ARIARI | E10: DUBERNEY RINCON | F10: 13540.4 | G10: 13547.9 | H10: =+G10-F10 -> 7.5 | I10: DESPLAZAMIENTO DE LA MAQUINA AL PUNTO DE TRABAJO Y SE REALIZA EXCAVACIÓN DE CANAL PARA DESVIAR CAUCE DEL RIO ARIARI
A11: 2 | B11: 45780 | C11: EL CASTILLO | D11: PUENTE LA AMISTAD, RIO ARIARI | E11: DUBERNEY RINCON | F11: =+G10 -> 13547.9 | G11: 13552.7 | H11: =+G11-F11 -> 4.8 | I11: SE TRANSPALEA MATERIAL PARA AMPLIACIÓN DE CANAL EN EL RIO ARIARI
A12: 3 | B12: 45781 | C12: EL CASTILLO | D12: PUENTE LA AMISTAD, RIO ARIARI | E12: DUBERNEY RINCON | F12: =+G11 -> 13552.7 | G12: 13563.4 | H12: =+G12-F12 -> 10.7 | I12: SE TRANSPALEA MATERIAL PARA AMPLIACIÓN DE CANAL EN EL RIO ARIARI
A13: 4 | B13: 45782 | C13: EL CASTILLO | D13: PUENTE LA AMISTAD, RIO ARIARI | E13: DUBERNEY RINCON | F13: =+G12 -> 13563.4 | G13: =+F13 -> 13563.4 | H13: =+G13-F13 -> 0 | I13: MAQUINA DISPONIBLE EN EL PUNTO, NO SE PUEDE INGRESAR AL RIO POR AUMENTO DEL CAUCE DEL RIO , SE REALIZA MANTENIMIENTO
A14: 5 | B14: 45783 | C14: EL CASTILLO | D14: PUENTE LA AMISTAD, RIO ARIARI | E14: DUBERNEY RINCON | F14: =+G13 -> 13563.4 | G14: 13581.6 | H14: =+G14-F14 -> 18.2 | I14: SE TRANSPALEA MATERIAL PARA AMPLIACIÓN DEL CANAL EN EL RIO ARIARI
A15: 6 | B15: 45784 | C15: EL CASTILLO | D15: PUENTE LA AMISTAD, RIO ARIARI | E15: DUBERNEY RINCON | F15: =+G14 -> 13581.6 | G15: 13592.7 | H15: =+G15-F15 -> 11.1 | I15: SE REALIZA EXCAVACIÓN Y SE CARGA MATERIAL A LA DUMPER
A16: 7 | B16: 45785 | C16: EL CASTILLO | D16: PUENTE LA AMISTAD, RIO ARIARI | E16: DUBERNEY RINCON | F16: =+G15 -> 13592.7 | G16: 13603.5 | H16: =+G16-F16 -> 10.8 | I16: SE REALIZA EXCAVACIÓN DE CANAL
A17: 8 | B17: 45786 | C17: EL CASTILLO | D17: PUENTE LA AMISTAD, RIO ARIARI | E17: DUBERNEY RINCON | F17: =+G16 -> 13603.5 | G17: 13613.4 | H17: =+G17-F17 -> 9.9 | I17: SE CARGA MATERIAL EN LA DUMPER, SE REALIZA EXCAVACIÓN Y CANALIZACIÓN DEL RIO
A18: 9 | B18: 45787 | C18: EL CASTILLO | D18: PUENTE LA AMISTAD, RIO ARIARI | E18: DUBERNEY RINCON | F18: =+G17 -> 13613.4 | G18: 13622 | H18: =+G18-F18 -> 8.6 | I18: SE REALIZA CANALIZACIÓN Y SE CARGA MATERIAL A LA DUMPER
A19: 10 | B19: 45788 | C19: EL CASTILLO | D19: PUENTE LA AMISTAD, RIO ARIARI | E19: DUBERNEY RINCON | F19: =+G18 -> 13622 | G19: =+F19 -> 13622 | H19: =+G19-F19 -> 0 | I19: DIA DE DESCANSO, MAQUINA DISPONIBLE EN EL PUNTO DE TRABAJO
A20: 11 | B20: 45789 | C20: EL CASTILLO | D20: PUENTE LA AMISTAD, RIO ARIARI | E20: DUBERNEY RINCON | F20: =+G19 -> 13622 | G20: 13629.4 | H20: =+G20-F20 -> 7.4 | I20: SE REALIZA EXCAVACIÓN PARA CANALIZAR YIO Y SE CARGA MATERIAL EN LA DUMPER
A21: 12 | B21: 45790 | C21: EL CASTILLO | D21: PUENTE LA AMISTAD, RIO ARIARI | E21: DUBERNEY RINCON | F21: =+G20 -> 13629.4 | G21: =+F21 -> 13629.4 | H21: =+G21-F21 -> 0 | I21: MAQUINA DISPONIBLE EN EL PUNTO DE TRABAJO, SE PRESENTA AUMENTO DEL C AUCE DEL RIO
A22: 13 | B22: 45791 | C22: EL CASTILLO | D22: PUENTE LA AMISTAD, RIO ARIARI | E22: DUBERNEY RINCON | F22: =+G21 -> 13629.4 | G22: 13636.2 | H22: =+G22-F22 -> 6.8 | I22: CANALIZACIÓN PARA DESVIAR EL CAUCE DEL RIO
A23: 14 | B23: 45792 | C23: EL CASTILLO | D23: PUENTE LA AMISTAD, RIO ARIARI | E23: DUBERNEY RINCON | F23: =+G22 -> 13636.2 | G23: =+F23 -> 13636.2 | H23: =+G23-F23 -> 0 | I23: MAQUINA DISPONIBLE EN EL PUNTO DE TRABAJO, EN ESPERA QUE DISLINUYA RL CAUCE DEL RIO
A24: 15 | B24: 45793 | C24: EL CASTILLO | D24: PUENTE LA AMISTAD, RIO ARIARI | E24: DUBERNEY RINCON | F24: =+G23 -> 13636.2 | G24: 13646.9 | H24: =+G24-F24 -> 10.7 | I24: SE REALIZA EXCAVACIÓN PARA CONSTRUCCIÓN DE JARILLON
G25: TOTAL | H25: =SUM(H10:H24) -> 106.5
B28: Inicio | C28: Fin | D28: Horometro inicio | E28: Horometro fin | F28: Total
B29: =+SMALL(B10:B24,1) -> 45779 | C29: =LARGE(B10:B24,1) -> 45793 | D29: =SMALL(F10:F24,1) -> 13540.4 | E29: =LARGE(G10:G24,1) -> 13646.9 | F29: =+E29-D29 -> 106.5
E30: TOTAL | F30: =SUM(F29) -> 106.5
B36: LUIS MIGUEL ANGEL RAMIREZ ROMERO | G36: CARMEN LUCIA AGUILAR GOMEZ
B37: Rep. Legal SERVICIOS MAQUINARIA Y CONSTRUCCIONES SAS "SERVIMACONS S.A.S." | G37: SERVICIOS MAQUINARIA Y CONSTRUCCIONES SAS "SERVIMACONS S.A.S."
B39: REPRESENTANTE LEGAL | G39: DIRECTORA

Sheet EXCA LINK BELT 2180.. #5
A1: RESUMEN GENERAL DE ACTIVIDADES EJECUTADAS
A2: CONTRATO Nº: 1040 DE 2025
A3: OBJETIVO:
A4: PERIODO DEL INFORME: | F4: AL
A5: FECHA PRESENTE ACTA:
A8: ITEM | B8: D E S C R I P C I Ó N / MAQUINA | C8: MUNICIPIO | D8: PUNTO | E8: FECHA INICIO | F8: FECHA FINAL | G8: HORAS EJECUTADAS | H8: VALOR EJECUTADO | I8: ACTIVIDAD REALIZADA
A9: 3 | B9: =+'EXCA LINK BELT #5..'!C6 -> EXCAVADORA LINK BELT 2180 #5 | C9: =+'EXCA LINK BELT #5..'!C10 -> EL CASTILLO | D9: =+'EXCA LINK BELT #5..'!D10 -> PUENTE LA AMISTAD, RIO ARIARI | E9: =+'EXCA LINK BELT #5..'!B33 -> 45784 | F9: =+'EXCA LINK BELT #5..'!C33 -> 45802 | G9: =+'EXCA LINK BELT #5..'!F34 -> 107.8 | H9: 0 | I9: =+'EXCA LINK BELT #5..'!I11 -> SE REALIZA LA CONSTRUCCIÓN DEL CANAL PARA DESVIO DEL CAUCE DEL RIO
B10: SUBTOTAL | H10: =+H9 -> 0
B11: IVA 19% | H11: =+H10*0.19 -> 0
B12: TOTAL | H12: =+H11+H10 -> 0
B24: LUIS MIGUEL ANGEL RAMIREZ ROMERO
B25: Rep. Legal SERVICIOS MAQUINARIA Y CONSTRUCCIONES SAS "SERVIMACONS S.A.S."
B26: CONTRATISTA

Sheet EXCA LINK BELT #5..
A1: REPORTE DIARIO DE HORAS
A2: CONTRATO No.
A3: OBJETIVO:
A5: REPORTE DE MAQUINARIA
A6: MAQUINA: | C6: EXCAVADORA LINK BELT 2180 #5
A8: N° | B8: FECHA | C8: LUGAR DE TRABAJO | E8: OPERADOR | F8: HOROMETRO | H8: HORAS DE TRABAJO | I8: ACTIVIDAD REALIZADA
C9: MUNICIPIO | D9: PUNTO | F9: INICIO | G9: FIN
A10: 1 | B10: 45784 | C10: EL CASTILLO | D10: PUENTE LA AMISTAD, RIO ARIARI | E10: WILLIAM GARAVITO | F10: 12467.9 | G10: 12475.9 | H10: =+G10-F10 -> 8 | I10: DESPLAZAMIENTO DE LA MAQUINA HASTA EL PUNTO DE TRABAJO Y SE INICIA RECOLECCIÓN DE PIEDRA PARA LA CONSTRUCCIÓN DEL ENROCADO DEL JARILLON
A11: 2 | B11: 45785 | C11: EL CASTILLO | D11: PUENTE LA AMISTAD, RIO ARIARI | E11: WILLIAM GARAVITO | F11: =+G10 -> 12475.9 | G11: 12484.9 | H11: =+G11-F11 -> 9 | I11: SE REALIZA LA CONSTRUCCIÓN DEL CANAL PARA DESVIO DEL CAUCE DEL RIO
A12: 3 | B12: 45786 | C12: EL CASTILLO | D12: PUENTE LA AMISTAD, RIO ARIARI | E12: WILLIAM GARAVITO | F12: =+G11 -> 12484.9 | G12: 12495.2 | H12: =+G12-F12 -> 10.3 | I12: SE REALIZA CANALIZACIÓN Y SE CONSTRUYE JARILLON DE PROTECCIÓN PARA LA MARGEN DERECHA AGUAS ABAJO
A13: 4 | B13: 45787 | C13: EL CASTILLO | D13: PUENTE LA AMISTAD, RIO ARIARI | E13: WILLIAM GARAVITO | F13: =+G12 -> 12495.2 | G13: 12500.8 | H13: =+G13-F13 -> 5.6 | I13: SE REALIZA LA CONSTRUCCIÓN DEL CANAL Y CONSTRUCCIÓN DEL JARILLON PARA PROTECCIÓN DE LA MARGEN DERECHA AGUAS ABAJO
A14: 5 | B14: 45788 | C14: EL CASTILLO | D14: PUENTE LA AMISTAD, RIO ARIARI | E14: WILLIAM GARAVITO | F14: =+G13 -> 12500.8 | G14: =+F14 -> 12500.8 | H14: =+G14-F14 -> 0 | I14: DIA DE DESCANSO, MAQUINA DISPONIBLE EN EL PUNTO DE TRABAJO
A15: 6 | B15: 45789 | C15: EL CASTILLO | D15: PUENTE LA AMISTAD, RIO ARIARI | E15: WILLIAM GARAVITO | F15: =+G14 -> 12500.8 | G15: 12510.3 | H15: =+G15-F15 -> 9.5 | I15: SE REALIZA LA CONSTRUCCIÓN DEL CANAL Y CONSTRUCCIÓN DE JARILLON DE PROTECCIÓN EN LA MARGEN DERECHA AGUAS
A16: 7 | B16: 45790 | C16: EL CASTILLO | D16: PUENTE LA AMISTAD, RIO ARIARI | E16: WILLIAM GARAVITO | F16: =+G15 -> 12510.3 | G16: =+F16 -> 12510.3 | H16: =+G16-F16 -> 0 | I16: MAQUINA DISPONIBLE EN EL PUNTO DE TRABAJO, SE PRESENTA UN AUMENTO EN EL CAUCE DEL RIO
A17: 8 | B17: 45791 | C17: EL CASTILLO | D17: PUENTE LA AMISTAD, RIO ARIARI | E17: WILLIAM GARAVITO | F17: =+G16 -> 12510.3 | G17: 12516.3 | H17: =+G17-F17 -> 6 | I17: COONSTRUCCIÓN DE CANAL Y CANALIZACIÓN PARA PROTECCIÓN DE LA MARGEN DERECHA AGUAS ABAJO
A18: 9 | B18: 45792 | C18: EL CASTILLO | D18: PUENTE LA AMISTAD, RIO ARIARI | E18: WILLIAM GARAVITO | F18: =+G17 -> 12516.3 | G18: =+F18 -> 12516.3 | H18: =+G18-F18 -> 0 | I18: MAQUINA DISPONIBLE EN EL PUNTO DE TRABAJO, SE PRESENTA UN AUMENTO EN EL CAUCE DEL RIO
A19: 10 | B19: 45793 | C19: EL CASTILLO | D19: PUENTE LA AMISTAD, RIO ARIARI | E19: WILLIAM GARAVITO | F19: =+G18 -> 12516.3 | G19: =+F19 -> 12516.3 | H19: =+G19-F19 -> 0 | I19: MAQUINA DISPONIBLE EN EL PUNTO DE TRABAJO
A20: 11 | B20: 45794 | C20: EL CASTILLO | D20: PUENTE LA AMISTAD, RIO ARIARI | E20: WILLIAM GARAVITO | F20: =+G19 -> 12516.3 | G20: 12526.3 | H20: =+G20-F20 -> 10 | I20: SE REALIZA CANALIZACIÓN Y SE RERALIZA CONSTRUCCIÓN DE JARILLON
A21: 12 | B21: 45795 | C21: EL CASTILLO | D21: PUENTE LA AMISTAD, RIO ARIARI | E21: WILLIAM GARAVITO | F21: =+G20 -> 12526.3 | G21: 12537 | H21: =+G21-F21 -> 10.7 | I21: CONSTRUCCIÓN DE CANAL Y DE JARILLON PARA PROTECCIÓN DE LA MARGEN DERECHA AGUAS ABAJO
A22: 13 | B22: 45796 | C22: EL CASTILLO | D22: PUENTE LA AMISTAD, RIO ARIARI | E22: WILLIAM GARAVITO | F22: =+G21 -> 12537 | G22: =+F22 -> 12537 | H22: =+G22-F22 -> 0 | I22: MAQUINA VARADA EN EL PUNTO DE TRABAJO
A23: 14 | B23: 45797 | C23: EL CASTILLO | D23: PUENTE LA AMISTAD, RIO ARIARI | E23: WILLIAM GARAVITO | F23: =+G22 -> 12537 | G23: 12547.5 | H23: =+G23-F23 -> 10.5 | I23: CONSTRUCCIÓN DE CANAL Y JARILLON DE PROTECCIÓN EN LA MARGEN DERECHA AGUAS ABAJO
A24: 15 | B24: 45798 | C24: EL CASTILLO | D24: PUENTE LA AMISTAD, RIO ARIARI | E24: WILLIAM GARAVITO | F24: =+G23 -> 12547.5 | G24: 12557.5 | H24: =+G24-F24 -> 10 | I24: CONSTRUCCIÓN DE JARILLON Y CANALIZACÓN PARA PROTEGER LA MARGEN DERECHA AGUAS ABAJO
A25: 16 | B25: 45799 | C25: EL CASTILLO | D25: PUENTE LA AMISTAD, RIO ARIARI | E25: WILLIAM GARAVITO | F25: =+G24 -> 12557.5 | G25: 12567.5 | H25: =+G25-F25 -> 10 | I25: CONSTRUCCIÓN DE CANAL Y CONSTRUCCIÓN DE JARILLON PARA PROTECCIÓN DE LA MARGEN IZQUIERDA
A26: 17 | B26: 45800 | C26: EL CASTILLO | D26: PUENTE LA AMISTAD, RIO ARIARI | E26: WILLIAM GARAVITO | F26: =+G25 -> 12567.5 | G26: 12575 | H26: =+G26-F26 -> 7.5 | I26: CONSTRUCCIÓN DE CANAL Y JARILLON DE PROTECCIÓN EN LA MARGEN DERECHA AGUAS ABAJO
A27: 18 | B27: 45801 | C27: EL CASTILLO | D27: PUENTE LA AMISTAD, RIO ARIARI | E27: WILLIAM GARAVITO | F27: =+G26 -> 12575 | G27: =+F27 -> 12575 | H27: =+G27-F27 -> 0 | I27: MAQUINA DISPONIBLE EN EL PUNTO DE TRABAJO
A28: 19 | B28: 45802 | C28: EL CASTILLO | D28: PUENTE LA AMISTAD, RIO ARIARI | E28: WILLIAM GARAVITO | F28: =+G27 -> 12575 | G28: 12575.7 | H28: =+G28-F28 -> 0.7 | I28: DESPLAZAMIENTO DE LA MAQUINA HASTA EL PATIO GALICIA SERVIAMCONS
G29: TOTAL | H29: =SUM(H10:H28) -> 107.8
B32: Inicio | C32: Fin | D32: Horometro inicio | E32: Horometro fin | F32: Total
B33: =+SMALL(B10:B28,1) -> 45784 | C33: =LARGE(B10:B28,1) -> 45802 | D33: =SMALL(F10:F28,1) -> 12467.9 | E33: =LARGE(G10:G28,1) -> 12575.7 | F33: =+E33-D33 -> 107.8
E34: TOTAL | F34: =SUM(F33) -> 107.8
B40: LUIS MIGUEL ANGEL RAMIREZ ROMERO | G40: CARMEN LUCIA AGUILAR GOMEZ
B41: Rep. Legal SERVICIOS MAQUINARIA Y CONSTRUCCIONES SAS "SERVIMACONS S.A.S." | G41: SERVICIOS MAQUINARIA Y CONSTRUCCIONES SAS "SERVIMACONS S.A.S."
B43: REPRESENTANTE LEGAL | G43: DIRECTORA

Sheet EXCA LINK BELT 2179 #4.
A1: RESUMEN GENERAL DE ACTIVIDADES EJECUTADAS
A2: CONTRATO Nº: 1040 DE 2025
A3: OBJETIVO:
A4: PERIODO DEL INFORME: | F4: AL
A5: FECHA PRESENTE ACTA:
A8: ITEM | B8: D E S C R I P C I Ó N / MAQUINA | C8: MUNICIPIO | D8: PUNTO | E8: FECHA INICIO | F8: FECHA FINAL | G8: HORAS EJECUTADAS | H8: VALOR EJECUTADO | I8: ACTIVIDAD REALIZADA
A9: 3 | B9: =+'EXCA LINK BELT #4.'!C6 -> EXCAVADORA LINK BELT 2179 #4 | C9: =+'EXCA LINK BELT #4.'!C10 -> EL CASTILLO | D9: =+'EXCA LINK BELT #4.'!D10 -> PUENTE LA AMISTAD, RIO ARIARI | E9: =+'EXCA LINK BELT #4.'!B35 -> 45784 | F9: =+'EXCA LINK BELT #4.'!C35 -> 45804 | G9: =+'EXCA LINK BELT #4.'!F36 -> 8.7 | H9: 0 | I9: =+'EXCA LINK BELT #4.'!I11 -> SE REALIZA LA CONSTRUCCIÓN DEL CANAL PARA DESVIO DEL CAUCE DEL RIO
B10: SUBTOTAL | H10: =+H9 -> 0
B11: IVA 19% | H11: =+H10*0.19 -> 0
B12: TOTAL | H12: =+H11+H10 -> 0
B24: LUIS MIGUEL ANGEL RAMIREZ ROMERO
B25: Rep. Legal SERVICIOS MAQUINARIA Y CONSTRUCCIONES SAS "SERVIMACONS S.A.S."
B26: CONTRATISTA

Sheet EXCA LINK BELT #4.
A1: REPORTE DIARIO DE HORAS
A2: CONTRATO No.
A3: OBJETIVO:
A5: REPORTE DE MAQUINARIA
A6: MAQUINA: | C6: EXCAVADORA LINK BELT 2179 #4
A8: N° | B8: FECHA | C8: LUGAR DE TRABAJO | E8: OPERADOR | F8: HOROMETRO | H8: HORAS DE TRABAJO | I8: ACTIVIDAD REALIZADA
C9: MUNICIPIO | D9: PUNTO | F9: INICIO | G9: FIN
A10: 1 | B10: 45784 | C10: EL CASTILLO | D10: PUENTE LA AMISTAD, RIO ARIARI | E10: JHONAL VAQUIRO | F10: 13792 | G10: 13794.5 | H10: =+G10-F10 -> 2.5 | I10: DESPLAZAMIENTO DE LA MAQUINA AL PUNTO DE TRABAJO Y SE INICIA RECOLECCIÓN DE PIEDRA PARA HACER ENROCADO
A11: 2 | B11: 45785 | C11: EL CASTILLO | D11: PUENTE LA AMISTAD, RIO ARIARI | E11: JHONAL VAQUIRO | F11: =+G10 -> 13794.5 | G11: 13800.1 | H11: =+G11-F11 -> 5.6 | I11: SE REALIZA LA CONSTRUCCIÓN DEL CANAL PARA DESVIO DEL CAUCE DEL RIO
A12: 3 | B12: 45786 | C12: EL CASTILLO | D12: PUENTE LA AMISTAD, RIO ARIARI | E12: JHONAL VAQUIRO | F12: =+G11 -> 13800.1 | G12: =+F12 -> 13800.1 | H12: =+G12-F12 -> 0 | I12: MAQUINA VARADA EN EL PUNTO DE TRABAJO
A13: 4 | B13: 45787 | C13: EL CASTILLO | D13: PUENTE LA AMISTAD, RIO ARIARI | E13: JHONAL VAQUIRO | F13: =+G12 -> 13800.1 | G13: =+F13 -> 13800.1 | H13: =+G13-F13 -> 0 | I13: MAQUINA DISPONIBLE EN EL PUNTO DE TRABAJO
A14: 5 | B14: 45788 | C14: EL CASTILLO | D14: PUENTE LA AMISTAD, RIO ARIARI | E14: JHONAL VAQUIRO | F14: =+G13 -> 13800.1 | G14: =+F14 -> 13800.1 | H14: =+G14-F14 -> 0 | I14: MAQUINA DISPONIBLE EN EL PUNTO DE TRABAJO
A15: 6 | B15: 45789 | C15: EL CASTILLO | D15: PUENTE LA AMISTAD, RIO ARIARI | E15: JHONAL VAQUIRO | F15: =+G14 -> 13800.1 | G15: =+F15 -> 13800.1 | H15: =+G15-F15 -> 0 | I15: MAQUINA DISPONIBLE EN EL PUNTO DE TRABAJO
A16: 7 | B16: 45790 | C16: EL CASTILLO | D16: PUENTE LA AMISTAD, RIO ARIARI | E16: JHONAL VAQUIRO | F16: =+G15 -> 13800.1 | G16: =+F16 -> 13800.1 | H16: =+G16-F16 -> 0 | I16: MAQUINA DISPONIBLE EN EL PUNTO DE TRABAJO
A17: 8 | B17: 45791 | C17: EL CASTILLO | D17: PUENTE LA AMISTAD, RIO ARIARI | E17: JHONAL VAQUIRO | F17: =+G16 -> 13800.1 | G17: =+F17 -> 13800.1 | H17: =+G17-F17 -> 0 | I17: MAQUINA DISPONIBLE EN EL PUNTO DE TRABAJO
A18: 9 | B18: 45792 | C18: EL CASTILLO | D18: PUENTE LA AMISTAD, RIO ARIARI | E18: JHONAL VAQUIRO | F18: =+G17 -> 13800.1 | G18: =+F18 -> 13800.1 | H18: =+G18-F18 -> 0 | I18: MAQUINA DISPONIBLE EN EL PUNTO DE TRABAJO
A19: 10 | B19: 45793 | C19: EL CASTILLO | D19: PUENTE LA AMISTAD, RIO ARIARI | E19: JHONAL VAQUIRO | F19: =+G18 -> 13800.1 | G19: =+F19 -> 13800.1 | H19: =+G19-F19 -> 0 | I19: MAQUINA DISPONIBLE EN EL PUNTO DE TRABAJO
A20: 11 | B20: 45794 | C20: EL CASTILLO | D20: PUENTE LA AMISTAD, RIO ARIARI | E20: JHONAL VAQUIRO | F20: =+G19 -> 13800.1 | G20: =+F20 -> 13800.1 | H20: =+G20-F20 -> 0 | I20: MAQUINA DISPONIBLE EN EL PUNTO DE TRABAJO
A21: 12 | B21: 45795 | C21: EL CASTILLO | D21: PUENTE LA AMISTAD, RIO ARIARI | E21: JHONAL VAQUIRO | F21: =+G20 -> 13800.1 | G21: =+F21 -> 13800.1 | H21: =+G21-F21 -> 0 | I21: MAQUINA DISPONIBLE EN EL PUNTO DE TRABAJO
A22: 13 | B22: 45796 | C22: EL CASTILLO | D22: PUENTE LA AMISTAD, RIO ARIARI | E22: JHONAL VAQUIRO | F22: =+G21 -> 13800.1 | G22: =+F22 -> 13800.1 | H22: =+G22-F22 -> 0 | I22: MAQUINA DISPONIBLE EN EL PUNTO DE TRABAJO
A23: 14 | B23: 45797 | C23: EL CASTILLO | D23: PUENTE LA AMISTAD, RIO ARIARI | E23: JHONAL VAQUIRO | F23: =+G22 -> 13800.1 | G23: =+F23 -> 13800.1 | H23: =+G23-F23 -> 0 | I23: MAQUINA DISPONIBLE EN EL PUNTO DE TRABAJO
... A29: 20 | B29: 45803 | C29: EL CASTILLO | D29: PUENTE LA AMISTAD, RIO ARIARI | E29: JHONAL VAQUIRO | F29: =+G28 -> 13800.1 | G29: =+F29 -> 13800.1 | H29: =+G29-F29 -> 0 | I29: MAQUINA DISPONIBLE EN EL PUNTO DE TRABAJO
A30: 21 | B30: 45804 | C30: EL CASTILLO | D30: PUENTE LA AMISTAD, RIO ARIARI | E30: JHONAL VAQUIRO | F30: =+G29 -> 13800.1 | G30: 13800.7 | H30: =+G30-F30 -> 0.6 | I30: DESPLAZAMIENTO DE LA MAQUINA HASTA EL PATIO GALICIA SERVIAMCONS
G31: TOTAL | H31: =SUM(H10:H30) -> 8.7
B34: Inicio | C34: Fin | D34: Horometro inicio | E34: Horometro fin | F34: Total
B35: =+SMALL(B10:B30,1) -> 45784 | C35: =LARGE(B10:B30,1) -> 45804 | D35: =SMALL(F10:F30,1) -> 13792 | E35: =LARGE(G10:G30,1) -> 13800.7 | F35: =+E35-D35 -> 8.7
E36: TOTAL | F36: =SUM(F35) -> 8.7
B42: LUIS MIGUEL ANGEL RAMIREZ ROMERO | G42: CARMEN LUCIA AGUILAR GOMEZ
B43: Rep. Legal SERVICIOS MAQUINARIA Y CONSTRUCCIONES SAS "SERVIMACONS S.A.S." | G43: SERVICIOS MAQUINARIA Y CONSTRUCCIONES SAS "SERVIMACONS S.A.S."
B45: REPRESENTANTE LEGAL | G45: DIRECTORA

Sheet EL CASTILLO - PUERTO ESPERANZA 
H9: 0

Sheet EXCA LINK BELT 2181. #1
A1: RESUMEN GENERAL DE ACTIVIDADES EJECUTADAS
A2: CONTRATO Nº: 1040 DE 2025
A3: OBJETIVO:
A4: PERIODO DEL INFORME: | F4: AL
A5: FECHA PRESENTE ACTA:
A8: ITEM | B8: D E S C R I P C I Ó N / MAQUINA | C8: MUNICIPIO | D8: PUNTO | E8: FECHA INICIO | F8: FECHA FINAL | G8: HORAS EJECUTADAS | H8: VALOR EJECUTADO | I8: ACTIVIDAD REALIZADA
A9: 3 | B9: =+'EXCA LINK BELT #1.'!C6 -> EXCAVADORA LINK BELT 2181 #1 | C9: =+'EXCA LINK BELT #1.'!C10 -> EL CASTILLO | D9: =+'EXCA LINK BELT #1.'!D10 -> PUERTO ESPERANZA, RIO LA CAL | E9: =+'EXCA LINK BELT #1.'!B28 -> 45794 | F9: =+'EXCA LINK BELT #1.'!C28 -> 45807 | G9: =+'EXCA LINK BELT #1.'!F29 -> 117 | H9: 0 | I9: =+'EXCA LINK BELT #1.'!I11 -> EXCAVACIÓN PARA CANAL Y SE CONFORMA JARILLON DE PROTECCIÓN
B10: SUBTOTAL | H10: =+H9 -> 0
B11: IVA 19% | H11: =+H10*0.19 -> 0
B12: TOTAL | H12: =+H11+H10 -> 0
B24: LUIS MIGUEL ANGEL RAMIREZ ROMERO
B25: Rep. Legal SERVICIOS MAQUINARIA Y CONSTRUCCIONES SAS "SERVIMACONS S.A.S."
B26: CONTRATISTA

Sheet EXCA LINK BELT #1.
A1: REPORTE DIARIO DE HORAS
A2: CONTRATO No.
A3: OBJETIVO:
A5: REPORTE DE MAQUINARIA
A6: MAQUINA: | C6: EXCAVADORA LINK BELT 2181 #1
A8: N° | B8: FECHA | C8: LUGAR DE TRABAJO | E8: OPERADOR | F8: HOROMETRO | H8: HORAS DE TRABAJO | I8: ACTIVIDAD REALIZADA
C9: MUNICIPIO | D9: PUNTO | F9: INICIO | G9: FIN
A10: 1 | B10: 45794 | C10: EL CASTILLO | D10: PUERTO ESPERANZA, RIO LA CAL | E10: DUBERNEY RINCON | F10: 13646.9 | G10: 13648.9 | H10: =+G10-F10 -> 2 | I10: DESPLAZAMIENTO DE LA MAQUINA HASTA EL PUNTO DE TRABAJO A INTERVENIR
A11: 2 | B11: 45795 | C11: EL CASTILLO | D11: PUERTO ESPERANZA, RIO LA CAL | E11: DUBERNEY RINCON | F11: =+G10 -> 13648.9 | G11: 13659.1 | H11: =+G11-F11 -> 10.2 | I11: EXCAVACIÓN PARA CANAL Y SE CONFORMA JARILLON DE PROTECCIÓN
A12: 3 | B12: 45796 | C12: EL CASTILLO | D12: PUERTO ESPERANZA, RIO LA CAL | E12: DUBERNEY RINCON | F12: =+G11 -> 13659.1 | G12: 13668.6 | H12: =+G12-F12 -> 9.5 | I12: SE REALIZA EXCAVACIÓN DE CANAL Y TRASPALEO DE MATERIAL
A13: 4 | B13: 45797 | C13: EL CASTILLO | D13: PUERTO ESPERANZA, RIO LA CAL | E13: DUBERNEY RINCON | F13: =+G12 -> 13668.6 | G13: 13679 | H13: =+G13-F13 -> 10.4 | I13: SE REALIZA EXCAVACIÓN DE CANAL Y TRASPALEO DE MATERIAL
A14: 5 | B14: 45798 | C14: EL CASTILLO | D14: PUERTO ESPERANZA, RIO LA CAL | E14: DUBERNEY RINCON | F14: =+G13 -> 13679 | G14: 13688.7 | H14: =+G14-F14 -> 9.7 | I14: TRASPALEO DE MATERIAL Y SE REFUERZA EL JARILLON DE PROTECCIÓN
A15: 6 | B15: 45799 | C15: EL CASTILLO | D15: PUERTO ESPERANZA, RIO LA CAL | E15: DUBERNEY RINCON | F15: =+G14 -> 13688.7 | G15: 13693.1 | H15: =+G15-F15 -> 4.4 | I15: EXCAVACIÓN DE CANAL PARA DESVIAR EL CAUCE DEL RIO, SE PRESENTA UN AUMENTO DEL CAUCE DEL RIO Y NO S EPUEDE COPNTINUAR TRABAJANNDO
A16: 7 | B16: 45800 | C16: EL CASTILLO | D16: PUERTO ESPERANZA, RIO LA CAL | E16: DUBERNEY RINCON | F16: =+G15 -> 13693.1 | G16: 13704.8 | H16: =+G16-F16 -> 11.7 | I16: EXCAVACIÓN DE CANAL PARA DESVIAR EL CAUCE DEL RIO
A17: 8 | B17: 45801 | C17: EL CASTILLO | D17: PUERTO ESPERANZA, RIO LA CAL | E17: DUBERNEY RINCON | F17: =+G16 -> 13704.8 | G17: 13714 | H17: =+G17-F17 -> 9.2 | I17: SE REALIZA REFUERZO, SE DESPLAZA LA MAQUINA A UN PUNTO MAS ABAJO Y SE INICIA EXCAVACIÓN DE CANAL
A18: 9 | B18: 45802 | C18: EL CASTILLO | D18: PUERTO ESPERANZA, RIO LA CAL | E18: DUBERNEY RINCON | F18: =+G17 -> 13714 | G18: 13722.6 | H18: =+G18-F18 -> 8.6 | I18: EXCAVACIÓN DE CANAL PARA DESVIAR EL CAUCE DEL RIO
A19: 10 | B19: 45803 | C19: EL CASTILLO | D19: PUERTO ESPERANZA, RIO LA CAL | E19: DUBERNEY RINCON | F19: =+G18 -> 13722.6 | G19: =+F19 -> 13722.6 | H19: =+G19-F19 -> 0 | I19: MAQUINA EN REPARACIONES DEL BALDE EN EL PUNTO DE TRABAJO
A20: 11 | B20: 45804 | C20: EL CASTILLO | D20: PUERTO ESPERANZA, RIO LA CAL | E20: DUBERNEY RINCON | F20: =+G19 -> 13722.6 | G20: 13735.5 | H20: =+G20-F20 -> 12.9 | I20: EXCAVACIÓN DE CANAL PARA DESVIAR EL CAUCE DEL RIO | J20: MENOS 1,6 PARA NOMINA
A21: 12 | B21: 45805 | C21: EL CASTILLO | D21: PUERTO ESPERANZA, RIO LA CAL | E21: DUBERNEY RINCON | F21: =+G20 -> 13735.5 | G21: 13746.8 | H21: =+G21-F21 -> 11.3 | I21: EXCAVACIÓN DE CANAL PARA DESVIAR EL CAUCE DEL RIO
A22: 13 | B22: 45806 | C22: EL CASTILLO | D22: PUERTO ESPERANZA, RIO LA CAL | E22: DUBERNEY RINCON | F22: =+G21 -> 13746.8 | G22: 13758.8 | H22: =+G22-F22 -> 12 | I22: SE TERMINA EL REFUERZO DEL JARILLON Y SE AMPLIA CANAL
A23: 14 | B23: 45807 | C23: EL CASTILLO | D23: PUERTO ESPERANZA, RIO LA CAL | E23: DUBERNEY RINCON | F23: =+G22 -> 13758.8 | G23: =+F23+5.1 -> 13763.9 | H23: =+G23-F23 -> 5.1 | I23: SE FINALIZA REFUERZO DEL JARILLON, SE REALIZA DESPLAZAMIENTO DE LA MAQUINA AL PUNTO DE EMBARQUE
G24: TOTAL | H24: =SUM(H10:H23) -> 117
B27: Inicio | C27: Fin | D27: Horometro inicio | E27: Horometro fin | F27: Total
B28: =+SMALL(B10:B23,1) -> 45794 | C28: =LARGE(B10:B23,1) -> 45807 | D28: =SMALL(F10:F23,1) -> 13646.9 | E28: =LARGE(G10:G23,1) -> 13763.9 | F28: =+E28-D28 -> 117
E29: TOTAL | F29: =SUM(F28) -> 117
B35: LUIS MIGUEL ANGEL RAMIREZ ROMERO | G35: CARMEN LUCIA AGUILAR GOMEZ
B36: Rep. Legal SERVICIOS MAQUINARIA Y CONSTRUCCIONES SAS "SERVIMACONS S.A.S." | G36: SERVICIOS MAQUINARIA Y CONSTRUCCIONES SAS "SERVIMACONS S.A.S."
B38: REPRESENTANTE LEGAL | G38: DIRECTORA

Sheet VOLQUETA
A1: RESUMEN GENERAL DE ACTIVIDADES EJECUTADAS
A2: CONTRATO Nº: 1040 DE 2025
A3: OBJETIVO: CONTRATO No: SERVICIO PARA LA OPERACIÓN DE LA MAQUINARIA AMARILLA ADSCRITA A LA DIRECCIÓN DEPARTAMENTAL PARA LA GESTIÓN DEL RIESGO DE DESASTRES PARA LA REDUCCIÓN DEL RIESGO EN LOS VEINTINUEVE (29) MUNICIPIOS DEL DEPARTAMENTO DEL META.
A4: PERIODO DEL INFORME: | F4: AL
A5: FECHA PRESENTE ACTA:
A8: ITEM | B8: D E S C R I P C I Ó N / MAQUINA | C8: MUNICIPIO | D8: PUNTO | E8: FECHA INICIO | F8: FECHA FINAL | G8: HORAS EJECUTADAS | H8: VALOR EJECUTADO | I8: ACTIVIDAD REALIZADA
H9: 0
B11: SUBTOTAL | H11: =+H10 -> 0
B12: IVA 19% | H12: =+H11*0.19 -> 0
B13: TOTAL | H13: =+H12+H11 -> 0
B25: LUIS MIGUEL ANGEL RAMIREZ ROMERO
B26: Rep. Legal SERVICIOS MAQUINARIA Y CONSTRUCCIONES SAS "SERVIMACONS S.A.S."
B27: CONTRATISTA

Sheet VOLQUETA COG789
A1: REPORTE DIARIO DE HORAS
A2: CONTRATO No.
A3: OBJETIVO:
A5: REPORTE DE MAQUINARIA
A6: MAQUINA: | C6: VOLQUETA COG789
A8: N° | B8: FECHA | C8: LUGAR DE TRABAJO | E8: OPERADOR | F8: HOROMETRO | H8: HORAS DE TRABAJO | I8: ACTIVIDAD REALIZADA
C9: MUNICIPIO | D9: PUNTO | F9: INICIO | G9: FIN
A10: 1 | B10: 45775 | C10: EL CALVARIO | D10: VIA MONFORTH | E10: RODRIGO BERNAL | F10: 1733.4 | G10: 1738.7 | H10: =+G10-F10 -> 5.3 | I10: DESPLAZAMIENTO DE VILLAVICENCIO PARA EL PUNTO VIA MONFORTH, SE REALIZA TRANSPORTE AL OPERADOR DE LA RETRO, YA QUE LA MAQUINA QUEDO VARADA
A11: 2 | B11: 45776 | C11: EL CALVARIO | D11: VIA MONFORTH | E11: RODRIGO BERNAL | F11: =+G10 -> 1738.7 | G11: 1748.3 | H11: =+G11-F11 -> 9.6 | I11: TRANSPORTE DE MATERIAL DE EXCAVACIÓN PARA RELLENO DEL LOTE
B37: Inicio | C37: Fin | D37: Horometro inicio | E37: Horometro fin | F37: Total
B38: =+SMALL(B10:B33,1) -> 45775 | C38: =LARGE(B10:B33,1) -> 45776 | D38: =SMALL(F10:F33,1) -> 1733.4 | E38: =LARGE(G10:G33,1) -> 1748.3 | F38: =+E38-D38 -> 14.9
E39: TOTAL | F39: =SUM(F38) -> 14.9
B45: LUIS MIGUEL ANGEL RAMIREZ ROMERO | G45: CARMEN LUCIA AGUILAR GOMEZ
B46: Rep. Legal SERVICIOS MAQUINARIA Y CONSTRUCCIONES SAS "SERVIMACONS S.A.S." | G46: SERVICIOS MAQUINARIA Y CONSTRUCCIONES SAS "SERVIMACONS S.A.S."
B48: REPRESENTANTE LEGAL | G48: DIRECTORA

Sheet 001. CONTRATO ADICIONAL
H9: 0

Sheet EL CALVARIO - SECTOR LAS BRUJAS
A1: RESUMEN GENERAL DE ACTIVIDADES EJECUTADAS
A2: CONTRATO Nº: 1040 DE 2025
A3: OBJETIVO: SERVICIO PARA LA OPERACIÓN DE LA MAQUINARIA AMARILLA ADSCRITA A LA DIRECCIÓN DEPARTAMENTAL PARA LA GESTIÓN DEL RIESGO DE DESASTRES PARA LA REDUCCIÓN DEL RIESGO EN LOS VEINTINUEVE (29) MUNICIPIOS DEL DEPARTAMENTO DEL META.
A4: PERIODO DEL INFORME: | F4: AL
A5: FECHA PRESENTE ACTA:
A8: ITEM | B8: D E S C R I P C I Ó N / MAQUINA | C8: MUNICIPIO | D8: PUNTO | E8: FECHA INICIO | F8: FECHA FINAL | G8: HORAS EJECUTADAS | H8: VALOR EJECUTADO | I8: ACTIVIDAD REALIZADA
A9: 2 | B9: =+'BULLDOZER CATERPILLAR 2765 #2.'!B9 -> BULLDOZER CATERPILLAR 2765 #2 | C9: =+'BULLDOZER CATERPILLAR 2765 #2.'!C9 -> EL CALVARIO | D9: =+'BULLDOZER CATERPILLAR 2765 #2.'!D9 -> SECTOR LAS BRUJAS | E9: =+'BULLDOZER CATERPILLAR 2765 #2.'!E9 -> 45814 | F9: =+'BULLDOZER CATERPILLAR 2765 #2.'!F9 -> 45825 | G9: =+'BULLDOZER CATERPILLAR 2765 #2.'!G9 -> 188 | H9: 0 | I9: =+'BULLDOZER CATERPILLAR 2765 #2.'!I9 -> MAQUINA DISPONIBLE EN EL PUNTO DE TRABAJO, SE PRESENTAN FUERTES LLUVIAS EN EL SECTOR
B10: SUBTOTAL | H10: =+H9 -> 0
B11: IVA 19% | H11: =+H10*0.19 -> 0
B12: TOTAL | H12: =+H11+H10 -> 0
B24: LUIS MIGUEL ANGEL RAMIREZ ROMERO
B25: Rep. Legal SERVICIOS MAQUINARIA Y CONSTRUCCIONES SAS "SERVIMACONS S.A.S."
B26: CONTRATISTA

Sheet BULLDOZER CATERPILLAR 2765 #2.
A1: RESUMEN GENERAL DE ACTIVIDADES EJECUTADAS
A2: CONTRATO Nº: 1040 DE 2025
A3: OBJETIVO:
A4: PERIODO DEL INFORME: | F4: AL
A5: FECHA PRESENTE ACTA:
A8: ITEM | B8: D E S C R I P C I Ó N / MAQUINA | C8: MUNICIPIO | D8: PUNTO | E8: FECHA INICIO | F8: FECHA FINAL | G8: HORAS EJECUTADAS | H8: VALOR EJECUTADO | I8: ACTIVIDAD REALIZADA
A9: 2 | B9: =+'BULLDOZER #2,,,'!C6 -> BULLDOZER CATERPILLAR 2765 #2 | C9: =+'BULLDOZER #2,,,'!C10 -> EL CALVARIO | D9: =+'BULLDOZER #2,,,'!D10 -> SECTOR LAS BRUJAS | E9: =+'BULLDOZER #2,,,'!B59 -> 45814 | F9: =+'BULLDOZER #2,,,'!C59 -> 45825 | G9: =+'BULLDOZER #2,,,'!F62 -> 188 | H9: 0 | I9: =+'BULLDOZER #2,,,'!I11 -> MAQUINA DISPONIBLE EN EL PUNTO DE TRABAJO, SE PRESENTAN FUERTES LLUVIAS EN EL SECTOR
B10: SUBTOTAL | H10: =+H9 -> 0
B11: IVA 19% | H11: =+H10*0.19 -> 0
B12: TOTAL | H12: =+H11+H10 -> 0
B24: LUIS MIGUEL ANGEL RAMIREZ ROMERO
B25: Rep. Legal SERVICIOS MAQUINARIA Y CONSTRUCCIONES SAS "SERVIMACONS S.A.S."
B26: CONTRATISTA

Sheet BULLDOZER #2,,,
A1: REPORTE DIARIO DE HORAS
A2: CONTRATO No.
A3: OBJETIVO:
A5: REPORTE DE MAQUINARIA
A6: MAQUINA: | C6: BULLDOZER CATERPILLAR 2765 #2
A8: N° | B8: FECHA | C8: LUGAR DE TRABAJO | E8: OPERADOR | F8: HOROMETRO | H8: HORAS DE TRABAJO | I8: ACTIVIDAD REALIZADA
C9: MUNICIPIO | D9: PUNTO | F9: INICIO | G9: FIN
A10: 1 | B10: 45814 | C10: EL CALVARIO | D10: SECTOR LAS BRUJAS | E10: EVELIO ALZATE | F10: 10430.7 | G10: 10433 | H10: =+G10-F10 -> 2.3 | I10: REHABILITACIÓN Y RECONFORMACIÓN DE VIA EL CALVARIO EN EL SECTOR LAS BRUJAS
A11: 2 | B11: 45815 | C11: EL CALVARIO | D11: SECTOR LAS BRUJAS | E11: EVELIO ALZATE | F11: =+G10 -> 10433 | G11: 10433 | H11: =+G11-F11 -> 0 | I11: MAQUINA DISPONIBLE EN EL PUNTO DE TRABAJO, SE PRESENTAN FUERTES LLUVIAS EN EL SECTOR
A12: 3 | B12: 45816 | C12: EL CALVARIO | D12: SECTOR LAS BRUJAS | E12: EVELIO ALZATE | F12: =+G11 -> 10433 | G12: 10441.5 | H12: =+G12-F12 -> 8.5 | I12: REHABILITACIÓN Y RECONFORMACIÓN DE VIA EL CALVARIO EN EL SECTOR LAS BRUJAS
A13: 4 | B13: 45817 | C13: EL CALVARIO | D13: SECTOR LAS BRUJAS | E13: EVELIO ALZATE | F13: =+G12 -> 10441.5 | G13: 10443.1 | H13: =+G13-F13 -> 1.6 | I13: REHABILITACIÓN Y RECONFORMACIÓN DE VIA EL CALVARIO EN EL SECTOR LAS BRUJAS, NO SE CONTINUA TRABAJANDO POR FUERTES LLUVIAS EN EL SECTOR
A14: 5 | B14: 45818 | C14: EL CALVARIO | D14: SECTOR LAS BRUJAS | E14: EVELIO ALZATE | F14: =+G13 -> 10443.1 | G14: 10450.5 | H14: =+G14-F14 -> 7.4 | I14: REHABILITACIÓN Y RECONFORMACIÓN DE VIA EL CALVARIO EN EL SECTOR LAS BRUJAS
A15: 6 | B15: 45819 | C15: EL CALVARIO | D15: SECTOR LAS BRUJAS | E15: EVELIO ALZATE | F15: =+G14 -> 10450.5 | G15: 10455.8 | H15: =+G15-F15 -> 5.3 | I15: REHABILITACIÓN Y RECONFORMACIÓN DE VIA EL CALVARIO EN EL SECTOR LAS BRUJAS
A16: 7 | B16: 45820 | C16: EL CALVARIO | D16: SECTOR LAS BRUJAS | E16: EVELIO ALZATE | F16: =+G15 -> 10455.8 | G16: 10457.5 | H16: =+G16-F16 -> 1.7 | I16: REHABILITACIÓN Y RECONFORMACIÓN DE VIA EL CALVARIO EN EL SECTOR LAS BRUJAS
A17: 8 | B17: 45821 | C17: EL CALVARIO | D17: SECTOR LAS BRUJAS | E17: EVELIO ALZATE | F17: =+G16 -> 10457.5 | G17: 10463 | H17: =+G17-F17 -> 5.5 | I17: REHABILITACIÓN Y RECONFORMACIÓN DE VIA EL CALVARIO EN EL SECTOR LAS BRUJAS
A18: 9 | B18: 45822 | C18: EL CALVARIO | D18: SECTOR LAS BRUJAS | E18: EVELIO ALZATE | F18: =+G17 -> 10463 | G18: 10470.6 | H18: =+G18-F18 -> 7.6 | I18: REHABILITACIÓN Y RECONFORMACIÓN DE VIA EL CALVARIO EN EL SECTOR LAS BRUJAS
A19: 10 | B19: 45823 | C19: EL CALVARIO | D19: SECTOR LAS BRUJAS | E19: EVELIO ALZATE | F19: =+G18 -> 10470.6 | G19: 10471.7 | H19: =+G19-F19 -> 1.1 | I19: REHABILITACIÓN Y RECONFORMACIÓN DE VIA EL CALVARIO EN EL SECTOR LAS BRUJAS, LA MAQUINA PRESENTA FALLAS MECANICAS Y NO SE PUEDE CONTINUAR TRABAJANDO
A20: 11 | B20: 45824 | C20: EL CALVARIO | D20: SECTOR LAS BRUJAS | E20: EVELIO ALZATE | F20: =+G19 -> 10471.7 | G20: =+F20 -> 10471.7 | H20: =+G20-F20 -> 0 | I20: MAQUINA VARADA EN EL PUNTO DE TRABAJO
A21: 12 | B21: 45825 | C21: EL CALVARIO | D21: SECTOR LAS BRUJAS | E21: EVELIO ALZATE | F21: =+G20 -> 10471.7 | G21: =+F21 -> 10471.7 | H21: =+G21-F21 -> 0 | I21: MAQUINA VARADA EN EL PUNTO DE TRABAJO
A22: 13 | B22: 45826 | C22: EL CALVARIO | D22: SECTOR LAS BRUJAS | E22: EVELIO ALZATE | F22: 10476.4 | G22: =+F22 -> 10476.4 | H22: =+G22-F22 -> 0 | I22: SE PRESENTA UN SALTO DE HOROMETRO, YA QUE 4,7 HORAS FUERON UTILIZADAS EN LA REPARACIÓN DE LA CADENA DE LA MAQUINA
